Workbook
Name AdjNetGross: #REF!
Name Attendance: #REF!
Name B: #REF!
Name calc: #REF!
Name Comps: #REF!
Name Currency: #REF!
Name d: #REF!
Name EV__LASTREFTIME__: 40416.6402546296
Name event: #REF!
Name localnetgross: #REF!
Name netcharitylocal: #REF!
Name NetGross: #REF!
Name NetTktRev: #REF!
Name PaidAttendance: #REF!
Name promoter: #REF!
Name rate: #REF!
Name scale1: #REF!
Name scale2: #REF!
Name scale3: #REF!
Name scale4: #REF!
Name scale5: #REF!
Name scale6: #REF!
Name splitamount: #REF!
Name t: #REF!
Name TaxRateDiv: #REF!
Name VCity: #REF!
Name venue: #REF!
Name With_Holding_Tax: #REF!

Sheet Summary
B11: =D49 -> Bryan Adams
B12: TOUR PROFIT OR LOSS - MERCHANDISE
B13: City | C13: =C50 -> Online | D13: =D50 -> Cape Town | E13: =E50 -> Cape Town | F13: =F50 -> Cape Town | G13: =G50 -> Pretoria | H13: =H50 -> Pretoria | I13: =I50 -> Durban | J13: =J50 -> Durban
B14: Venue | C14: =C51 -> Pre and Post Sales | D14: =D51 -> Grand Arena | E14: =E51 -> Grand Arena | F14: =F51 -> Grand Arena | G14: =G51 -> SunBet Arena | H14: =H51 -> SunBet Arena | I14: =I51 -> Durban ICC | J14: =J51 -> Durban ICC
B15: Date of Show | C15: =C52 -> 27 Mar - 1 May | D15: =D52 -> 46133 | E15: =E52 -> 46134 | F15: =F52 -> 46135 | G15: =G52 -> 46137 | H15: =H52 -> 46138 | I15: =I52 -> 46140 | J15: =J52 -> 46141
B16: Income | C16: TOTAL ZAR | D16: TOTAL ZAR | E16: TOTAL ZAR | F16: TOTAL ZAR | G16: TOTAL ZAR | H16: TOTAL ZAR | I16: TOTAL ZAR | J16: TOTAL ZAR | K16: TOTAL ZAR | L16: TOTAL GBP
B17: Gross Sales | C17: =Sales!B9 -> 0 | D17: =Sales!C9 -> 200000 | E17: =Sales!D9 -> 200000 | F17: =Sales!E9 -> 200000 | G17: =Sales!F9 -> 480000 | H17: =Sales!G9 -> 480000 | I17: =Sales!H9 -> 150000 | J17: =Sales!I9 -> 150000 | K17: =SUM(C17:J17) -> 1860000 | L17: =K17/$D$55 -> 83221.477
B18: VAT (SALES TAX 15%) | C18: =C17/(100+$D$57)*$D$57 -> 0 | D18: =D17/(100+$D$57)*$D$57 -> 26086.957 | E18: =E17/(100+$D$57)*$D$57 -> 26086.957 | F18: =F17/(100+$D$57)*$D$57 -> 26086.957 | G18: =G17/(100+$D$57)*$D$57 -> 62608.696 | H18: =H17/(100+$D$57)*$D$57 -> 62608.696 | I18: =I17/(100+$D$57)*$D$57 -> 19565.217 | J18: =J17/(100+$D$57)*$D$57 -> 19565.217 | ... L18: =L17/(100+$D$57)*$D$57 -> 10854.975
B19: Net Income | C19: =C17-C18 -> 0 | D19: =D17-D18 -> 173913.04 | E19: =E17-E18 -> 173913.04 | F19: =F17-F18 -> 173913.04 | G19: =G17-G18 -> 417391.3 | H19: =H17-H18 -> 417391.3 | I19: =I17-I18 -> 130434.78 | J19: =J17-J18 -> 130434.78 | ... L19: =L17-L18 -> 72366.501
B20: Customs Duty & Freight | C20: =('Manufacturing & Shipping'!$G$64+'Manufacturing & Shipping'!$F$70)*(C17/$K$17) -> 0 | D20: =('Manufacturing & Shipping'!$G$64+'Manufacturing & Shipping'!$F$70)*(D17/$K$17) -> 5198.1774 | E20: =('Manufacturing & Shipping'!$G$64+'Manufacturing & Shipping'!$F$70)*(E17/$K$17) -> 5198.1774 | F20: =('Manufacturing & Shipping'!$G$64+'Manufacturing & Shipping'!$F$70)*(F17/$K$17) -> 5198.1774 | G20: =('Manufacturing & Shipping'!$G$64+'Manufacturing & Shipping'!$F$70)*(G17/$K$17) -> 12475.626 | H20: =('Manufacturing & Shipping'!$G$64+'Manufacturing & Shipping'!$F$70)*(H17/$K$17) -> 12475.626 | I20: =('Manufacturing & Shipping'!$G$64+'Manufacturing & Shipping'!$F$70)*(I17/$K$17) -> 3898.6331 | J20: =('Manufacturing & Shipping'!$G$64+'Manufacturing & Shipping'!$F$70)*(J17/$K$17) -> 3898.6331 | K20: =SUM(C20:J20) -> 48343.05 | L20: =K20/$D$55 -> 2163
B21: Less: Manufacturing costs LOCAL | C21: ='Manufacturing & Shipping'!$F$35*(C17/$K$17) -> 0 | D21: ='Manufacturing & Shipping'!$F$35*(D17/$K$17) -> 52174.194 | E21: ='Manufacturing & Shipping'!$F$35*(E17/$K$17) -> 52174.194 | F21: ='Manufacturing & Shipping'!$F$35*(F17/$K$17) -> 52174.194 | G21: ='Manufacturing & Shipping'!$F$35*(G17/$K$17) -> 125218.06 | H21: ='Manufacturing & Shipping'!$F$35*(H17/$K$17) -> 125218.06 | I21: ='Manufacturing & Shipping'!$F$35*(I17/$K$17) -> 39130.645 | J21: ='Manufacturing & Shipping'!$F$35*(J17/$K$17) -> 39130.645 | K21: =SUM(C21:J21) -> 485220 | L21: =K21/$D$55 -> 21710.067
B22: Less: Manufacturing costs INT | C22: ='Manufacturing & Shipping'!$F$18*(C17/$K$17) -> 0 | D22: ='Manufacturing & Shipping'!$F$18*(D17/$K$17) -> 13659.935 | E22: ='Manufacturing & Shipping'!$F$18*(E17/$K$17) -> 13659.935 | F22: ='Manufacturing & Shipping'!$F$18*(F17/$K$17) -> 13659.935 | G22: ='Manufacturing & Shipping'!$F$18*(G17/$K$17) -> 32783.845 | H22: ='Manufacturing & Shipping'!$F$18*(H17/$K$17) -> 32783.845 | I22: ='Manufacturing & Shipping'!$F$18*(I17/$K$17) -> 10244.952 | J22: ='Manufacturing & Shipping'!$F$18*(J17/$K$17) -> 10244.952 | K22: =SUM(C22:J22) -> 127037.4 | L22: =K22/$D$55 -> 5684
B23: TOTAL COSTS OF SALES | C23: =SUM(C20:C22) -> 0 | D23: =SUM(D20:D22) -> 71032.306 | E23: =SUM(E20:E22) -> 71032.306 | F23: =SUM(F20:F22) -> 71032.306 | G23: =SUM(G20:G22) -> 170477.54 | H23: =SUM(H20:H22) -> 170477.54 | I23: =SUM(I20:I22) -> 53274.23 | J23: =SUM(J20:J22) -> 53274.23 | ... L23: =SUM(L20:L22) -> 29557.067
B24: Less: Credit card commissions (Cost of sales) | C24: =C17*$D$58% -> 0 | D24: =D17*$D$58% -> 6400 | E24: =E17*$D$58% -> 6400 | F24: =F17*$D$58% -> 6400 | G24: =G17*$D$58% -> 15360 | H24: =H17*$D$58% -> 15360 | I24: =I17*$D$58% -> 4800 | J24: =J17*$D$58% -> 4800 | K24: =SUM(C24:J24) -> 59520 | L24: =K24/$D$55 -> 2663.0872
B25: Operating income before ops costs | C25: =C19-C23-C24 -> 0 | D25: =D19-D23-D24 -> 96480.737 | E25: =E19-E23-E24 -> 96480.737 | F25: =F19-F23-F24 -> 96480.737 | G25: =G19-G23-G24 -> 231553.77 | H25: =H19-H23-H24 -> 231553.77 | I25: =I19-I23-I24 -> 72360.553 | J25: =J19-J23-J24 -> 72360.553 | ... L25: =L19-L23-L24 -> 40146.347
B26: Operating costs
B27: Accommodation | C27: 0 | D27: 3043.48 | E27: 3043.48 | F27: 6086.96 | G27: 6086.96 | H27: 0 | I27: 6086.96 | J27: 6086.96 | K27: =SUM(C27:J27) -> 30434.8 | L27: =K27/$D$55 -> 1361.736
B28: Advertising/branding & signage (including ad spend) | D28: 2000 | E28: 2000 | F28: 2000 | G28: 2000 | H28: 2000 | I28: 2000 | J28: 2000 | K28: =SUM(C28:J28) -> 14000 | L28: =K28/$D$55 -> 626.39821
B29: Airfares | C29: 0 | D29: 0 | E29: 0 | F29: 0 | G29: 0 | H29: 0 | I29: 4500 | J29: 4500 | K29: =SUM(C29:J29) -> 9000 | L29: =K29/$D$55 -> 402.68456
B30: Ground Transport | C30: 0 | D30: 1000 | E30: 1000 | F30: 1000 | G30: 2000 | H30: 2000 | I30: 950 | J30: 950 | K30: =SUM(C30:J30) -> 8900 | L30: =K30/$D$55 -> 398.21029
B31: Electrical expenses | C31: 0 | D31: 0 | E31: 0 | F31: 0 | G31: 0 | H31: 0 | I31: 0 | J31: 0 | K31: =SUM(C31:J31) -> 0 | L31: =K31/$D$55 -> 0
B32: Fencing | C32: 0 | D32: 0 | E32: 0 | F32: 0 | G32: 0 | H32: 0 | I32: 0 | J32: 0 | K32: =SUM(C32:J32) -> 0 | L32: =K32/$D$55 -> 0
B33: Meals and catering | C33: 0 | D33: 600 | E33: 600 | F33: 600 | G33: 600 | H33: 600 | I33: 600 | J33: 600 | K33: =SUM(C33:J33) -> 4200 | L33: =K33/$D$55 -> 187.91946
B34: Rentals, consumables, etc | C34: 0 | D34: 0 | E34: 0 | F34: 0 | G34: 0 | H34: 0 | I34: 0 | J34: 0 | K34: =SUM(C34:J34) -> 0 | L34: =K34/$D$55 -> 0
B35: Equipment | C35: 0 | D35: 15000 | E35: 15000 | F35: 15000 | G35: 25000 | H35: 25000 | I35: 15000 | J35: 15000 | K35: =SUM(C35:J35) -> 125000 | L35: =K35/$D$55 -> 5592.8412
B36: Security | C36: 0 | D36: 0 | E36: 0 | F36: 0 | G36: 0 | H36: 0 | I36: 1500 | J36: 1500 | K36: =SUM(C36:J36) -> 3000 | L36: =K36/$D$55 -> 134.22819
B37: Local staff / Fulfilment (Picking & Packing 6.5%) | C37: =0.065*C17 -> 0 | D37: 30760 | E37: 30760 | F37: 30760 | G37: 51000 | H37: 51000 | I37: 22200 | J37: 22200 | K37: =SUM(C37:J37) -> 238680 | L37: =K37/$D$55 -> 10679.195
B38: Telephone & internet | C38: 0 | D38: 2500 | E38: 2500 | F38: 2500 | G38: 5000 | H38: 5000 | I38: 2500 | J38: 2500 | K38: =SUM(C38:J38) -> 22500 | L38: =K38/$D$55 -> 1006.7114
B39: Trucking, storage & local shipping | C39: 0 | D39: 5000 | E39: 5000 | F39: 5000 | G39: 0 | H39: 0 | I39: 0 | J39: 0 | K39: =SUM(C39:J39) -> 15000 | L39: =K39/$D$55 -> 671.14094
B40: Service fee | C40: 0 | D40: 0 | E40: 0 | F40: 0 | G40: 0 | H40: 0 | I40: 0 | J40: 0 | K40: =SUM(C40:J40) -> 0 | L40: =K40/$D$55 -> 0
B41: Total Operating costs | C41: =SUM(C27:C40) -> 0 | D41: =SUM(D27:D40) -> 59903.48 | E41: =SUM(E27:E40) -> 59903.48 | F41: =SUM(F27:F40) -> 62946.96 | G41: =SUM(G27:G40) -> 91686.96 | H41: =SUM(H27:H40) -> 85600 | I41: =SUM(I27:I40) -> 55336.96 | J41: =SUM(J27:J40) -> 55336.96 | ... L41: =SUM(L27:L40) -> 21061.065
B42: TOTAL PROFIT | C42: =C25-C41 -> 0 | D42: =D25-D41 -> 36577.257 | E42: =E25-E41 -> 36577.257 | F42: =F25-F41 -> 33533.777 | G42: =G25-G41 -> 139866.81 | H42: =H25-H41 -> 145953.77 | I42: =I25-I41 -> 17023.593 | J42: =J25-J41 -> 17023.593 | ... L42: =L25-L41 -> 19085.282
B43: TOTAL PROFIT - ARTIST | C43: =C42*$D$59% -> 0 | D43: =D42*$D$59% -> 25604.08 | E43: =E42*$D$59% -> 25604.08 | F43: =F42*$D$59% -> 23473.644 | G43: =G42*$D$59% -> 97906.766 | H43: =H42*$D$59% -> 102167.64 | I43: =I42*$D$59% -> 11916.515 | J43: =J42*$D$59% -> 11916.515 | K43: =SUM(C43:J43) -> 298589.24 | L43: =L42*D59% -> 13359.697
B44: TOTAL PROFIT - PROMOTER | C44: =C42-C43 -> 0 | D44: =D42-D43 -> 10973.177 | E44: =E42-E43 -> 10973.177 | F44: =F42-F43 -> 10060.133 | G44: =G42-G43 -> 41960.043 | H44: =H42-H43 -> 43786.131 | I44: =I42-I43 -> 5107.0778 | J44: =J42-J43 -> 5107.0778 | K44: =SUM(C44:J44) -> 127966.82 | L44: =L42-L43 -> 5725.5846
B46: Breakeven% | D46: =(K41+K23+K24)/K19 -> 0.73626911
B49: PROJECT | D49: Bryan Adams
B50: CITY | C50: Online | D50: Cape Town | E50: Cape Town | F50: Cape Town | G50: Pretoria | H50: Pretoria | I50: Durban | J50: Durban
B51: VENUE | C51: Pre and Post Sales | D51: Grand Arena | E51: Grand Arena | F51: Grand Arena | G51: SunBet Arena | H51: SunBet Arena | I51: Durban ICC | J51: Durban ICC
B52: DATE OF SHOW | C52: 27 Mar - 1 May | D52: 46133 | E52: 46134 | F52: 46135 | G52: 46137 | H52: 46138 | I52: 46140 | J52: 46141 | K52: TOTAL SHOWS
B53: NUMBER OF SHOWS | D53: 1 | E53: 1 | F53: 1 | G53: 1 | H53: 1 | I53: 1 | J53: 1 | K53: =SUM(D53:J53) -> 7
B54: FOREX CURRENCY | D54: GBP
B55: EXCHANGE RATE | D55: 22.35
B56: BREAKEVEN PERCENTAGE | D56: =D46 -> 0.73626911
B57: VAT RATE | D57: 15
B58: CARD FEES % | D58: 3.2
B59: ARTIST % SPLIT | D59: 70
B60: PROMOTER % SPLIT | D60: 30

Sheet Sales
A1: TOUR SALES REPORT | P1: TOTAL AVERAGE SPEND PER HEAD PROJECTION | Q1: TOTAL PAID ATTENDANCE | R1: GROSS TARGET
A2: TOUR SALES REPORT | P2: =R2/Q2 -> 43.255814 | Q2: =J7-B7 -> 43000 | R2: =J9 -> 1860000
A3: ARTIST | B3: =Summary!D49 -> Bryan Adams | C3: =Summary!D49 -> Bryan Adams | D3: =C3 -> Bryan Adams | E3: =D3 -> Bryan Adams | F3: =E3 -> Bryan Adams | G3: =F3 -> Bryan Adams | H3: =G3 -> Bryan Adams | I3: =H3 -> Bryan Adams | J3: TOTAL
A4: REGION | B4: =Summary!C50 -> Online | C4: =Summary!D50 -> Cape Town | D4: =Summary!E50 -> Cape Town | E4: =Summary!F50 -> Cape Town | F4: =Summary!G50 -> Pretoria | G4: =Summary!H50 -> Pretoria | H4: =Summary!I50 -> Durban | I4: =Summary!J50 -> Durban
A5: VENUE | B5: =Summary!C51 -> Pre and Post Sales | C5: =Summary!D51 -> Grand Arena | D5: =Summary!E51 -> Grand Arena | E5: =Summary!F51 -> Grand Arena | F5: =Summary!G51 -> SunBet Arena | G5: =Summary!H51 -> SunBet Arena | H5: =Summary!I51 -> Durban ICC | I5: =Summary!J51 -> Durban ICC
A6: DATE | B6: =Summary!C52 -> 27 Mar - 1 May | C6: =Summary!D52 -> 46133 | D6: =Summary!E52 -> 46134 | E6: =Summary!F52 -> 46135 | F6: =Summary!G52 -> 46137 | G6: =Summary!H52 -> 46138 | H6: =Summary!I52 -> 46140 | I6: =Summary!J52 -> 46141
A7: CAPACITY/(total transactions) | C7: 5000 | D7: 5000 | E7: 5000 | F7: 8000 | G7: 8000 | H7: 6000 | I7: 6000 | J7: =SUM(B7:I7) -> 43000
A8: SPEND PER HEAD(/transaction) | C8: 40 | D8: 40 | E8: 40 | F8: 60 | G8: 60 | H8: 25 | I8: 25 | J8: =J9/J7 -> 43.255814
A9: TOTAL GROSS | B9: =B7*B8 -> 0 | C9: =C7*C8 -> 200000 | D9: =D7*D8 -> 200000 | E9: =E7*E8 -> 200000 | F9: =F7*F8 -> 480000 | G9: =G7*G8 -> 480000 | H9: =H7*H8 -> 150000 | I9: =I7*I8 -> 150000 | J9: =SUM(B9:I9) -> 1860000 | L9: \
A10: % OF TOTAL GROSS | B10: =B9/$J$9 -> 0 | C10: =C9/$J$9 -> 0.10752688 | D10: =D9/$J$9 -> 0.10752688 | E10: =E9/$J$9 -> 0.10752688 | F10: =F9/$J$9 -> 0.25806452 | G10: =G9/$J$9 -> 0.25806452 | H10: =H9/$J$9 -> 0.080645161 | I10: =I9/$J$9 -> 0.080645161
A12: Inventory ID | C12: Name | D12: Description | E12: Opening | F12: Add | G12: Adj | H12: Total Opening Stock | I12: Comps | J12: Losses/damages | K12: Total Closing Stock | L12: Sold | M12: Selling Price | N12: Gross Sales | O12: % of total sales | P12: % of gross target per stock stock category | Q12: TOTAL GROSS TARGET | R12: % of gross target per stock stock category
A13: 1 | C13: Shadow boxing - Ash Melange Navy Unisex | D13: S | E13: =MROUND(R13*$Q$13/M13,1) -> 93 | H13: =SUM(E13:G13) -> 93 | K13: 0 | L13: =H13-I13-J13-K13 -> 93 | M13: 500 | N13: =L13*M13 -> 46500 | O13: =N13/$N$78 -> 0.024994625 | P13: 0.25 | Q13: =P13*$R$2 -> 465000 | R13: 0.1 | U13: Ash Navy melange CTH6 | Y13: Indigo blue | AC13: COMMENTS
C14: Shadow boxing - Ash Melange Navy Unisex | D14: M | E14: =MROUND(R14*$Q$13/M14,1) -> 186 | H14: =SUM(E14:G14) -> 186 | K14: 0 | L14: =H14-I14-J14-K14 -> 186 | M14: 500 | N14: =L14*M14 -> 93000 | O14: =N14/$N$78 -> 0.04998925 | R14: 0.2
C15: Shadow boxing - Ash Melange Navy Unisex | D15: L | E15: =MROUND(R15*$Q$13/M15,1) -> 279 | H15: =SUM(E15:G15) -> 279 | K15: 0 | L15: =H15-I15-J15-K15 -> 279 | M15: 500 | N15: =L15*M15 -> 139500 | O15: =N15/$N$78 -> 0.074983874 | R15: 0.3 | AC15: Can't find any Indigo blue
C16: Shadow boxing - Ash Melange Navy Unisex | D16: XL | E16: =MROUND(R16*$Q$13/M16,1) -> 233 | H16: =SUM(E16:G16) -> 233 | K16: 0 | L16: =H16-I16-J16-K16 -> 233 | M16: 500 | N16: =L16*M16 -> 116500 | O16: =N16/$N$78 -> 0.062620942 | R16: 0.25
C17: Shadow boxing - Ash Melange Navy Unisex | D17: XXL | E17: =MROUND(R17*$Q$13/M17,1) -> 140 | H17: =SUM(E17:G17) -> 140 | K17: 0 | L17: =H17-I17-J17-K17 -> 140 | M17: 500 | N17: =L17*M17 -> 70000 | O17: =N17/$N$78 -> 0.037626317 | R17: 0.15
C18: =C17 -> Shadow boxing - Ash Melange Navy Unisex | E18: =SUM(E13:E17) -> 931 | F18: =SUM(F13:F17) -> 0 | G18: =SUM(G13:G17) -> 0 | H18: =SUM(H13:H17) -> 931 | I18: =SUM(I13:I17) -> 0 | J18: =SUM(J13:J17) -> 0 | K18: =SUM(K13:K17) -> 0 | L18: =SUM(L13:L17) -> 931 | N18: =SUM(N13:N17) -> 465500 | O18: =SUM(O13:O17) -> 0.25021501
A19: 2 | C19: Shadow boxing - Lt Blue Unisex | D19: S | E19: =MROUND(R19*$Q$19/M19,1) -> 74 | H19: =SUM(E19:G19) -> 74 | K19: 0 | L19: =H19-I19-J19-K19 -> 74 | M19: 500 | N19: =L19*M19 -> 37000 | O19: =N19/$N$78 -> 0.019888196 | P19: 0.2 | Q19: =P19*$R$2 -> 372000 | R19: 0.1
C20: Shadow boxing - Lt Blue Unisex | D20: M | E20: =MROUND(R20*$Q$19/M20,1) -> 149 | H20: =SUM(E20:G20) -> 149 | K20: 0 | L20: =H20-I20-J20-K20 -> 149 | M20: 500 | N20: =L20*M20 -> 74500 | O20: =N20/$N$78 -> 0.040045152 | R20: 0.2
C21: Shadow boxing - Lt Blue Unisex | D21: L | E21: =MROUND(R21*$Q$19/M21,1) -> 223 | H21: =SUM(E21:G21) -> 223 | K21: 0 | L21: =H21-I21-J21-K21 -> 223 | M21: 500 | N21: =L21*M21 -> 111500 | O21: =N21/$N$78 -> 0.059933348 | R21: 0.3
C22: Shadow boxing - Lt Blue Unisex | D22: XL | E22: =MROUND(R22*$Q$19/M22,1) -> 186 | H22: =SUM(E22:G22) -> 186 | K22: 0 | L22: =H22-I22-J22-K22 -> 186 | M22: 500 | N22: =L22*M22 -> 93000 | O22: =N22/$N$78 -> 0.04998925 | R22: 0.25
C23: Shadow boxing - Lt Blue Unisex | D23: XXL | E23: =MROUND(R23*$Q$19/M23,1) -> 112 | H23: =SUM(E23:G23) -> 112 | K23: 0 | L23: =H23-I23-J23-K23 -> 112 | M23: 500 | N23: =L23*M23 -> 56000 | O23: =N23/$N$78 -> 0.030101054 | R23: 0.15
C24: =C23 -> Shadow boxing - Lt Blue Unisex | E24: =SUM(E19:E23) -> 744 | F24: =SUM(F19:F23) -> 0 | G24: =SUM(G19:G23) -> 0 | H24: =SUM(H19:H23) -> 744 | I24: =SUM(I19:I23) -> 0 | J24: =SUM(J19:J23) -> 0 | K24: =SUM(K19:K23) -> 0 | L24: =SUM(L19:L23) -> 744 | N24: =SUM(N19:N23) -> 372000 | O24: =SUM(O19:O23) -> 0.199957
A25: 3 | C25: Roll type unisex in black T | D25: S | E25: =MROUND(R25*$Q$25/M25,1) -> 37 | H25: =SUM(E25:G25) -> 37 | K25: 0 | L25: =H25-I25-J25-K25 -> 37 | M25: 500 | N25: =L25*M25 -> 18500 | O25: =N25/$N$78 -> 0.009944098 | P25: 0.1 | Q25: =P25*$R$2 -> 186000 | R25: 0.1
C26: Roll type unisex in black T | D26: M | E26: =MROUND(R26*$Q$25/M26,1) -> 93 | H26: =SUM(E26:G26) -> 93 | K26: 0 | L26: =H26-I26-J26-K26 -> 93 | M26: 500 | N26: =L26*M26 -> 46500 | O26: =N26/$N$78 -> 0.024994625 | R26: 0.25 | V26: 160g | W26: Black cotton
C27: Roll type unisex in black T | D27: L | E27: =MROUND(R27*$Q$25/M27,1) -> 112 | H27: =SUM(E27:G27) -> 112 | K27: 0 | L27: =H27-I27-J27-K27 -> 112 | M27: 500 | N27: =L27*M27 -> 56000 | O27: =N27/$N$78 -> 0.030101054 | R27: 0.3
C28: Roll type unisex in black T | D28: XL | E28: =MROUND(R28*$Q$25/M28,1) -> 74 | H28: =SUM(E28:G28) -> 74 | K28: 0 | L28: =H28-I28-J28-K28 -> 74 | M28: 500 | N28: =L28*M28 -> 37000 | O28: =N28/$N$78 -> 0.019888196 | R28: 0.2
C29: Roll type unisex in black T | D29: XXL | E29: =MROUND(R29*$Q$25/M29,1) -> 56 | H29: =SUM(E29:G29) -> 56 | K29: 0 | L29: =H29-I29-J29-K29 -> 56 | M29: 500 | N29: =L29*M29 -> 28000 | O29: =N29/$N$78 -> 0.015050527 | R29: 0.15
C30: =C29 -> Roll type unisex in black T | E30: =SUM(E25:E29) -> 372 | F30: =SUM(F25:F29) -> 0 | G30: =SUM(G25:G29) -> 0 | H30: =SUM(H25:H29) -> 372 | I30: =SUM(I25:I29) -> 0 | J30: =SUM(J25:J29) -> 0 | K30: =SUM(K25:K29) -> 0 | L30: =SUM(L25:L29) -> 372 | N30: =SUM(N25:N29) -> 186000 | O30: =SUM(O25:O29) -> 0.099978499
A31: 4 | C31: Bryan Punched - Charcoal unisex | D31: S | E31: =MROUND(R31*$Q$31/M31,1) -> 30 | H31: =SUM(E31:G31) -> 30 | K31: 0 | L31: =H31-I31-J31-K31 -> 30 | M31: 500 | N31: =L31*M31 -> 15000 | O31: =N31/$N$78 -> 0.0080627822 | P31: 0.08 | Q31: =P31*$R$2 -> 148800 | R31: 0.1 | U31: CTH6 | V31: 160g | W31: Grey or Charcoal Melange | AC31: We have a grey or a charcoal Melange
C32: Bryan Punched - Charcoal unisex | D32: M | E32: =MROUND(R32*$Q$31/M32,1) -> 74 | H32: =SUM(E32:G32) -> 74 | K32: 0 | L32: =H32-I32-J32-K32 -> 74 | M32: 500 | N32: =L32*M32 -> 37000 | O32: =N32/$N$78 -> 0.019888196 | R32: 0.25
C33: Bryan Punched - Charcoal unisex | D33: L | E33: =MROUND(R33*$Q$31/M33,1) -> 89 | H33: =SUM(E33:G33) -> 89 | K33: 0 | L33: =H33-I33-J33-K33 -> 89 | M33: 500 | N33: =L33*M33 -> 44500 | O33: =N33/$N$78 -> 0.023919587 | R33: 0.3
C34: Bryan Punched - Charcoal unisex | D34: XL | E34: =MROUND(R34*$Q$31/M34,1) -> 60 | H34: =SUM(E34:G34) -> 60 | K34: 0 | L34: =H34-I34-J34-K34 -> 60 | M34: 500 | N34: =L34*M34 -> 30000 | O34: =N34/$N$78 -> 0.016125564 | R34: 0.2
C35: Bryan Punched - Charcoal unisex | D35: XXL | E35: =MROUND(R35*$Q$31/M35,1) -> 45 | H35: =SUM(E35:G35) -> 45 | K35: 0 | L35: =H35-I35-J35-K35 -> 45 | M35: 500 | N35: =L35*M35 -> 22500 | O35: =N35/$N$78 -> 0.012094173 | R35: 0.15
C36: =C35 -> Bryan Punched - Charcoal unisex | E36: =SUM(E31:E35) -> 298 | F36: =SUM(F31:F35) -> 0 | G36: =SUM(G31:G35) -> 0 | H36: =SUM(H31:H35) -> 298 | I36: =SUM(I31:I35) -> 0 | J36: =SUM(J31:J35) -> 0 | K36: =SUM(K31:K35) -> 0 | L36: =SUM(L31:L35) -> 298 | N36: =SUM(N31:N35) -> 149000 | O36: =SUM(O31:O35) -> 0.080090303
A37: 5 | C37: Glove tour white Unisex | D37: S | E37: =MROUND(R37*$Q$37/M37,1) -> 37 | H37: =SUM(E37:G37) -> 37 | K37: 0 | L37: =H37-I37-J37-K37 -> 37 | M37: 500 | N37: =L37*M37 -> 18500 | O37: =N37/$N$78 -> 0.009944098 | P37: 0.1 | Q37: =P37*$R$2 -> 186000 | R37: 0.1
C38: Glove tour white Unisex | D38: M | E38: =MROUND(R38*$Q$37/M38,1) -> 74 | H38: =SUM(E38:G38) -> 74 | K38: 0 | L38: =H38-I38-J38-K38 -> 74 | M38: 500 | N38: =L38*M38 -> 37000 | O38: =N38/$N$78 -> 0.019888196 | R38: 0.2 | V38: 180g | W38: White | X38: OR | Y38: 160g | Z38: White
C39: Glove tour white Unisex | D39: L | E39: =MROUND(R39*$Q$37/M39,1) -> 112 | H39: =SUM(E39:G39) -> 112 | K39: 0 | L39: =H39-I39-J39-K39 -> 112 | M39: 500 | N39: =L39*M39 -> 56000 | O39: =N39/$N$78 -> 0.030101054 | R39: 0.3
C40: Glove tour white Unisex | D40: XL | E40: =MROUND(R40*$Q$37/M40,1) -> 93 | H40: =SUM(E40:G40) -> 93 | K40: 0 | L40: =H40-I40-J40-K40 -> 93 | M40: 500 | N40: =L40*M40 -> 46500 | O40: =N40/$N$78 -> 0.024994625 | R40: 0.25
C41: Glove tour white Unisex | D41: XXL | E41: =MROUND(R41*$Q$37/M41,1) -> 56 | H41: =SUM(E41:G41) -> 56 | K41: 0 | L41: =H41-I41-J41-K41 -> 56 | M41: 500 | N41: =L41*M41 -> 28000 | O41: =N41/$N$78 -> 0.015050527 | R41: 0.15
C42: =C41 -> Glove tour white Unisex | E42: =SUM(E37:E41) -> 372 | F42: =SUM(F37:F41) -> 0 | G42: =SUM(G37:G41) -> 0 | H42: =SUM(H37:H41) -> 372 | I42: =SUM(I37:I41) -> 0 | J42: =SUM(J37:J41) -> 0 | K42: =SUM(K37:K41) -> 0 | L42: =SUM(L37:L41) -> 372 | N42: =SUM(N37:N41) -> 186000 | O42: =SUM(O37:O41) -> 0.099978499
A43: 5 | C43: Black Zip Hoodie | D43: S | E43: =MROUND(R43*$Q$43/M43,1) -> 30 | H43: =SUM(E43:G43) -> 30 | K43: 0 | L43: =H43-I43-J43-K43 -> 30 | M43: 750 | N43: =L43*M43 -> 22500 | O43: =N43/$N$78 -> 0.012094173 | P43: 0.12 | Q43: =P43*$R$2 -> 223200 | R43: 0.1
C44: Black Zip Hoodie | D44: M | E44: =MROUND(R44*$Q$43/M44,1) -> 60 | H44: =SUM(E44:G44) -> 60 | K44: 0 | L44: =H44-I44-J44-K44 -> 60 | M44: 750 | N44: =L44*M44 -> 45000 | O44: =N44/$N$78 -> 0.024188347 | R44: 0.2
C45: Black Zip Hoodie | D45: L | E45: =MROUND(R45*$Q$43/M45,1) -> 89 | H45: =SUM(E45:G45) -> 89 | K45: 0 | L45: =H45-I45-J45-K45 -> 89 | M45: 750 | N45: =L45*M45 -> 66750 | O45: =N45/$N$78 -> 0.035879381 | R45: 0.3
C46: Black Zip Hoodie | D46: XL | E46: =MROUND(R46*$Q$43/M46,1) -> 74 | H46: =SUM(E46:G46) -> 74 | K46: 0 | L46: =H46-I46-J46-K46 -> 74 | M46: 750 | N46: =L46*M46 -> 55500 | O46: =N46/$N$78 -> 0.029832294 | R46: 0.25
C47: Black Zip Hoodie | D47: XXL | E47: =MROUND(R47*$Q$43/M47,1) -> 45 | H47: =SUM(E47:G47) -> 45 | K47: 0 | L47: =H47-I47-J47-K47 -> 45 | M47: 750 | N47: =L47*M47 -> 33750 | O47: =N47/$N$78 -> 0.01814126 | R47: 0.15
C48: =C47 -> Black Zip Hoodie | E48: =SUM(E43:E47) -> 298 | F48: =SUM(F43:F47) -> 0 | G48: =SUM(G43:G47) -> 0 | H48: =SUM(H43:H47) -> 298 | I48: =SUM(I43:I47) -> 0 | J48: =SUM(J43:J47) -> 0 | K48: =SUM(K43:K47) -> 0 | L48: =SUM(L43:L47) -> 298 | N48: =SUM(N43:N47) -> 223500 | O48: =SUM(O43:O47) -> 0.12013545
A49: 7 | D49: S | H49: =SUM(E49:G49) -> 0 | K49: 0 | L49: =H49-I49-J49-K49 -> 0 | M49: 500 | N49: =L49*M49 -> 0 | O49: =N49/$N$78 -> 0 | Q49: =P49*$R$2 -> 0 | R49: 0.1
D50: M | H50: =SUM(E50:G50) -> 0 | K50: 0 | L50: =H50-I50-J50-K50 -> 0 | M50: 500 | N50: =L50*M50 -> 0 | O50: =N50/$N$78 -> 0 | R50: 0.2
D51: L | H51: =SUM(E51:G51) -> 0 | K51: 0 | L51: =H51-I51-J51-K51 -> 0 | M51: 500 | N51: =L51*M51 -> 0 | O51: =N51/$N$78 -> 0 | R51: 0.3
D52: XL | H52: =SUM(E52:G52) -> 0 | K52: 0 | L52: =H52-I52-J52-K52 -> 0 | M52: 500 | N52: =L52*M52 -> 0 | O52: =N52/$N$78 -> 0 | R52: 0.25
D53: XXL | H53: =SUM(E53:G53) -> 0 | K53: 0 | L53: =H53-I53-J53-K53 -> 0 | M53: 500 | N53: =L53*M53 -> 0 | O53: =N53/$N$78 -> 0 | R53: 0.15
C54: =C53 -> 0 | E54: =SUM(E49:E53) -> 0 | F54: =SUM(F49:F53) -> 0 | G54: =SUM(G49:G53) -> 0 | H54: =SUM(H49:H53) -> 0 | I54: =SUM(I49:I53) -> 0 | J54: =SUM(J49:J53) -> 0 | K54: =SUM(K49:K53) -> 0 | L54: =SUM(L49:L53) -> 0 | N54: =SUM(N49:N53) -> 0 | O54: =SUM(O49:O53) -> 0
A55: 8 | D55: S | H55: =SUM(E55:G55) -> 0 | K55: 0 | L55: =H55-I55-J55-K55 -> 0 | M55: 500 | N55: =L55*M55 -> 0 | O55: =N55/$N$78 -> 0 | Q55: =P55*$R$2 -> 0 | R55: 0.1
D56: M | H56: =SUM(E56:G56) -> 0 | K56: 0 | L56: =H56-I56-J56-K56 -> 0 | M56: 500 | N56: =L56*M56 -> 0 | O56: =N56/$N$78 -> 0 | R56: 0.2
D57: L | H57: =SUM(E57:G57) -> 0 | K57: 0 | L57: =H57-I57-J57-K57 -> 0 | M57: 500 | N57: =L57*M57 -> 0 | O57: =N57/$N$78 -> 0 | R57: 0.3
D58: XL | H58: =SUM(E58:G58) -> 0 | K58: 0 | L58: =H58-I58-J58-K58 -> 0 | M58: 500 | N58: =L58*M58 -> 0 | O58: =N58/$N$78 -> 0 | R58: 0.25
D59: XXL | H59: =SUM(E59:G59) -> 0 | K59: 0 | L59: =H59-I59-J59-K59 -> 0 | M59: 500 | N59: =L59*M59 -> 0 | O59: =N59/$N$78 -> 0 | R59: 0.15
C60: =C59 -> 0 | E60: =SUM(E55:E59) -> 0 | F60: =SUM(F55:F59) -> 0 | G60: =SUM(G55:G59) -> 0 | H60: =SUM(H55:H59) -> 0 | I60: =SUM(I55:I59) -> 0 | J60: =SUM(J55:J59) -> 0 | K60: =SUM(K55:K59) -> 0 | L60: =SUM(L55:L59) -> 0 | N60: =SUM(N55:N59) -> 0 | O60: =SUM(O55:O59) -> 0
A61: 9 | D61: S | H61: =SUM(E61:G61) -> 0 | K61: 0 | L61: =H61-I61-J61-K61 -> 0 | M61: 500 | N61: =L61*M61 -> 0 | O61: =N61/$N$78 -> 0 | Q61: =P61*$R$2 -> 0 | R61: 0.1
D62: M | H62: =SUM(E62:G62) -> 0 | K62: 0 | L62: =H62-I62-J62-K62 -> 0 | M62: 500 | N62: =L62*M62 -> 0 | O62: =N62/$N$78 -> 0 | R62: 0.2
D63: L | H63: =SUM(E63:G63) -> 0 | K63: 0 | L63: =H63-I63-J63-K63 -> 0 | M63: 500 | N63: =L63*M63 -> 0 | O63: =N63/$N$78 -> 0 | R63: 0.3
D64: XL | H64: =SUM(E64:G64) -> 0 | K64: 0 | L64: =H64-I64-J64-K64 -> 0 | M64: 500 | N64: =L64*M64 -> 0 | O64: =N64/$N$78 -> 0 | R64: 0.25
D65: XXL | H65: =SUM(E65:G65) -> 0 | K65: 0 | L65: =H65-I65-J65-K65 -> 0 | M65: 500 | N65: =L65*M65 -> 0 | O65: =N65/$N$78 -> 0 | R65: 0.15
C66: =C65 -> 0 | E66: =SUM(E61:E65) -> 0 | F66: =SUM(F61:F65) -> 0 | G66: =SUM(G61:G65) -> 0 | H66: =SUM(H61:H65) -> 0 | I66: =SUM(I61:I65) -> 0 | J66: =SUM(J61:J65) -> 0 | K66: =SUM(K61:K65) -> 0 | L66: =SUM(L61:L65) -> 0 | N66: =SUM(N61:N65) -> 0 | O66: =SUM(O61:O65) -> 0
A67: A | C67: Cap | E67: =MROUND(R67*Q67/M67,1) -> 319 | H67: =SUM(E67:G67) -> 319 | K67: 0 | L67: =H67-I67-J67-K67 -> 319 | M67: 350 | N67: =L67*M67 -> 111650 | O67: =N67/$N$78 -> 0.060013975 | P67: 0.06 | Q67: =P67*$R$2 -> 111600 | R67: 1
A68: B | C68: Black Tote Bag | E68: =MROUND(R68*Q68/M68,1) -> 372 | H68: =SUM(E68:G68) -> 372 | K68: 0 | L68: =H68-I68-J68-K68 -> 372 | M68: 100 | N68: =L68*M68 -> 37200 | O68: =N68/$N$78 -> 0.0199957 | P68: 0.02 | Q68: =P68*$R$2 -> 37200 | R68: 1
A69: C | C69: Tour Book/Program | E69: =MROUND(R69*Q69/M69,1) -> 322 | H69: =SUM(E69:G69) -> 322 | K69: 0 | L69: =H69-I69-J69-K69 -> 322 | M69: 150 | N69: =L69*M69 -> 48300 | O69: =N69/$N$78 -> 0.025962159 | P69: 0.026 | Q69: =P69*$R$2 -> 48360 | R69: 1
A70: D | C70: Boxing Glove Key Ring | E70: =MROUND(R70*Q70/M70,1) -> 506 | H70: =SUM(E70:G70) -> 506 | K70: 0 | L70: =H70-I70-J70-K70 -> 506 | M70: 125 | N70: =L70*M70 -> 63250 | O70: =N70/$N$78 -> 0.033998065 | P70: 0.034 | Q70: =P70*$R$2 -> 63240 | R70: 1
A71: E | C71: CD - punched | E71: =MROUND(R71*Q71/M71,1) -> 23 | H71: =SUM(E71:G71) -> 23 | K71: 0 | L71: =H71-I71-J71-K71 -> 23 | M71: 200 | N71: =L71*M71 -> 4600 | O71: =N71/$N$78 -> 0.0024725865 | P71: 0.0025 | Q71: =P71*$R$2 -> 4650 | R71: 1
A72: F | C72: Vinyl - punched | E72: =MROUND(R72*Q72/M72,1) -> 8 | H72: =SUM(E72:G72) -> 8 | K72: 0 | L72: =H72-I72-J72-K72 -> 8 | M72: 550 | N72: =L72*M72 -> 4400 | O72: =N72/$N$78 -> 0.0023650828 | P72: 0.0025 | Q72: =P72*$R$2 -> 4650 | R72: 1
A73: G | C73: CD - classic | E73: =MROUND(R73*Q73/M73,1) -> 23 | H73: =SUM(E73:G73) -> 23 | K73: 0 | L73: =H73-I73-J73-K73 -> 23 | M73: 200 | N73: =L73*M73 -> 4600 | O73: =N73/$N$78 -> 0.0024725865 | P73: 0.0025 | Q73: =P73*$R$2 -> 4650 | R73: 1
A74: H | C74: Vinyl - classic | E74: =MROUND(R74*Q74/M74,1) -> 8 | H74: =SUM(E74:G74) -> 8 | K74: 0 | L74: =H74-I74-J74-K74 -> 8 | M74: 550 | N74: =L74*M74 -> 4400 | O74: =N74/$N$78 -> 0.0023650828 | P74: 0.0025 | Q74: =P74*$R$2 -> 4650 | R74: 1
E75: =SUM(E67:E74) -> 1581 | F75: =SUM(F67:F74) -> 0 | G75: =SUM(G67:G74) -> 0 | H75: =SUM(H67:H74) -> 1581 | I75: =SUM(I67:I74) -> 0 | J75: =SUM(J67:J74) -> 0 | K75: =SUM(K67:K74) -> 0 | L75: =SUM(L67:L74) -> 1581 | N75: =SUM(N67:N74) -> 278400 | O75: =SUM(O67:O74) -> 0.14964524
D76: TOTAL | E76: =E18+E24+E30+E36+E42+E48+E54+E60+E66+E75 -> 4596 | F76: =F18+F24+F30+F36+F42+F48+F54+F60+F66+F75 -> 0 | G76: =G18+G24+G30+G36+G42+G48+G54+G60+G66+G75 -> 0 | H76: =H18+H24+H30+H36+H42+H48+H54+H60+H66+H75 -> 4596 | I76: =I18+I24+I30+I36+I42+I48+I54+I60+I66+I75 -> 0 | J76: =J18+J24+J30+J36+J42+J48+J54+J60+J66+J75 -> 0 | K76: =K18+K24+K30+K36+K42+K48+K54+K60+K66+K75 -> 0 | L76: =L18+L24+L30+L36+L42+L48+L54+L60+L66+L75 -> 4596 | O76: =O18+O24+O30+O36+O42+O48+O54+O60+O66+O75 -> 1 | P76: =SUM(P13:P75) -> 1
E78: TOTAL TAKINGS | N78: =N18+N24+N30+N36+N42+N48+N54+N60+N66+N75 -> 1860400
E80: PAID ATTENDANCE | N80: =Q2 -> 43000
E82: TOTAL TAKINGS | N82: =N78/N80 -> 43.265116

Sheet Manufacturing & Shipping
A1: MANUFACTURING & SHIPPING EXPENSES
G2: Exchange rate
A3: MANUFACTURING - INTERNATIONAL | G3: GBP VS ZAR
G4: =Summary!D55 -> 22.35
A6: ITEM | B6: Units | C6: GBP | D6: ZAR | E6: TOTAL COST GBP | F6: TOTAL COST ZAR
A7: =Sales!C69 -> Tour Book/Program | B7: =Sales!E69 -> 322 | C7: 3 | D7: =C7*$G$4 -> 67.05 | E7: =C7*B7 -> 966 | F7: =D7*B7 -> 21590.1
A8: =Sales!C70 -> Boxing Glove Key Ring | B8: =Sales!H70 -> 506 | C8: 3 | D8: =C8*$G$4 -> 67.05 | E8: =C8*B8 -> 1518 | F8: =D8*B8 -> 33927.3
A9: =Sales!C71 -> CD - punched | B9: =Sales!E71 -> 23 | C9: 2 | D9: =C9*$G$4 -> 44.7 | E9: =C9*B9 -> 46 | F9: =D9*B9 -> 1028.1
A10: =Sales!C72 -> Vinyl - punched | B10: =Sales!E72 -> 8 | C10: 8 | D10: =C10*$G$4 -> 178.8 | E10: =C10*B10 -> 64 | F10: =D10*B10 -> 1430.4
A11: =Sales!C73 -> CD - classic | B11: =Sales!E73 -> 23 | C11: 2 | D11: =C11*$G$4 -> 44.7 | E11: =C11*B11 -> 46 | F11: =D11*B11 -> 1028.1
A12: =Sales!C74 -> Vinyl - classic | B12: =Sales!E74 -> 8 | C12: 8 | D12: =C12*$G$4 -> 178.8 | E12: =C12*B12 -> 64 | F12: =D12*B12 -> 1430.4
A13: =Sales!C43 -> Black Zip Hoodie | B13: =Sales!E48 -> 298 | C13: 10 | D13: =C13*$G$4 -> 223.5 | E13: =C13*B13 -> 2980 | F13: =D13*B13 -> 66603
D14: =C14*$G$4 -> 0 | E14: =C14*B14 -> 0 | F14: =D14*B14 -> 0
D15: =C15*$G$4 -> 0 | E15: =C15*B15 -> 0 | F15: =D15*B15 -> 0
D16: =C16*$G$4 -> 0 | E16: =C16*B16 -> 0 | F16: =D16*B16 -> 0
D17: =C17*$G$4 -> 0 | E17: =C17*B17 -> 0 | F17: =D17*B17 -> 0
A18: TOTAL | B18: =SUM(B7:B17) -> 1188 | E18: =SUM(E7:E17) -> 5684 | F18: =SUM(F7:F17) -> 127037.4
A20: MANUFACTURING - LOCAL
A23: ITEM | B23: Units | C23: GBP | D23: ZAR | E23: TOTAL COST GBP | F23: TOTAL COST ZAR
A24: =Sales!C13 -> Shadow boxing - Ash Melange Navy Unisex | B24: =Sales!E18 -> 931 | C24: =D24/Summary!$D$55 -> 7.1588367 | D24: 160 | E24: =C24*B24 -> 6664.877 | F24: =D24*B24 -> 148960
A25: =Sales!C19 -> Shadow boxing - Lt Blue Unisex | B25: =Sales!E24 -> 744 | C25: =D25/Summary!$D$55 -> 7.1588367 | D25: 160 | E25: =C25*B25 -> 5326.1745 | F25: =D25*B25 -> 119040
A26: =Sales!C25 -> Roll type unisex in black T | B26: =Sales!E30 -> 372 | C26: =D26/Summary!$D$55 -> 7.1588367 | D26: 160 | E26: =C26*B26 -> 2663.0872 | F26: =D26*B26 -> 59520
A27: =Sales!C31 -> Bryan Punched - Charcoal unisex | B27: =Sales!E36 -> 298 | C27: =D27/Summary!$D$55 -> 7.1588367 | D27: 160 | E27: =C27*B27 -> 2133.3333 | F27: =D27*B27 -> 47680
A28: =Sales!C37 -> Glove tour white Unisex | B28: =Sales!E42 -> 372 | C28: =D28/Summary!$D$55 -> 7.1588367 | D28: 160 | E28: =C28*B28 -> 2663.0872 | F28: =D28*B28 -> 59520
A29: =Sales!C67 -> Cap | B29: =Sales!E67 -> 319 | C29: =D29/Summary!$D$55 -> 4.4742729 | D29: 100 | E29: =C29*B29 -> 1427.2931 | F29: =D29*B29 -> 31900
A30: =Sales!C68 -> Black Tote Bag | B30: =Sales!E68 -> 372 | C30: =D30/Summary!$D$55 -> 2.2371365 | D30: 50 | E30: =C30*B30 -> 832.21477 | F30: =D30*B30 -> 18600
E31: =C31*B31 -> 0 | F31: =D31*B31 -> 0
A35: TOTAL | B35: =SUM(B24:B34) -> 3408 | E35: =SUM(E24:E34) -> 21710.067 | F35: =SUM(F24:F34) -> 485220
A37: Customs Duty
A39: GBP | C39: Keyring & media | D39: 0.1 | E39: Hoodie | F39: 0.45
A40: ITEM | B40: Units | C40: GBP unit price | D40: Duties | E40: GBP Unit cost after import duties | F40: TOTAL INCL IMPORT DUTIES COST GBP | G40: TOTAL IMPORT DUTIES
A41: =A8 -> Boxing Glove Key Ring | B41: =B8 -> 506 | C41: =C8 -> 3 | E41: =D41+C41 -> 3 | F41: =E41*B41 -> 1518 | G41: =D41*B41 -> 0
A42: =A9 -> CD - punched | B42: =B9 -> 23 | C42: =C9 -> 2 | D42: =C42*$D$39 -> 0.2 | E42: =D42+C42 -> 2.2 | F42: =E42*B42 -> 50.6 | G42: =D42*B42 -> 4.6
A43: =A10 -> Vinyl - punched | B43: =B10 -> 8 | C43: =C10 -> 8 | D43: =C43*$D$39 -> 0.8 | E43: =D43+C43 -> 8.8 | F43: =E43*B43 -> 70.4 | G43: =D43*B43 -> 6.4
A44: =A11 -> CD - classic | B44: =B11 -> 23 | C44: =C11 -> 2 | D44: =C44*$D$39 -> 0.2 | E44: =D44+C44 -> 2.2 | F44: =E44*B44 -> 50.6 | G44: =D44*B44 -> 4.6
A45: =A12 -> Vinyl - classic | B45: =B12 -> 8 | C45: =C12 -> 8 | D45: =C45*$D$39 -> 0.8 | E45: =D45+C45 -> 8.8 | F45: =E45*B45 -> 70.4 | G45: =D45*B45 -> 6.4
A46: =A13 -> Black Zip Hoodie | B46: =B13 -> 298 | C46: =C13 -> 10 | D46: =C46*$F$39 -> 4.5 | E46: =D46+C46 -> 14.5 | F46: =E46*B46 -> 4321 | G46: =D46*B46 -> 1341
D47: =C47*$D$39 -> 0 | E47: =D47+C47 -> 0 | F47: =E47*B47 -> 0 | G47: =D47*B47 -> 0
D48: =C48*$D$39 -> 0 | E48: =D48+C48 -> 0 | F48: =E48*B48 -> 0 | G48: =D48*B48 -> 0
D49: =C49*$D$39 -> 0 | E49: =D49+C49 -> 0 | F49: =E49*B49 -> 0 | G49: =D49*B49 -> 0
D50: =C50*$D$39 -> 0 | E50: =D50+C50 -> 0 | F50: =E50*B50 -> 0 | G50: =D50*B50 -> 0
A51: TOTAL | B51: =SUM(B41:B50) -> 866 | F51: =SUM(F41:F50) -> 6081 | G51: =SUM(G41:G50) -> 1363
A52: ZAR
A53: ITEM | B53: Units | C53: ZAR | D53: Duties | E53: ZAR Unit cost after import duties | F53: TOTAL INCL IMPORT DUTIES COST ZAR | G53: TOTAL IMPORT DUTIES
A54: =A8 -> Boxing Glove Key Ring | B54: =B8 -> 506 | C54: =D8 -> 67.05 | E54: =D54+C54 -> 67.05 | F54: =E54*B54 -> 33927.3 | G54: =D54*B54 -> 0
A55: =A9 -> CD - punched | B55: =B9 -> 23 | C55: =D9 -> 44.7 | D55: =C55*$D$39 -> 4.47 | E55: =D55+C55 -> 49.17 | F55: =E55*B55 -> 1130.91 | G55: =D55*B55 -> 102.81
A56: =A10 -> Vinyl - punched | B56: =B10 -> 8 | C56: =D10 -> 178.8 | D56: =C56*$D$39 -> 17.88 | E56: =D56+C56 -> 196.68 | F56: =E56*B56 -> 1573.44 | G56: =D56*B56 -> 143.04
A57: =A11 -> CD - classic | B57: =B11 -> 23 | C57: =D11 -> 44.7 | D57: =C57*$D$39 -> 4.47 | E57: =D57+C57 -> 49.17 | F57: =E57*B57 -> 1130.91 | G57: =D57*B57 -> 102.81
A58: =A12 -> Vinyl - classic | B58: =B12 -> 8 | C58: =D12 -> 178.8 | D58: =C58*$D$39 -> 17.88 | E58: =D58+C58 -> 196.68 | F58: =E58*B58 -> 1573.44 | G58: =D58*B58 -> 143.04
A59: =A13 -> Black Zip Hoodie | B59: =B13 -> 298 | C59: =D13 -> 223.5 | D59: =C59*$F$39 -> 100.575 | E59: =D59+C59 -> 324.075 | F59: =E59*B59 -> 96574.35 | G59: =D59*B59 -> 29971.35
C60: =D14 -> 0 | D60: =C60*$D$39 -> 0 | E60: =D60+C60 -> 0 | F60: =E60*B60 -> 0 | G60: =D60*B60 -> 0
C61: =D15 -> 0 | D61: =C61*$D$39 -> 0 | E61: =D61+C61 -> 0 | F61: =E61*B61 -> 0 | G61: =D61*B61 -> 0
C62: =D16 -> 0 | D62: =C62*$D$39 -> 0 | E62: =D62+C62 -> 0 | F62: =E62*B62 -> 0 | G62: =D62*B62 -> 0
C63: =D17 -> 0 | D63: =C63*$D$39 -> 0 | E63: =D63+C63 -> 0 | F63: =E63*B63 -> 0 | G63: =D63*B63 -> 0
A64: TOTAL | B64: =SUM(B54:B63) -> 866 | F64: =SUM(F54:F63) -> 135910.35 | G64: =SUM(G54:G63) -> 30463.05
A66: FREIGHT & SHIPPING
A67: ITEM | B67: Units | C67: GBP | D67: ZAR | E67: TOTAL COST GBP | F67: TOTAL COST ZAR
A68: Freight costs/shipping | B68: 1 | C68: 800 | D68: =C68*$G$4 -> 17880 | E68: =B68*C68 -> 800 | F68: =D68*B68 -> 17880
A69: Venue to port - boxing of apparell & labour | B69: 1 | D69: =C69*$G$4 -> 0 | E69: =B69*C69 -> 0 | F69: =D69*B69 -> 0
A70: TOTAL | E70: =SUM(E68:E69) -> 800 | F70: =SUM(F68:F69) -> 17880

Sheet FINANCE
A1: FINANCE MODULE
A3: ARTIST | B3: =#REF! -> #REF!
A4: REGION | B4: South Africa
A5: SHOW | B5: All
A6: DATE | B6: All shows
A8: Date | B8: Sales | C8: Credit Cards | D8: Cash Deposits | E8: C/Cards not batched | F8: Wages | G8: Pre Paid EFT | H8: Credit Sales | I8: Management Wages | J8: Cash Expenses | K8: Cash Float | L8: Attie Advance | M8: Len Advance | N8: Intl Advances | O8: Loss / (gain) on cash
A9: 45676 | B9: =#REF! -> #REF! | H9: 0 | O9: =B9-SUM(C9:N9) -> #REF! | P9: =O9/B9 -> #REF!
A10: 45680 | B10: =#REF! -> #REF! | H10: 0 | O10: =B10-SUM(C10:N10) -> #REF!
A11: TOTAL | B11: =SUM(B9:B10) -> #REF! | C11: =SUM(C9:C10) -> 0 | D11: =SUM(D9:D10) -> 0 | E11: =SUM(E9:E10) -> 0 | F11: =SUM(F9:F10) -> 0 | G11: =SUM(G9:G10) -> 0 | H11: =SUM(H9:H10) -> 0 | I11: =SUM(I9:I10) -> 0 | ... O11: =SUM(O9:O10) -> #REF! | P11: =O11/B11 -> #REF!
H13: =F13*G13 -> 0
