Workbook

Sheet Setup
A1: MERCHANDISE SALES FORECAST - SETUP
A2: Blue cells = inputs. Light grey/pink background = input fields. All retail prices INCLUDE VAT. Costs are shown EXCLUDING VAT. Edit input cells and all other sheets update automatically.
A3: Artist: | B3: UB40 feat. Ali Campbell
A4: Tour Name: | B4: UB40 SA Tour 2026
A5: Currency: | B5: R | G5: Report Currency: | H5: GBP | J5: (e.g. USD, GBP, EUR) | K5: Party 1: | L5: Artist | N5: 0.7 | O5: =IF(N5+N6=1,"✓ 100%","⚠ "&TEXT(N5+N6,"0%")) -> ✓ 100%
A6: VAT Rate: | B6: 0.15 | G6: Exchange Rate: | H6: 23 | J6: (local currency per 1 report currency) | K6: Party 2: | L6: Promoter | N6: 0.3 | O6: (Profit Share)
A7: EVENT DETAILS & COSTS
B8: Date | C8: City | D8: Venue | E8: Capacity | F8: Est. Attendance | G8: # Stalls | H8: Spend /Head (incl VAT) | I8: Gross Target (incl VAT) | J8: Flights & Accom | K8: Other Costs | L8: Sales Ops Costs | M8: CC Fee % | N8: COGS (ex VAT) | O8: Net Profit (ex VAT) | P8: =Setup!L5&" Share" -> Artist Share | Q8: =Setup!L6&" Share" -> Promoter Share
A9: 1 | B9: 46175 | C9: Cape Town | D9: Grand Arena at GrandWest | E9: 5400 | F9: 5254 | G9: 1 | H9: 30 | I9: =IF(F9="","",F9*H9) -> 157620 | J9: 0 | K9: 0 | L9: 50000 | M9: 0.032 | N9: ='P&L Summary'!B10 -> 49482 | O9: ='P&L Summary'!B25 -> 33062.696 | P9: ='P&L Summary'!B29 -> 23143.887 | Q9: ='P&L Summary'!B30 -> 9918.8087
A10: 2 | B10: 46177 | C10: Durban | D10: Durban ICC | E10: 6000 | F10: 5200 | G10: 1 | H10: 30 | I10: =IF(F10="","",F10*H10) -> 156000 | J10: 0 | K10: 0 | L10: 50000 | M10: 0.032 | N10: ='P&L Summary'!C10 -> 49167 | O10: ='P&L Summary'!C25 -> 32540.13 | P10: ='P&L Summary'!C29 -> 22778.091 | Q10: ='P&L Summary'!C30 -> 9762.0391
A11: 3 | B11: 46179 | C11: Pretoria | D11: SunBet Arena Time Square | E11: 8500 | F11: 8450 | G11: 3 | H11: 45 | I11: =IF(F11="","",F11*H11) -> 380250 | J11: 0 | K11: 0 | L11: 75000 | M11: 0.032 | N11: ='P&L Summary'!D10 -> 119321 | O11: ='P&L Summary'!D25 -> 125335.77 | P11: ='P&L Summary'!D29 -> 87735.036 | Q11: ='P&L Summary'!D30 -> 37600.73
A12: 4 | B12: 46180 | C12: Pretoria | D12: SunBet Arena Time Square | E12: 8500 | F12: 5500 | G12: 3 | H12: 35 | I12: =IF(F12="","",F12*H12) -> 192500 | J12: 0 | K12: 0 | L12: 60000 | M12: 0.032 | N12: ='P&L Summary'!E10 -> 60247 | O12: ='P&L Summary'!E25 -> 41151.817 | P12: ='P&L Summary'!E29 -> 28806.272 | Q12: ='P&L Summary'!E30 -> 12345.545
I13: =IF(F13="","",F13*H13) | N13: ='P&L Summary'!F10 -> 0 | O13: ='P&L Summary'!F25 -> 0 | P13: ='P&L Summary'!F29 -> 0 | Q13: ='P&L Summary'!F30 -> 0
I14: =IF(F14="","",F14*H14) | N14: ='P&L Summary'!G10 -> 0 | O14: ='P&L Summary'!G25 -> 0 | P14: ='P&L Summary'!G29 -> 0 | Q14: ='P&L Summary'!G30 -> 0
I15: =IF(F15="","",F15*H15) | N15: ='P&L Summary'!H10 -> 0 | O15: ='P&L Summary'!H25 -> 0 | P15: ='P&L Summary'!H29 -> 0 | Q15: ='P&L Summary'!H30 -> 0
I16: =IF(F16="","",F16*H16) | N16: ='P&L Summary'!I10 -> 0 | O16: ='P&L Summary'!I25 -> 0 | P16: ='P&L Summary'!I29 -> 0 | Q16: ='P&L Summary'!I30 -> 0
A17: ONLINE SALES (Pre-Show & Post-Show)
A18: Pre-Show | I18: =IF(F18="","",F18*H18) | N18: ='P&L Summary'!J10 -> 0 | O18: ='P&L Summary'!J25 -> 0 | P18: ='P&L Summary'!J29 -> 0 | Q18: ='P&L Summary'!J30 -> 0
A19: Post-Show | I19: =IF(F19="","",F19*H19) | N19: ='P&L Summary'!K10 -> 0 | O19: ='P&L Summary'!K25 -> 0 | P19: ='P&L Summary'!K29 -> 0 | Q19: ='P&L Summary'!K30 -> 0
A20: TOTALS | E20: =SUM(E9:E16)+SUM(E18:E19) -> 28400 | F20: =SUM(F9:F16)+SUM(F18:F19) -> 24404 | G20: =SUM(G9:G16)+SUM(G18:G19) -> 8 | H20: =IFERROR(AVERAGEIF(H9:H16,"<>"),0) -> 35 | I20: =SUM(I9:I16)+SUM(I18:I19) -> 886370 | J20: =SUM(J9:J16)+SUM(J18:J19) -> 0 | K20: =SUM(K9:K16)+SUM(K18:K19) -> 0 | L20: =SUM(L9:L16)+SUM(L18:L19) -> 235000 | N20: ='P&L Summary'!L10 -> 278217 | O20: ='P&L Summary'!L25 -> 232090.41 | P20: ='P&L Summary'!L29 -> 162463.29 | Q20: ='P&L Summary'!L30 -> 69627.123
A21: Spend/Head and Gross Target are VAT-inclusive. All event costs (Flights, Other, Sales Ops) are ex VAT. CC Fee is applied to gross (incl VAT) revenue. Green columns (N-Q) are calculated from the P&L Summary.
A23: PRODUCT CATALOG & MANUFACTURING COSTS
A24: Retail prices INCLUDE VAT. Manufacturing/import costs are EXCLUDING VAT. Size %s must total 100% for apparel (column M check). % of Total Sales should sum to 100%.
A25: # | B25: Product Name | C25: Category | D25: Retail Price (incl VAT) | E25: % of Total Sales | F25: XS % | G25: S % | H25: M % | I25: L % | J25: XL % | K25: XXL % | L25: XXXL % | M25: Size % Check | N25: Garment/ Product | O25: Branding Cost | P25: Packing Cost | Q25: Import Duty | R25: Shipping /Unit | S25: Total Unit Cost
A26: 1 | B26: Sing Song Black tee | C26: Apparel | D26: 550 | E26: 0.3 | G26: 0.15 | H26: 0.25 | I26: 0.3 | J26: 0.18 | K26: 0.12 | M26: =IF(COUNTA(F26:L26)=0,"N/A",IF(ABS(SUM(F26:L26)-1)<0.001,"✓","✗ "&TEXT(SUM(F26:L26),"0%"))) -> ✓ | N26: 169 | O26: 0 | P26: 0 | Q26: 0 | S26: =IF(COUNTA(N26:R26)=0,"",SUM(N26:R26)) -> 169
A27: 2 | B27: Kingston Black Tee | C27: Apparel | D27: 550 | E27: 0.2 | G27: 0.15 | H27: 0.25 | I27: 0.3 | J27: 0.18 | K27: 0.12 | M27: =IF(COUNTA(F27:L27)=0,"N/A",IF(ABS(SUM(F27:L27)-1)<0.001,"✓","✗ "&TEXT(SUM(F27:L27),"0%"))) -> ✓ | N27: 169 | O27: 0 | P27: 0 | Q27: 0 | S27: =IF(COUNTA(N27:R27)=0,"",SUM(N27:R27)) -> 169
A28: 3 | B28: Red Red Wine White tee | C28: Apparel | D28: 550 | E28: 0.3 | G28: 0.15 | H28: 0.25 | I28: 0.3 | J28: 0.18 | K28: 0.12 | M28: =IF(COUNTA(F28:L28)=0,"N/A",IF(ABS(SUM(F28:L28)-1)<0.001,"✓","✗ "&TEXT(SUM(F28:L28),"0%"))) -> ✓ | N28: 162 | O28: 0 | P28: 0 | Q28: 0 | S28: =IF(COUNTA(N28:R28)=0,"",SUM(N28:R28)) -> 162
A29: 4 | B29: Cap | C29: Accessory | D29: 350 | E29: 0.13 | M29: =IF(COUNTA(F29:L29)=0,"N/A",IF(ABS(SUM(F29:L29)-1)<0.001,"✓","✗ "&TEXT(SUM(F29:L29),"0%"))) -> N/A | N29: 96 | O29: 0 | P29: 0 | Q29: 0 | S29: =IF(COUNTA(N29:R29)=0,"",SUM(N29:R29)) -> 96
A30: 5 | B30: Tote | C30: Accessory | D30: 100 | E30: 0.07 | M30: =IF(COUNTA(F30:L30)=0,"N/A",IF(ABS(SUM(F30:L30)-1)<0.001,"✓","✗ "&TEXT(SUM(F30:L30),"0%"))) -> N/A | N30: 50 | O30: 0 | P30: 0 | Q30: 0 | S30: =IF(COUNTA(N30:R30)=0,"",SUM(N30:R30)) -> 50
A31: 6 | M31: =IF(COUNTA(F31:L31)=0,"N/A",IF(ABS(SUM(F31:L31)-1)<0.001,"✓","✗ "&TEXT(SUM(F31:L31),"0%"))) -> N/A | N31: 0 | O31: 0 | P31: 0 | Q31: 0 | S31: =IF(COUNTA(N31:R31)=0,"",SUM(N31:R31)) -> 0
M32: =IF(COUNTA(F32:L32)=0,"N/A",IF(ABS(SUM(F32:L32)-1)<0.001,"✓","✗ "&TEXT(SUM(F32:L32),"0%"))) -> N/A | S32: =IF(COUNTA(N32:R32)=0,"",SUM(N32:R32))
M33: =IF(COUNTA(F33:L33)=0,"N/A",IF(ABS(SUM(F33:L33)-1)<0.001,"✓","✗ "&TEXT(SUM(F33:L33),"0%"))) -> N/A | S33: =IF(COUNTA(N33:R33)=0,"",SUM(N33:R33))
M34: =IF(COUNTA(F34:L34)=0,"N/A",IF(ABS(SUM(F34:L34)-1)<0.001,"✓","✗ "&TEXT(SUM(F34:L34),"0%"))) -> N/A | S34: =IF(COUNTA(N34:R34)=0,"",SUM(N34:R34))
M35: =IF(COUNTA(F35:L35)=0,"N/A",IF(ABS(SUM(F35:L35)-1)<0.001,"✓","✗ "&TEXT(SUM(F35:L35),"0%"))) -> N/A | S35: =IF(COUNTA(N35:R35)=0,"",SUM(N35:R35))
M36: =IF(COUNTA(F36:L36)=0,"N/A",IF(ABS(SUM(F36:L36)-1)<0.001,"✓","✗ "&TEXT(SUM(F36:L36),"0%"))) -> N/A | S36: =IF(COUNTA(N36:R36)=0,"",SUM(N36:R36))
M37: =IF(COUNTA(F37:L37)=0,"N/A",IF(ABS(SUM(F37:L37)-1)<0.001,"✓","✗ "&TEXT(SUM(F37:L37),"0%"))) -> N/A | S37: =IF(COUNTA(N37:R37)=0,"",SUM(N37:R37))
M38: =IF(COUNTA(F38:L38)=0,"N/A",IF(ABS(SUM(F38:L38)-1)<0.001,"✓","✗ "&TEXT(SUM(F38:L38),"0%"))) -> N/A | S38: =IF(COUNTA(N38:R38)=0,"",SUM(N38:R38))
M39: =IF(COUNTA(F39:L39)=0,"N/A",IF(ABS(SUM(F39:L39)-1)<0.001,"✓","✗ "&TEXT(SUM(F39:L39),"0%"))) -> N/A | S39: =IF(COUNTA(N39:R39)=0,"",SUM(N39:R39))
M40: =IF(COUNTA(F40:L40)=0,"N/A",IF(ABS(SUM(F40:L40)-1)<0.001,"✓","✗ "&TEXT(SUM(F40:L40),"0%"))) -> N/A | S40: =IF(COUNTA(N40:R40)=0,"",SUM(N40:R40))
D41: TOTAL % OF SALES: | E41: =SUM(E26:E40) -> 1 | R41: AVG UNIT COST: | S41: =IFERROR(AVERAGEIF(S26:S40,"<>"),0) -> 107.66667
D42: (Should equal 100%)

Sheet Sales per event
A1: TOUR TOTALS - ALL EVENTS COMBINED
A2: Product | B2: Category | C2: Price (incl VAT) | D2: % Sales | E2: Target Rev | F2: Total Units | G2: XS | H2: S | I2: M | J2: L | K2: XL | L2: XXL | M2: XXXL | N2: Rev (incl VAT) | O2: VAT | P2: Rev (ex VAT) | Q2: Unit Cost | R2: COGS | S2: Gross Profit
A3: =IF(Setup!B26="","",Setup!B26) -> Sing Song Black tee | B3: =IF($A3="","",Setup!C26) -> Apparel | C3: =IF($A3="","",Setup!D26) -> 550 | D3: =IF($A3="","",Setup!E26) -> 0.3 | E3: =IF($A3="","",SUM(E23,E44,E65,E86,E107,E128,E149,E170,E191,E212)) -> 265911 | F3: =IF($A3="","",SUM(F23,F44,F65,F86,F107,F128,F149,F170,F191,F212)) -> 485 | G3: =IF($A3="","",SUM(G23,G44,G65,G86,G107,G128,G149,G170,G191,G212)) -> 0 | H3: =IF($A3="","",SUM(H23,H44,H65,H86,H107,H128,H149,H170,H191,H212)) -> 73 | I3: =IF($A3="","",SUM(I23,I44,I65,I86,I107,I128,I149,I170,I191,I212)) -> 122 | J3: =IF($A3="","",SUM(J23,J44,J65,J86,J107,J128,J149,J170,J191,J212)) -> 146 | K3: =IF($A3="","",SUM(K23,K44,K65,K86,K107,K128,K149,K170,K191,K212)) -> 86 | L3: =IF($A3="","",SUM(L23,L44,L65,L86,L107,L128,L149,L170,L191,L212)) -> 58 | ... P3: =IF($A3="","",SUM(P23,P44,P65,P86,P107,P128,P149,P170,P191,P212)) -> 231956.52 | Q3: =IF($A3="","",Setup!S26) -> 169 | R3: =IF($A3="","",SUM(R23,R44,R65,R86,R107,R128,R149,R170,R191,R212)) -> 81965 | S3: =IF($A3="","",SUM(S23,S44,S65,S86,S107,S128,S149,S170,S191,S212)) -> 149991.52
A4: =IF(Setup!B27="","",Setup!B27) -> Kingston Black Tee | B4: =IF($A4="","",Setup!C27) -> Apparel | C4: =IF($A4="","",Setup!D27) -> 550 | D4: =IF($A4="","",Setup!E27) -> 0.2 | E4: =IF($A4="","",SUM(E24,E45,E66,E87,E108,E129,E150,E171,E192,E213)) -> 177274 | F4: =IF($A4="","",SUM(F24,F45,F66,F87,F108,F129,F150,F171,F192,F213)) -> 324 | G4: =IF($A4="","",SUM(G24,G45,G66,G87,G108,G129,G150,G171,G192,G213)) -> 0 | H4: =IF($A4="","",SUM(H24,H45,H66,H87,H108,H129,H150,H171,H192,H213)) -> 50 | I4: =IF($A4="","",SUM(I24,I45,I66,I87,I108,I129,I150,I171,I192,I213)) -> 82 | J4: =IF($A4="","",SUM(J24,J45,J66,J87,J108,J129,J150,J171,J192,J213)) -> 97 | K4: =IF($A4="","",SUM(K24,K45,K66,K87,K108,K129,K150,K171,K192,K213)) -> 58 | L4: =IF($A4="","",SUM(L24,L45,L66,L87,L108,L129,L150,L171,L192,L213)) -> 39 | ... P4: =IF($A4="","",SUM(P24,P45,P66,P87,P108,P129,P150,P171,P192,P213)) -> 154956.52 | Q4: =IF($A4="","",Setup!S27) -> 169 | R4: =IF($A4="","",SUM(R24,R45,R66,R87,R108,R129,R150,R171,R192,R213)) -> 54756 | S4: =IF($A4="","",SUM(S24,S45,S66,S87,S108,S129,S150,S171,S192,S213)) -> 100200.52
A5: =IF(Setup!B28="","",Setup!B28) -> Red Red Wine White tee | B5: =IF($A5="","",Setup!C28) -> Apparel | C5: =IF($A5="","",Setup!D28) -> 550 | D5: =IF($A5="","",Setup!E28) -> 0.3 | E5: =IF($A5="","",SUM(E25,E46,E67,E88,E109,E130,E151,E172,E193,E214)) -> 265911 | F5: =IF($A5="","",SUM(F25,F46,F67,F88,F109,F130,F151,F172,F193,F214)) -> 485 | G5: =IF($A5="","",SUM(G25,G46,G67,G88,G109,G130,G151,G172,G193,G214)) -> 0 | H5: =IF($A5="","",SUM(H25,H46,H67,H88,H109,H130,H151,H172,H193,H214)) -> 73 | I5: =IF($A5="","",SUM(I25,I46,I67,I88,I109,I130,I151,I172,I193,I214)) -> 122 | J5: =IF($A5="","",SUM(J25,J46,J67,J88,J109,J130,J151,J172,J193,J214)) -> 146 | K5: =IF($A5="","",SUM(K25,K46,K67,K88,K109,K130,K151,K172,K193,K214)) -> 86 | L5: =IF($A5="","",SUM(L25,L46,L67,L88,L109,L130,L151,L172,L193,L214)) -> 58 | ... P5: =IF($A5="","",SUM(P25,P46,P67,P88,P109,P130,P151,P172,P193,P214)) -> 231956.52 | Q5: =IF($A5="","",Setup!S28) -> 162 | R5: =IF($A5="","",SUM(R25,R46,R67,R88,R109,R130,R151,R172,R193,R214)) -> 78570 | S5: =IF($A5="","",SUM(S25,S46,S67,S88,S109,S130,S151,S172,S193,S214)) -> 153386.52
A6: =IF(Setup!B29="","",Setup!B29) -> Cap | B6: =IF($A6="","",Setup!C29) -> Accessory | C6: =IF($A6="","",Setup!D29) -> 350 | D6: =IF($A6="","",Setup!E29) -> 0.13 | E6: =IF($A6="","",SUM(E26,E47,E68,E89,E110,E131,E152,E173,E194,E215)) -> 115228.1 | F6: =IF($A6="","",SUM(F26,F47,F68,F89,F110,F131,F152,F173,F194,F215)) -> 331 | G6: =IF($A6="","",SUM(G26,G47,G68,G89,G110,G131,G152,G173,G194,G215)) -> 0 | H6: =IF($A6="","",SUM(H26,H47,H68,H89,H110,H131,H152,H173,H194,H215)) -> 0 | I6: =IF($A6="","",SUM(I26,I47,I68,I89,I110,I131,I152,I173,I194,I215)) -> 0 | J6: =IF($A6="","",SUM(J26,J47,J68,J89,J110,J131,J152,J173,J194,J215)) -> 0 | K6: =IF($A6="","",SUM(K26,K47,K68,K89,K110,K131,K152,K173,K194,K215)) -> 0 | L6: =IF($A6="","",SUM(L26,L47,L68,L89,L110,L131,L152,L173,L194,L215)) -> 0 | ... P6: =IF($A6="","",SUM(P26,P47,P68,P89,P110,P131,P152,P173,P194,P215)) -> 100739.13 | Q6: =IF($A6="","",Setup!S29) -> 96 | R6: =IF($A6="","",SUM(R26,R47,R68,R89,R110,R131,R152,R173,R194,R215)) -> 31776 | S6: =IF($A6="","",SUM(S26,S47,S68,S89,S110,S131,S152,S173,S194,S215)) -> 68963.13
A7: =IF(Setup!B30="","",Setup!B30) -> Tote | B7: =IF($A7="","",Setup!C30) -> Accessory | C7: =IF($A7="","",Setup!D30) -> 100 | D7: =IF($A7="","",Setup!E30) -> 0.07 | E7: =IF($A7="","",SUM(E27,E48,E69,E90,E111,E132,E153,E174,E195,E216)) -> 62045.9 | F7: =IF($A7="","",SUM(F27,F48,F69,F90,F111,F132,F153,F174,F195,F216)) -> 623 | G7: =IF($A7="","",SUM(G27,G48,G69,G90,G111,G132,G153,G174,G195,G216)) -> 0 | H7: =IF($A7="","",SUM(H27,H48,H69,H90,H111,H132,H153,H174,H195,H216)) -> 0 | I7: =IF($A7="","",SUM(I27,I48,I69,I90,I111,I132,I153,I174,I195,I216)) -> 0 | J7: =IF($A7="","",SUM(J27,J48,J69,J90,J111,J132,J153,J174,J195,J216)) -> 0 | K7: =IF($A7="","",SUM(K27,K48,K69,K90,K111,K132,K153,K174,K195,K216)) -> 0 | L7: =IF($A7="","",SUM(L27,L48,L69,L90,L111,L132,L153,L174,L195,L216)) -> 0 | ... P7: =IF($A7="","",SUM(P27,P48,P69,P90,P111,P132,P153,P174,P195,P216)) -> 54173.913 | Q7: =IF($A7="","",Setup!S30) -> 50 | R7: =IF($A7="","",SUM(R27,R48,R69,R90,R111,R132,R153,R174,R195,R216)) -> 31150 | S7: =IF($A7="","",SUM(S27,S48,S69,S90,S111,S132,S153,S174,S195,S216)) -> 23023.913
A8: =IF(Setup!B31="","",Setup!B31) | B8: =IF($A8="","",Setup!C31) | C8: =IF($A8="","",Setup!D31) | D8: =IF($A8="","",Setup!E31) | E8: =IF($A8="","",SUM(E28,E49,E70,E91,E112,E133,E154,E175,E196,E217)) | F8: =IF($A8="","",SUM(F28,F49,F70,F91,F112,F133,F154,F175,F196,F217)) | G8: =IF($A8="","",SUM(G28,G49,G70,G91,G112,G133,G154,G175,G196,G217)) | H8: =IF($A8="","",SUM(H28,H49,H70,H91,H112,H133,H154,H175,H196,H217)) | I8: =IF($A8="","",SUM(I28,I49,I70,I91,I112,I133,I154,I175,I196,I217)) | J8: =IF($A8="","",SUM(J28,J49,J70,J91,J112,J133,J154,J175,J196,J217)) | K8: =IF($A8="","",SUM(K28,K49,K70,K91,K112,K133,K154,K175,K196,K217)) | L8: =IF($A8="","",SUM(L28,L49,L70,L91,L112,L133,L154,L175,L196,L217)) | ... P8: =IF($A8="","",SUM(P28,P49,P70,P91,P112,P133,P154,P175,P196,P217)) | Q8: =IF($A8="","",Setup!S31) | R8: =IF($A8="","",SUM(R28,R49,R70,R91,R112,R133,R154,R175,R196,R217)) | S8: =IF($A8="","",SUM(S28,S49,S70,S91,S112,S133,S154,S175,S196,S217))
A9: =IF(Setup!B32="","",Setup!B32) | B9: =IF($A9="","",Setup!C32) | C9: =IF($A9="","",Setup!D32) | D9: =IF($A9="","",Setup!E32) | E9: =IF($A9="","",SUM(E29,E50,E71,E92,E113,E134,E155,E176,E197,E218)) | F9: =IF($A9="","",SUM(F29,F50,F71,F92,F113,F134,F155,F176,F197,F218)) | G9: =IF($A9="","",SUM(G29,G50,G71,G92,G113,G134,G155,G176,G197,G218)) | H9: =IF($A9="","",SUM(H29,H50,H71,H92,H113,H134,H155,H176,H197,H218)) | I9: =IF($A9="","",SUM(I29,I50,I71,I92,I113,I134,I155,I176,I197,I218)) | J9: =IF($A9="","",SUM(J29,J50,J71,J92,J113,J134,J155,J176,J197,J218)) | K9: =IF($A9="","",SUM(K29,K50,K71,K92,K113,K134,K155,K176,K197,K218)) | L9: =IF($A9="","",SUM(L29,L50,L71,L92,L113,L134,L155,L176,L197,L218)) | ... P9: =IF($A9="","",SUM(P29,P50,P71,P92,P113,P134,P155,P176,P197,P218)) | Q9: =IF($A9="","",Setup!S32) | R9: =IF($A9="","",SUM(R29,R50,R71,R92,R113,R134,R155,R176,R197,R218)) | S9: =IF($A9="","",SUM(S29,S50,S71,S92,S113,S134,S155,S176,S197,S218))
A10: =IF(Setup!B33="","",Setup!B33) | B10: =IF($A10="","",Setup!C33) | C10: =IF($A10="","",Setup!D33) | D10: =IF($A10="","",Setup!E33) | E10: =IF($A10="","",SUM(E30,E51,E72,E93,E114,E135,E156,E177,E198,E219)) | F10: =IF($A10="","",SUM(F30,F51,F72,F93,F114,F135,F156,F177,F198,F219)) | G10: =IF($A10="","",SUM(G30,G51,G72,G93,G114,G135,G156,G177,G198,G219)) | H10: =IF($A10="","",SUM(H30,H51,H72,H93,H114,H135,H156,H177,H198,H219)) | I10: =IF($A10="","",SUM(I30,I51,I72,I93,I114,I135,I156,I177,I198,I219)) | J10: =IF($A10="","",SUM(J30,J51,J72,J93,J114,J135,J156,J177,J198,J219)) | K10: =IF($A10="","",SUM(K30,K51,K72,K93,K114,K135,K156,K177,K198,K219)) | L10: =IF($A10="","",SUM(L30,L51,L72,L93,L114,L135,L156,L177,L198,L219)) | ... P10: =IF($A10="","",SUM(P30,P51,P72,P93,P114,P135,P156,P177,P198,P219)) | Q10: =IF($A10="","",Setup!S33) | R10: =IF($A10="","",SUM(R30,R51,R72,R93,R114,R135,R156,R177,R198,R219)) | S10: =IF($A10="","",SUM(S30,S51,S72,S93,S114,S135,S156,S177,S198,S219))
A11: =IF(Setup!B34="","",Setup!B34) | B11: =IF($A11="","",Setup!C34) | C11: =IF($A11="","",Setup!D34) | D11: =IF($A11="","",Setup!E34) | E11: =IF($A11="","",SUM(E31,E52,E73,E94,E115,E136,E157,E178,E199,E220)) | F11: =IF($A11="","",SUM(F31,F52,F73,F94,F115,F136,F157,F178,F199,F220)) | G11: =IF($A11="","",SUM(G31,G52,G73,G94,G115,G136,G157,G178,G199,G220)) | H11: =IF($A11="","",SUM(H31,H52,H73,H94,H115,H136,H157,H178,H199,H220)) | I11: =IF($A11="","",SUM(I31,I52,I73,I94,I115,I136,I157,I178,I199,I220)) | J11: =IF($A11="","",SUM(J31,J52,J73,J94,J115,J136,J157,J178,J199,J220)) | K11: =IF($A11="","",SUM(K31,K52,K73,K94,K115,K136,K157,K178,K199,K220)) | L11: =IF($A11="","",SUM(L31,L52,L73,L94,L115,L136,L157,L178,L199,L220)) | ... P11: =IF($A11="","",SUM(P31,P52,P73,P94,P115,P136,P157,P178,P199,P220)) | Q11: =IF($A11="","",Setup!S34) | R11: =IF($A11="","",SUM(R31,R52,R73,R94,R115,R136,R157,R178,R199,R220)) | S11: =IF($A11="","",SUM(S31,S52,S73,S94,S115,S136,S157,S178,S199,S220))
A12: =IF(Setup!B35="","",Setup!B35) | B12: =IF($A12="","",Setup!C35) | C12: =IF($A12="","",Setup!D35) | D12: =IF($A12="","",Setup!E35) | E12: =IF($A12="","",SUM(E32,E53,E74,E95,E116,E137,E158,E179,E200,E221)) | F12: =IF($A12="","",SUM(F32,F53,F74,F95,F116,F137,F158,F179,F200,F221)) | G12: =IF($A12="","",SUM(G32,G53,G74,G95,G116,G137,G158,G179,G200,G221)) | H12: =IF($A12="","",SUM(H32,H53,H74,H95,H116,H137,H158,H179,H200,H221)) | I12: =IF($A12="","",SUM(I32,I53,I74,I95,I116,I137,I158,I179,I200,I221)) | J12: =IF($A12="","",SUM(J32,J53,J74,J95,J116,J137,J158,J179,J200,J221)) | K12: =IF($A12="","",SUM(K32,K53,K74,K95,K116,K137,K158,K179,K200,K221)) | L12: =IF($A12="","",SUM(L32,L53,L74,L95,L116,L137,L158,L179,L200,L221)) | ... P12: =IF($A12="","",SUM(P32,P53,P74,P95,P116,P137,P158,P179,P200,P221)) | Q12: =IF($A12="","",Setup!S35) | R12: =IF($A12="","",SUM(R32,R53,R74,R95,R116,R137,R158,R179,R200,R221)) | S12: =IF($A12="","",SUM(S32,S53,S74,S95,S116,S137,S158,S179,S200,S221))
A13: =IF(Setup!B36="","",Setup!B36) | B13: =IF($A13="","",Setup!C36) | C13: =IF($A13="","",Setup!D36) | D13: =IF($A13="","",Setup!E36) | E13: =IF($A13="","",SUM(E33,E54,E75,E96,E117,E138,E159,E180,E201,E222)) | F13: =IF($A13="","",SUM(F33,F54,F75,F96,F117,F138,F159,F180,F201,F222)) | G13: =IF($A13="","",SUM(G33,G54,G75,G96,G117,G138,G159,G180,G201,G222)) | H13: =IF($A13="","",SUM(H33,H54,H75,H96,H117,H138,H159,H180,H201,H222)) | I13: =IF($A13="","",SUM(I33,I54,I75,I96,I117,I138,I159,I180,I201,I222)) | J13: =IF($A13="","",SUM(J33,J54,J75,J96,J117,J138,J159,J180,J201,J222)) | K13: =IF($A13="","",SUM(K33,K54,K75,K96,K117,K138,K159,K180,K201,K222)) | L13: =IF($A13="","",SUM(L33,L54,L75,L96,L117,L138,L159,L180,L201,L222)) | ... P13: =IF($A13="","",SUM(P33,P54,P75,P96,P117,P138,P159,P180,P201,P222)) | Q13: =IF($A13="","",Setup!S36) | R13: =IF($A13="","",SUM(R33,R54,R75,R96,R117,R138,R159,R180,R201,R222)) | S13: =IF($A13="","",SUM(S33,S54,S75,S96,S117,S138,S159,S180,S201,S222))
A14: =IF(Setup!B37="","",Setup!B37) | B14: =IF($A14="","",Setup!C37) | C14: =IF($A14="","",Setup!D37) | D14: =IF($A14="","",Setup!E37) | E14: =IF($A14="","",SUM(E34,E55,E76,E97,E118,E139,E160,E181,E202,E223)) | F14: =IF($A14="","",SUM(F34,F55,F76,F97,F118,F139,F160,F181,F202,F223)) | G14: =IF($A14="","",SUM(G34,G55,G76,G97,G118,G139,G160,G181,G202,G223)) | H14: =IF($A14="","",SUM(H34,H55,H76,H97,H118,H139,H160,H181,H202,H223)) | I14: =IF($A14="","",SUM(I34,I55,I76,I97,I118,I139,I160,I181,I202,I223)) | J14: =IF($A14="","",SUM(J34,J55,J76,J97,J118,J139,J160,J181,J202,J223)) | K14: =IF($A14="","",SUM(K34,K55,K76,K97,K118,K139,K160,K181,K202,K223)) | L14: =IF($A14="","",SUM(L34,L55,L76,L97,L118,L139,L160,L181,L202,L223)) | ... P14: =IF($A14="","",SUM(P34,P55,P76,P97,P118,P139,P160,P181,P202,P223)) | Q14: =IF($A14="","",Setup!S37) | R14: =IF($A14="","",SUM(R34,R55,R76,R97,R118,R139,R160,R181,R202,R223)) | S14: =IF($A14="","",SUM(S34,S55,S76,S97,S118,S139,S160,S181,S202,S223))
... A17: =IF(Setup!B40="","",Setup!B40) | B17: =IF($A17="","",Setup!C40) | C17: =IF($A17="","",Setup!D40) | D17: =IF($A17="","",Setup!E40) | E17: =IF($A17="","",SUM(E37,E58,E79,E100,E121,E142,E163,E184,E205,E226)) | F17: =IF($A17="","",SUM(F37,F58,F79,F100,F121,F142,F163,F184,F205,F226)) | G17: =IF($A17="","",SUM(G37,G58,G79,G100,G121,G142,G163,G184,G205,G226)) | H17: =IF($A17="","",SUM(H37,H58,H79,H100,H121,H142,H163,H184,H205,H226)) | I17: =IF($A17="","",SUM(I37,I58,I79,I100,I121,I142,I163,I184,I205,I226)) | J17: =IF($A17="","",SUM(J37,J58,J79,J100,J121,J142,J163,J184,J205,J226)) | K17: =IF($A17="","",SUM(K37,K58,K79,K100,K121,K142,K163,K184,K205,K226)) | L17: =IF($A17="","",SUM(L37,L58,L79,L100,L121,L142,L163,L184,L205,L226)) | ... P17: =IF($A17="","",SUM(P37,P58,P79,P100,P121,P142,P163,P184,P205,P226)) | Q17: =IF($A17="","",Setup!S40) | R17: =IF($A17="","",SUM(R37,R58,R79,R100,R121,R142,R163,R184,R205,R226)) | S17: =IF($A17="","",SUM(S37,S58,S79,S100,S121,S142,S163,S184,S205,S226))
A18: GRAND TOTAL | E18: =SUM(E3:E17) -> 886370 | F18: =SUM(F3:F17) -> 2248 | G18: =SUM(G3:G17) -> 0 | H18: =SUM(H3:H17) -> 196 | I18: =SUM(I3:I17) -> 326 | J18: =SUM(J3:J17) -> 389 | K18: =SUM(K3:K17) -> 230 | L18: =SUM(L3:L17) -> 155 | ... P18: =SUM(P3:P17) -> 773782.61 | R18: =SUM(R3:R17) -> 278217 | S18: =SUM(S3:S17) -> 495565.61
A20: =IF(Setup!C9="","Event 1: Not configured",UPPER(Setup!C9&" - "&Setup!D9&" | "&TEXT(Setup!B9,"DD MMM YYYY"))) -> CAPE TOWN - GRAND ARENA AT GRANDWEST | 02 JUN 2026 | N20: GROSS TARGET (incl VAT): | Q20: =Setup!I9 -> 157620
A21: Attendance: | B21: =Setup!F9 -> 5254 | D21: Stalls: | E21: =Setup!G9 -> 1 | G21: Spend/Head: | H21: =Setup!H9 -> 30 | J21: VAT Rate: | K21: =Setup!B6 -> 0.15 | M21: Flights: | N21: =Setup!J9 -> 0 | P21: Sales Ops: | Q21: =Setup!L9 -> 50000 | R21: CC Fee: | S21: =Setup!M9 -> 0.032
A22: Product | B22: Category | C22: Price (incl VAT) | D22: % Sales | E22: Target Rev | F22: Total Units | G22: XS | H22: S | I22: M | J22: L | K22: XL | L22: XXL | M22: XXXL | N22: Rev (incl VAT) | O22: VAT | P22: Rev (ex VAT) | Q22: Unit Cost | R22: COGS | S22: Gross Profit
A23: =IF(Setup!B26="","",Setup!B26) -> Sing Song Black tee | B23: =IF($A23="","",Setup!C26) -> Apparel | C23: =IF($A23="","",Setup!D26) -> 550 | D23: =IF($A23="","",Setup!E26) -> 0.3 | E23: =IF(OR($A23="",$Q$20=""),"",$Q$20*D23) -> 47286 | F23: =IF(OR($A23="",C23=0,E23=""),"",ROUNDUP(E23/C23,0)) -> 86 | G23: =IF(OR($A23="",F23=""),"",ROUND(F23*Setup!F26,0)) -> 0 | H23: =IF(OR($A23="",F23=""),"",ROUND(F23*Setup!G26,0)) -> 13 | I23: =IF(OR($A23="",F23=""),"",ROUND(F23*Setup!H26,0)) -> 22 | J23: =IF(OR($A23="",F23=""),"",ROUND(F23*Setup!I26,0)) -> 26 | K23: =IF(OR($A23="",F23=""),"",ROUND(F23*Setup!J26,0)) -> 15 | L23: =IF(OR($A23="",F23=""),"",ROUND(F23*Setup!K26,0)) -> 10 | M23: =IF(OR($A23="",F23=""),"",ROUND(F23*Setup!L26,0)) -> 0 | N23: =IF(OR($A23="",F23=""),"",F23*C23) -> 47300 | O23: =IF(OR($A23="",N23=""),"",N23*Setup!$B$6/(1+Setup!$B$6)) -> 6169.5652 | P23: =IF(OR($A23="",N23=""),"",N23-O23) -> 41130.435 | Q23: =IF($A23="","",Setup!S26) -> 169 | R23: =IF(OR($A23="",F23="",Q23=""),"",F23*Q23) -> 14534 | S23: =IF(OR($A23="",P23="",R23=""),"",P23-R23) -> 26596.435
A24: =IF(Setup!B27="","",Setup!B27) -> Kingston Black Tee | B24: =IF($A24="","",Setup!C27) -> Apparel | C24: =IF($A24="","",Setup!D27) -> 550 | D24: =IF($A24="","",Setup!E27) -> 0.2 | E24: =IF(OR($A24="",$Q$20=""),"",$Q$20*D24) -> 31524 | F24: =IF(OR($A24="",C24=0,E24=""),"",ROUNDUP(E24/C24,0)) -> 58 | G24: =IF(OR($A24="",F24=""),"",ROUND(F24*Setup!F27,0)) -> 0 | H24: =IF(OR($A24="",F24=""),"",ROUND(F24*Setup!G27,0)) -> 9 | I24: =IF(OR($A24="",F24=""),"",ROUND(F24*Setup!H27,0)) -> 15 | J24: =IF(OR($A24="",F24=""),"",ROUND(F24*Setup!I27,0)) -> 17 | K24: =IF(OR($A24="",F24=""),"",ROUND(F24*Setup!J27,0)) -> 10 | L24: =IF(OR($A24="",F24=""),"",ROUND(F24*Setup!K27,0)) -> 7 | M24: =IF(OR($A24="",F24=""),"",ROUND(F24*Setup!L27,0)) -> 0 | N24: =IF(OR($A24="",F24=""),"",F24*C24) -> 31900 | O24: =IF(OR($A24="",N24=""),"",N24*Setup!$B$6/(1+Setup!$B$6)) -> 4160.8696 | P24: =IF(OR($A24="",N24=""),"",N24-O24) -> 27739.13 | Q24: =IF($A24="","",Setup!S27) -> 169 | R24: =IF(OR($A24="",F24="",Q24=""),"",F24*Q24) -> 9802 | S24: =IF(OR($A24="",P24="",R24=""),"",P24-R24) -> 17937.13
A25: =IF(Setup!B28="","",Setup!B28) -> Red Red Wine White tee | B25: =IF($A25="","",Setup!C28) -> Apparel | C25: =IF($A25="","",Setup!D28) -> 550 | D25: =IF($A25="","",Setup!E28) -> 0.3 | E25: =IF(OR($A25="",$Q$20=""),"",$Q$20*D25) -> 47286 | F25: =IF(OR($A25="",C25=0,E25=""),"",ROUNDUP(E25/C25,0)) -> 86 | G25: =IF(OR($A25="",F25=""),"",ROUND(F25*Setup!F28,0)) -> 0 | H25: =IF(OR($A25="",F25=""),"",ROUND(F25*Setup!G28,0)) -> 13 | I25: =IF(OR($A25="",F25=""),"",ROUND(F25*Setup!H28,0)) -> 22 | J25: =IF(OR($A25="",F25=""),"",ROUND(F25*Setup!I28,0)) -> 26 | K25: =IF(OR($A25="",F25=""),"",ROUND(F25*Setup!J28,0)) -> 15 | L25: =IF(OR($A25="",F25=""),"",ROUND(F25*Setup!K28,0)) -> 10 | M25: =IF(OR($A25="",F25=""),"",ROUND(F25*Setup!L28,0)) -> 0 | N25: =IF(OR($A25="",F25=""),"",F25*C25) -> 47300 | O25: =IF(OR($A25="",N25=""),"",N25*Setup!$B$6/(1+Setup!$B$6)) -> 6169.5652 | P25: =IF(OR($A25="",N25=""),"",N25-O25) -> 41130.435 | Q25: =IF($A25="","",Setup!S28) -> 162 | R25: =IF(OR($A25="",F25="",Q25=""),"",F25*Q25) -> 13932 | S25: =IF(OR($A25="",P25="",R25=""),"",P25-R25) -> 27198.435
A26: =IF(Setup!B29="","",Setup!B29) -> Cap | B26: =IF($A26="","",Setup!C29) -> Accessory | C26: =IF($A26="","",Setup!D29) -> 350 | D26: =IF($A26="","",Setup!E29) -> 0.13 | E26: =IF(OR($A26="",$Q$20=""),"",$Q$20*D26) -> 20490.6 | F26: =IF(OR($A26="",C26=0,E26=""),"",ROUNDUP(E26/C26,0)) -> 59 | G26: =IF(OR($A26="",F26=""),"",ROUND(F26*Setup!F29,0)) -> 0 | H26: =IF(OR($A26="",F26=""),"",ROUND(F26*Setup!G29,0)) -> 0 | I26: =IF(OR($A26="",F26=""),"",ROUND(F26*Setup!H29,0)) -> 0 | J26: =IF(OR($A26="",F26=""),"",ROUND(F26*Setup!I29,0)) -> 0 | K26: =IF(OR($A26="",F26=""),"",ROUND(F26*Setup!J29,0)) -> 0 | L26: =IF(OR($A26="",F26=""),"",ROUND(F26*Setup!K29,0)) -> 0 | M26: =IF(OR($A26="",F26=""),"",ROUND(F26*Setup!L29,0)) -> 0 | N26: =IF(OR($A26="",F26=""),"",F26*C26) -> 20650 | O26: =IF(OR($A26="",N26=""),"",N26*Setup!$B$6/(1+Setup!$B$6)) -> 2693.4783 | P26: =IF(OR($A26="",N26=""),"",N26-O26) -> 17956.522 | Q26: =IF($A26="","",Setup!S29) -> 96 | R26: =IF(OR($A26="",F26="",Q26=""),"",F26*Q26) -> 5664 | S26: =IF(OR($A26="",P26="",R26=""),"",P26-R26) -> 12292.522
A27: =IF(Setup!B30="","",Setup!B30) -> Tote | B27: =IF($A27="","",Setup!C30) -> Accessory | C27: =IF($A27="","",Setup!D30) -> 100 | D27: =IF($A27="","",Setup!E30) -> 0.07 | E27: =IF(OR($A27="",$Q$20=""),"",$Q$20*D27) -> 11033.4 | F27: =IF(OR($A27="",C27=0,E27=""),"",ROUNDUP(E27/C27,0)) -> 111 | G27: =IF(OR($A27="",F27=""),"",ROUND(F27*Setup!F30,0)) -> 0 | H27: =IF(OR($A27="",F27=""),"",ROUND(F27*Setup!G30,0)) -> 0 | I27: =IF(OR($A27="",F27=""),"",ROUND(F27*Setup!H30,0)) -> 0 | J27: =IF(OR($A27="",F27=""),"",ROUND(F27*Setup!I30,0)) -> 0 | K27: =IF(OR($A27="",F27=""),"",ROUND(F27*Setup!J30,0)) -> 0 | L27: =IF(OR($A27="",F27=""),"",ROUND(F27*Setup!K30,0)) -> 0 | M27: =IF(OR($A27="",F27=""),"",ROUND(F27*Setup!L30,0)) -> 0 | N27: =IF(OR($A27="",F27=""),"",F27*C27) -> 11100 | O27: =IF(OR($A27="",N27=""),"",N27*Setup!$B$6/(1+Setup!$B$6)) -> 1447.8261 | P27: =IF(OR($A27="",N27=""),"",N27-O27) -> 9652.1739 | Q27: =IF($A27="","",Setup!S30) -> 50 | R27: =IF(OR($A27="",F27="",Q27=""),"",F27*Q27) -> 5550 | S27: =IF(OR($A27="",P27="",R27=""),"",P27-R27) -> 4102.1739
A28: =IF(Setup!B31="","",Setup!B31) | B28: =IF($A28="","",Setup!C31) | C28: =IF($A28="","",Setup!D31) | D28: =IF($A28="","",Setup!E31) | E28: =IF(OR($A28="",$Q$20=""),"",$Q$20*D28) | F28: =IF(OR($A28="",C28=0,E28=""),"",ROUNDUP(E28/C28,0)) | G28: =IF(OR($A28="",F28=""),"",ROUND(F28*Setup!F31,0)) | H28: =IF(OR($A28="",F28=""),"",ROUND(F28*Setup!G31,0)) | I28: =IF(OR($A28="",F28=""),"",ROUND(F28*Setup!H31,0)) | J28: =IF(OR($A28="",F28=""),"",ROUND(F28*Setup!I31,0)) | K28: =IF(OR($A28="",F28=""),"",ROUND(F28*Setup!J31,0)) | L28: =IF(OR($A28="",F28=""),"",ROUND(F28*Setup!K31,0)) | M28: =IF(OR($A28="",F28=""),"",ROUND(F28*Setup!L31,0)) | N28: =IF(OR($A28="",F28=""),"",F28*C28) | O28: =IF(OR($A28="",N28=""),"",N28*Setup!$B$6/(1+Setup!$B$6)) | P28: =IF(OR($A28="",N28=""),"",N28-O28) | Q28: =IF($A28="","",Setup!S31) | R28: =IF(OR($A28="",F28="",Q28=""),"",F28*Q28) | S28: =IF(OR($A28="",P28="",R28=""),"",P28-R28)
A29: =IF(Setup!B32="","",Setup!B32) | B29: =IF($A29="","",Setup!C32) | C29: =IF($A29="","",Setup!D32) | D29: =IF($A29="","",Setup!E32) | E29: =IF(OR($A29="",$Q$20=""),"",$Q$20*D29) | F29: =IF(OR($A29="",C29=0,E29=""),"",ROUNDUP(E29/C29,0)) | G29: =IF(OR($A29="",F29=""),"",ROUND(F29*Setup!F32,0)) | H29: =IF(OR($A29="",F29=""),"",ROUND(F29*Setup!G32,0)) | I29: =IF(OR($A29="",F29=""),"",ROUND(F29*Setup!H32,0)) | J29: =IF(OR($A29="",F29=""),"",ROUND(F29*Setup!I32,0)) | K29: =IF(OR($A29="",F29=""),"",ROUND(F29*Setup!J32,0)) | L29: =IF(OR($A29="",F29=""),"",ROUND(F29*Setup!K32,0)) | M29: =IF(OR($A29="",F29=""),"",ROUND(F29*Setup!L32,0)) | N29: =IF(OR($A29="",F29=""),"",F29*C29) | O29: =IF(OR($A29="",N29=""),"",N29*Setup!$B$6/(1+Setup!$B$6)) | P29: =IF(OR($A29="",N29=""),"",N29-O29) | Q29: =IF($A29="","",Setup!S32) | R29: =IF(OR($A29="",F29="",Q29=""),"",F29*Q29) | S29: =IF(OR($A29="",P29="",R29=""),"",P29-R29)
A30: =IF(Setup!B33="","",Setup!B33) | B30: =IF($A30="","",Setup!C33) | C30: =IF($A30="","",Setup!D33) | D30: =IF($A30="","",Setup!E33) | E30: =IF(OR($A30="",$Q$20=""),"",$Q$20*D30) | F30: =IF(OR($A30="",C30=0,E30=""),"",ROUNDUP(E30/C30,0)) | G30: =IF(OR($A30="",F30=""),"",ROUND(F30*Setup!F33,0)) | H30: =IF(OR($A30="",F30=""),"",ROUND(F30*Setup!G33,0)) | I30: =IF(OR($A30="",F30=""),"",ROUND(F30*Setup!H33,0)) | J30: =IF(OR($A30="",F30=""),"",ROUND(F30*Setup!I33,0)) | K30: =IF(OR($A30="",F30=""),"",ROUND(F30*Setup!J33,0)) | L30: =IF(OR($A30="",F30=""),"",ROUND(F30*Setup!K33,0)) | M30: =IF(OR($A30="",F30=""),"",ROUND(F30*Setup!L33,0)) | N30: =IF(OR($A30="",F30=""),"",F30*C30) | O30: =IF(OR($A30="",N30=""),"",N30*Setup!$B$6/(1+Setup!$B$6)) | P30: =IF(OR($A30="",N30=""),"",N30-O30) | Q30: =IF($A30="","",Setup!S33) | R30: =IF(OR($A30="",F30="",Q30=""),"",F30*Q30) | S30: =IF(OR($A30="",P30="",R30=""),"",P30-R30)
A31: =IF(Setup!B34="","",Setup!B34) | B31: =IF($A31="","",Setup!C34) | C31: =IF($A31="","",Setup!D34) | D31: =IF($A31="","",Setup!E34) | E31: =IF(OR($A31="",$Q$20=""),"",$Q$20*D31) | F31: =IF(OR($A31="",C31=0,E31=""),"",ROUNDUP(E31/C31,0)) | G31: =IF(OR($A31="",F31=""),"",ROUND(F31*Setup!F34,0)) | H31: =IF(OR($A31="",F31=""),"",ROUND(F31*Setup!G34,0)) | I31: =IF(OR($A31="",F31=""),"",ROUND(F31*Setup!H34,0)) | J31: =IF(OR($A31="",F31=""),"",ROUND(F31*Setup!I34,0)) | K31: =IF(OR($A31="",F31=""),"",ROUND(F31*Setup!J34,0)) | L31: =IF(OR($A31="",F31=""),"",ROUND(F31*Setup!K34,0)) | M31: =IF(OR($A31="",F31=""),"",ROUND(F31*Setup!L34,0)) | N31: =IF(OR($A31="",F31=""),"",F31*C31) | O31: =IF(OR($A31="",N31=""),"",N31*Setup!$B$6/(1+Setup!$B$6)) | P31: =IF(OR($A31="",N31=""),"",N31-O31) | Q31: =IF($A31="","",Setup!S34) | R31: =IF(OR($A31="",F31="",Q31=""),"",F31*Q31) | S31: =IF(OR($A31="",P31="",R31=""),"",P31-R31)
A32: =IF(Setup!B35="","",Setup!B35) | B32: =IF($A32="","",Setup!C35) | C32: =IF($A32="","",Setup!D35) | D32: =IF($A32="","",Setup!E35) | E32: =IF(OR($A32="",$Q$20=""),"",$Q$20*D32) | F32: =IF(OR($A32="",C32=0,E32=""),"",ROUNDUP(E32/C32,0)) | G32: =IF(OR($A32="",F32=""),"",ROUND(F32*Setup!F35,0)) | H32: =IF(OR($A32="",F32=""),"",ROUND(F32*Setup!G35,0)) | I32: =IF(OR($A32="",F32=""),"",ROUND(F32*Setup!H35,0)) | J32: =IF(OR($A32="",F32=""),"",ROUND(F32*Setup!I35,0)) | K32: =IF(OR($A32="",F32=""),"",ROUND(F32*Setup!J35,0)) | L32: =IF(OR($A32="",F32=""),"",ROUND(F32*Setup!K35,0)) | M32: =IF(OR($A32="",F32=""),"",ROUND(F32*Setup!L35,0)) | N32: =IF(OR($A32="",F32=""),"",F32*C32) | O32: =IF(OR($A32="",N32=""),"",N32*Setup!$B$6/(1+Setup!$B$6)) | P32: =IF(OR($A32="",N32=""),"",N32-O32) | Q32: =IF($A32="","",Setup!S35) | R32: =IF(OR($A32="",F32="",Q32=""),"",F32*Q32) | S32: =IF(OR($A32="",P32="",R32=""),"",P32-R32)
A33: =IF(Setup!B36="","",Setup!B36) | B33: =IF($A33="","",Setup!C36) | C33: =IF($A33="","",Setup!D36) | D33: =IF($A33="","",Setup!E36) | E33: =IF(OR($A33="",$Q$20=""),"",$Q$20*D33) | F33: =IF(OR($A33="",C33=0,E33=""),"",ROUNDUP(E33/C33,0)) | G33: =IF(OR($A33="",F33=""),"",ROUND(F33*Setup!F36,0)) | H33: =IF(OR($A33="",F33=""),"",ROUND(F33*Setup!G36,0)) | I33: =IF(OR($A33="",F33=""),"",ROUND(F33*Setup!H36,0)) | J33: =IF(OR($A33="",F33=""),"",ROUND(F33*Setup!I36,0)) | K33: =IF(OR($A33="",F33=""),"",ROUND(F33*Setup!J36,0)) | L33: =IF(OR($A33="",F33=""),"",ROUND(F33*Setup!K36,0)) | M33: =IF(OR($A33="",F33=""),"",ROUND(F33*Setup!L36,0)) | N33: =IF(OR($A33="",F33=""),"",F33*C33) | O33: =IF(OR($A33="",N33=""),"",N33*Setup!$B$6/(1+Setup!$B$6)) | P33: =IF(OR($A33="",N33=""),"",N33-O33) | Q33: =IF($A33="","",Setup!S36) | R33: =IF(OR($A33="",F33="",Q33=""),"",F33*Q33) | S33: =IF(OR($A33="",P33="",R33=""),"",P33-R33)
A34: =IF(Setup!B37="","",Setup!B37) | B34: =IF($A34="","",Setup!C37) | C34: =IF($A34="","",Setup!D37) | D34: =IF($A34="","",Setup!E37) | E34: =IF(OR($A34="",$Q$20=""),"",$Q$20*D34) | F34: =IF(OR($A34="",C34=0,E34=""),"",ROUNDUP(E34/C34,0)) | G34: =IF(OR($A34="",F34=""),"",ROUND(F34*Setup!F37,0)) | H34: =IF(OR($A34="",F34=""),"",ROUND(F34*Setup!G37,0)) | I34: =IF(OR($A34="",F34=""),"",ROUND(F34*Setup!H37,0)) | J34: =IF(OR($A34="",F34=""),"",ROUND(F34*Setup!I37,0)) | K34: =IF(OR($A34="",F34=""),"",ROUND(F34*Setup!J37,0)) | L34: =IF(OR($A34="",F34=""),"",ROUND(F34*Setup!K37,0)) | M34: =IF(OR($A34="",F34=""),"",ROUND(F34*Setup!L37,0)) | N34: =IF(OR($A34="",F34=""),"",F34*C34) | O34: =IF(OR($A34="",N34=""),"",N34*Setup!$B$6/(1+Setup!$B$6)) | P34: =IF(OR($A34="",N34=""),"",N34-O34) | Q34: =IF($A34="","",Setup!S37) | R34: =IF(OR($A34="",F34="",Q34=""),"",F34*Q34) | S34: =IF(OR($A34="",P34="",R34=""),"",P34-R34)
... A37: =IF(Setup!B40="","",Setup!B40) | B37: =IF($A37="","",Setup!C40) | C37: =IF($A37="","",Setup!D40) | D37: =IF($A37="","",Setup!E40) | E37: =IF(OR($A37="",$Q$20=""),"",$Q$20*D37) | F37: =IF(OR($A37="",C37=0,E37=""),"",ROUNDUP(E37/C37,0)) | G37: =IF(OR($A37="",F37=""),"",ROUND(F37*Setup!F40,0)) | H37: =IF(OR($A37="",F37=""),"",ROUND(F37*Setup!G40,0)) | I37: =IF(OR($A37="",F37=""),"",ROUND(F37*Setup!H40,0)) | J37: =IF(OR($A37="",F37=""),"",ROUND(F37*Setup!I40,0)) | K37: =IF(OR($A37="",F37=""),"",ROUND(F37*Setup!J40,0)) | L37: =IF(OR($A37="",F37=""),"",ROUND(F37*Setup!K40,0)) | M37: =IF(OR($A37="",F37=""),"",ROUND(F37*Setup!L40,0)) | N37: =IF(OR($A37="",F37=""),"",F37*C37) | O37: =IF(OR($A37="",N37=""),"",N37*Setup!$B$6/(1+Setup!$B$6)) | P37: =IF(OR($A37="",N37=""),"",N37-O37) | Q37: =IF($A37="","",Setup!S40) | R37: =IF(OR($A37="",F37="",Q37=""),"",F37*Q37) | S37: =IF(OR($A37="",P37="",R37=""),"",P37-R37)
A38: TOTAL | E38: =SUM(E23:E37) -> 157620 | F38: =SUM(F23:F37) -> 400 | G38: =SUM(G23:G37) -> 0 | H38: =SUM(H23:H37) -> 35 | I38: =SUM(I23:I37) -> 59 | J38: =SUM(J23:J37) -> 69 | K38: =SUM(K23:K37) -> 40 | L38: =SUM(L23:L37) -> 27 | ... P38: =SUM(P23:P37) -> 137608.7 | R38: =SUM(R23:R37) -> 49482 | S38: =SUM(S23:S37) -> 88126.696
A41: =IF(Setup!C10="","Event 2: Not configured",UPPER(Setup!C10&" - "&Setup!D10&" | "&TEXT(Setup!B10,"DD MMM YYYY"))) -> DURBAN - DURBAN ICC | 04 JUN 2026 | N41: GROSS TARGET (incl VAT): | Q41: =Setup!I10 -> 156000
A42: Attendance: | B42: =Setup!F10 -> 5200 | D42: Stalls: | E42: =Setup!G10 -> 1 | G42: Spend/Head: | H42: =Setup!H10 -> 30 | J42: VAT Rate: | K42: =Setup!B6 -> 0.15 | M42: Flights: | N42: =Setup!J10 -> 0 | P42: Sales Ops: | Q42: =Setup!L10 -> 50000 | R42: CC Fee: | S42: =Setup!M10 -> 0.032
A43: Product | B43: Category | C43: Price (incl VAT) | D43: % Sales | E43: Target Rev | F43: Total Units | G43: XS | H43: S | I43: M | J43: L | K43: XL | L43: XXL | M43: XXXL | N43: Rev (incl VAT) | O43: VAT | P43: Rev (ex VAT) | Q43: Unit Cost | R43: COGS | S43: Gross Profit
A44: =IF(Setup!B26="","",Setup!B26) -> Sing Song Black tee | B44: =IF($A44="","",Setup!C26) -> Apparel | C44: =IF($A44="","",Setup!D26) -> 550 | D44: =IF($A44="","",Setup!E26) -> 0.3 | E44: =IF(OR($A44="",$Q$41=""),"",$Q$41*D44) -> 46800 | F44: =IF(OR($A44="",C44=0,E44=""),"",ROUNDUP(E44/C44,0)) -> 86 | G44: =IF(OR($A44="",F44=""),"",ROUND(F44*Setup!F26,0)) -> 0 | H44: =IF(OR($A44="",F44=""),"",ROUND(F44*Setup!G26,0)) -> 13 | I44: =IF(OR($A44="",F44=""),"",ROUND(F44*Setup!H26,0)) -> 22 | J44: =IF(OR($A44="",F44=""),"",ROUND(F44*Setup!I26,0)) -> 26 | K44: =IF(OR($A44="",F44=""),"",ROUND(F44*Setup!J26,0)) -> 15 | L44: =IF(OR($A44="",F44=""),"",ROUND(F44*Setup!K26,0)) -> 10 | M44: =IF(OR($A44="",F44=""),"",ROUND(F44*Setup!L26,0)) -> 0 | N44: =IF(OR($A44="",F44=""),"",F44*C44) -> 47300 | O44: =IF(OR($A44="",N44=""),"",N44*Setup!$B$6/(1+Setup!$B$6)) -> 6169.5652 | P44: =IF(OR($A44="",N44=""),"",N44-O44) -> 41130.435 | Q44: =IF($A44="","",Setup!S26) -> 169 | R44: =IF(OR($A44="",F44="",Q44=""),"",F44*Q44) -> 14534 | S44: =IF(OR($A44="",P44="",R44=""),"",P44-R44) -> 26596.435
A45: =IF(Setup!B27="","",Setup!B27) -> Kingston Black Tee | B45: =IF($A45="","",Setup!C27) -> Apparel | C45: =IF($A45="","",Setup!D27) -> 550 | D45: =IF($A45="","",Setup!E27) -> 0.2 | E45: =IF(OR($A45="",$Q$41=""),"",$Q$41*D45) -> 31200 | F45: =IF(OR($A45="",C45=0,E45=""),"",ROUNDUP(E45/C45,0)) -> 57 | G45: =IF(OR($A45="",F45=""),"",ROUND(F45*Setup!F27,0)) -> 0 | H45: =IF(OR($A45="",F45=""),"",ROUND(F45*Setup!G27,0)) -> 9 | I45: =IF(OR($A45="",F45=""),"",ROUND(F45*Setup!H27,0)) -> 14 | J45: =IF(OR($A45="",F45=""),"",ROUND(F45*Setup!I27,0)) -> 17 | K45: =IF(OR($A45="",F45=""),"",ROUND(F45*Setup!J27,0)) -> 10 | L45: =IF(OR($A45="",F45=""),"",ROUND(F45*Setup!K27,0)) -> 7 | M45: =IF(OR($A45="",F45=""),"",ROUND(F45*Setup!L27,0)) -> 0 | N45: =IF(OR($A45="",F45=""),"",F45*C45) -> 31350 | O45: =IF(OR($A45="",N45=""),"",N45*Setup!$B$6/(1+Setup!$B$6)) -> 4089.1304 | P45: =IF(OR($A45="",N45=""),"",N45-O45) -> 27260.87 | Q45: =IF($A45="","",Setup!S27) -> 169 | R45: =IF(OR($A45="",F45="",Q45=""),"",F45*Q45) -> 9633 | S45: =IF(OR($A45="",P45="",R45=""),"",P45-R45) -> 17627.87
A46: =IF(Setup!B28="","",Setup!B28) -> Red Red Wine White tee | B46: =IF($A46="","",Setup!C28) -> Apparel | C46: =IF($A46="","",Setup!D28) -> 550 | D46: =IF($A46="","",Setup!E28) -> 0.3 | E46: =IF(OR($A46="",$Q$41=""),"",$Q$41*D46) -> 46800 | F46: =IF(OR($A46="",C46=0,E46=""),"",ROUNDUP(E46/C46,0)) -> 86 | G46: =IF(OR($A46="",F46=""),"",ROUND(F46*Setup!F28,0)) -> 0 | H46: =IF(OR($A46="",F46=""),"",ROUND(F46*Setup!G28,0)) -> 13 | I46: =IF(OR($A46="",F46=""),"",ROUND(F46*Setup!H28,0)) -> 22 | J46: =IF(OR($A46="",F46=""),"",ROUND(F46*Setup!I28,0)) -> 26 | K46: =IF(OR($A46="",F46=""),"",ROUND(F46*Setup!J28,0)) -> 15 | L46: =IF(OR($A46="",F46=""),"",ROUND(F46*Setup!K28,0)) -> 10 | M46: =IF(OR($A46="",F46=""),"",ROUND(F46*Setup!L28,0)) -> 0 | N46: =IF(OR($A46="",F46=""),"",F46*C46) -> 47300 | O46: =IF(OR($A46="",N46=""),"",N46*Setup!$B$6/(1+Setup!$B$6)) -> 6169.5652 | P46: =IF(OR($A46="",N46=""),"",N46-O46) -> 41130.435 | Q46: =IF($A46="","",Setup!S28) -> 162 | R46: =IF(OR($A46="",F46="",Q46=""),"",F46*Q46) -> 13932 | S46: =IF(OR($A46="",P46="",R46=""),"",P46-R46) -> 27198.435
A47: =IF(Setup!B29="","",Setup!B29) -> Cap | B47: =IF($A47="","",Setup!C29) -> Accessory | C47: =IF($A47="","",Setup!D29) -> 350 | D47: =IF($A47="","",Setup!E29) -> 0.13 | E47: =IF(OR($A47="",$Q$41=""),"",$Q$41*D47) -> 20280 | F47: =IF(OR($A47="",C47=0,E47=""),"",ROUNDUP(E47/C47,0)) -> 58 | G47: =IF(OR($A47="",F47=""),"",ROUND(F47*Setup!F29,0)) -> 0 | H47: =IF(OR($A47="",F47=""),"",ROUND(F47*Setup!G29,0)) -> 0 | I47: =IF(OR($A47="",F47=""),"",ROUND(F47*Setup!H29,0)) -> 0 | J47: =IF(OR($A47="",F47=""),"",ROUND(F47*Setup!I29,0)) -> 0 | K47: =IF(OR($A47="",F47=""),"",ROUND(F47*Setup!J29,0)) -> 0 | L47: =IF(OR($A47="",F47=""),"",ROUND(F47*Setup!K29,0)) -> 0 | M47: =IF(OR($A47="",F47=""),"",ROUND(F47*Setup!L29,0)) -> 0 | N47: =IF(OR($A47="",F47=""),"",F47*C47) -> 20300 | O47: =IF(OR($A47="",N47=""),"",N47*Setup!$B$6/(1+Setup!$B$6)) -> 2647.8261 | P47: =IF(OR($A47="",N47=""),"",N47-O47) -> 17652.174 | Q47: =IF($A47="","",Setup!S29) -> 96 | R47: =IF(OR($A47="",F47="",Q47=""),"",F47*Q47) -> 5568 | S47: =IF(OR($A47="",P47="",R47=""),"",P47-R47) -> 12084.174
A48: =IF(Setup!B30="","",Setup!B30) -> Tote | B48: =IF($A48="","",Setup!C30) -> Accessory | C48: =IF($A48="","",Setup!D30) -> 100 | D48: =IF($A48="","",Setup!E30) -> 0.07 | E48: =IF(OR($A48="",$Q$41=""),"",$Q$41*D48) -> 10920 | F48: =IF(OR($A48="",C48=0,E48=""),"",ROUNDUP(E48/C48,0)) -> 110 | G48: =IF(OR($A48="",F48=""),"",ROUND(F48*Setup!F30,0)) -> 0 | H48: =IF(OR($A48="",F48=""),"",ROUND(F48*Setup!G30,0)) -> 0 | I48: =IF(OR($A48="",F48=""),"",ROUND(F48*Setup!H30,0)) -> 0 | J48: =IF(OR($A48="",F48=""),"",ROUND(F48*Setup!I30,0)) -> 0 | K48: =IF(OR($A48="",F48=""),"",ROUND(F48*Setup!J30,0)) -> 0 | L48: =IF(OR($A48="",F48=""),"",ROUND(F48*Setup!K30,0)) -> 0 | M48: =IF(OR($A48="",F48=""),"",ROUND(F48*Setup!L30,0)) -> 0 | N48: =IF(OR($A48="",F48=""),"",F48*C48) -> 11000 | O48: =IF(OR($A48="",N48=""),"",N48*Setup!$B$6/(1+Setup!$B$6)) -> 1434.7826 | P48: =IF(OR($A48="",N48=""),"",N48-O48) -> 9565.2174 | Q48: =IF($A48="","",Setup!S30) -> 50 | R48: =IF(OR($A48="",F48="",Q48=""),"",F48*Q48) -> 5500 | S48: =IF(OR($A48="",P48="",R48=""),"",P48-R48) -> 4065.2174
A49: =IF(Setup!B31="","",Setup!B31) | B49: =IF($A49="","",Setup!C31) | C49: =IF($A49="","",Setup!D31) | D49: =IF($A49="","",Setup!E31) | E49: =IF(OR($A49="",$Q$41=""),"",$Q$41*D49) | F49: =IF(OR($A49="",C49=0,E49=""),"",ROUNDUP(E49/C49,0)) | G49: =IF(OR($A49="",F49=""),"",ROUND(F49*Setup!F31,0)) | H49: =IF(OR($A49="",F49=""),"",ROUND(F49*Setup!G31,0)) | I49: =IF(OR($A49="",F49=""),"",ROUND(F49*Setup!H31,0)) | J49: =IF(OR($A49="",F49=""),"",ROUND(F49*Setup!I31,0)) | K49: =IF(OR($A49="",F49=""),"",ROUND(F49*Setup!J31,0)) | L49: =IF(OR($A49="",F49=""),"",ROUND(F49*Setup!K31,0)) | M49: =IF(OR($A49="",F49=""),"",ROUND(F49*Setup!L31,0)) | N49: =IF(OR($A49="",F49=""),"",F49*C49) | O49: =IF(OR($A49="",N49=""),"",N49*Setup!$B$6/(1+Setup!$B$6)) | P49: =IF(OR($A49="",N49=""),"",N49-O49) | Q49: =IF($A49="","",Setup!S31) | R49: =IF(OR($A49="",F49="",Q49=""),"",F49*Q49) | S49: =IF(OR($A49="",P49="",R49=""),"",P49-R49)
A50: =IF(Setup!B32="","",Setup!B32) | B50: =IF($A50="","",Setup!C32) | C50: =IF($A50="","",Setup!D32) | D50: =IF($A50="","",Setup!E32) | E50: =IF(OR($A50="",$Q$41=""),"",$Q$41*D50) | F50: =IF(OR($A50="",C50=0,E50=""),"",ROUNDUP(E50/C50,0)) | G50: =IF(OR($A50="",F50=""),"",ROUND(F50*Setup!F32,0)) | H50: =IF(OR($A50="",F50=""),"",ROUND(F50*Setup!G32,0)) | I50: =IF(OR($A50="",F50=""),"",ROUND(F50*Setup!H32,0)) | J50: =IF(OR($A50="",F50=""),"",ROUND(F50*Setup!I32,0)) | K50: =IF(OR($A50="",F50=""),"",ROUND(F50*Setup!J32,0)) | L50: =IF(OR($A50="",F50=""),"",ROUND(F50*Setup!K32,0)) | M50: =IF(OR($A50="",F50=""),"",ROUND(F50*Setup!L32,0)) | N50: =IF(OR($A50="",F50=""),"",F50*C50) | O50: =IF(OR($A50="",N50=""),"",N50*Setup!$B$6/(1+Setup!$B$6)) | P50: =IF(OR($A50="",N50=""),"",N50-O50) | Q50: =IF($A50="","",Setup!S32) | R50: =IF(OR($A50="",F50="",Q50=""),"",F50*Q50) | S50: =IF(OR($A50="",P50="",R50=""),"",P50-R50)
A51: =IF(Setup!B33="","",Setup!B33) | B51: =IF($A51="","",Setup!C33) | C51: =IF($A51="","",Setup!D33) | D51: =IF($A51="","",Setup!E33) | E51: =IF(OR($A51="",$Q$41=""),"",$Q$41*D51) | F51: =IF(OR($A51="",C51=0,E51=""),"",ROUNDUP(E51/C51,0)) | G51: =IF(OR($A51="",F51=""),"",ROUND(F51*Setup!F33,0)) | H51: =IF(OR($A51="",F51=""),"",ROUND(F51*Setup!G33,0)) | I51: =IF(OR($A51="",F51=""),"",ROUND(F51*Setup!H33,0)) | J51: =IF(OR($A51="",F51=""),"",ROUND(F51*Setup!I33,0)) | K51: =IF(OR($A51="",F51=""),"",ROUND(F51*Setup!J33,0)) | L51: =IF(OR($A51="",F51=""),"",ROUND(F51*Setup!K33,0)) | M51: =IF(OR($A51="",F51=""),"",ROUND(F51*Setup!L33,0)) | N51: =IF(OR($A51="",F51=""),"",F51*C51) | O51: =IF(OR($A51="",N51=""),"",N51*Setup!$B$6/(1+Setup!$B$6)) | P51: =IF(OR($A51="",N51=""),"",N51-O51) | Q51: =IF($A51="","",Setup!S33) | R51: =IF(OR($A51="",F51="",Q51=""),"",F51*Q51) | S51: =IF(OR($A51="",P51="",R51=""),"",P51-R51)
A52: =IF(Setup!B34="","",Setup!B34) | B52: =IF($A52="","",Setup!C34) | C52: =IF($A52="","",Setup!D34) | D52: =IF($A52="","",Setup!E34) | E52: =IF(OR($A52="",$Q$41=""),"",$Q$41*D52) | F52: =IF(OR($A52="",C52=0,E52=""),"",ROUNDUP(E52/C52,0)) | G52: =IF(OR($A52="",F52=""),"",ROUND(F52*Setup!F34,0)) | H52: =IF(OR($A52="",F52=""),"",ROUND(F52*Setup!G34,0)) | I52: =IF(OR($A52="",F52=""),"",ROUND(F52*Setup!H34,0)) | J52: =IF(OR($A52="",F52=""),"",ROUND(F52*Setup!I34,0)) | K52: =IF(OR($A52="",F52=""),"",ROUND(F52*Setup!J34,0)) | L52: =IF(OR($A52="",F52=""),"",ROUND(F52*Setup!K34,0)) | M52: =IF(OR($A52="",F52=""),"",ROUND(F52*Setup!L34,0)) | N52: =IF(OR($A52="",F52=""),"",F52*C52) | O52: =IF(OR($A52="",N52=""),"",N52*Setup!$B$6/(1+Setup!$B$6)) | P52: =IF(OR($A52="",N52=""),"",N52-O52) | Q52: =IF($A52="","",Setup!S34) | R52: =IF(OR($A52="",F52="",Q52=""),"",F52*Q52) | S52: =IF(OR($A52="",P52="",R52=""),"",P52-R52)
A53: =IF(Setup!B35="","",Setup!B35) | B53: =IF($A53="","",Setup!C35) | C53: =IF($A53="","",Setup!D35) | D53: =IF($A53="","",Setup!E35) | E53: =IF(OR($A53="",$Q$41=""),"",$Q$41*D53) | F53: =IF(OR($A53="",C53=0,E53=""),"",ROUNDUP(E53/C53,0)) | G53: =IF(OR($A53="",F53=""),"",ROUND(F53*Setup!F35,0)) | H53: =IF(OR($A53="",F53=""),"",ROUND(F53*Setup!G35,0)) | I53: =IF(OR($A53="",F53=""),"",ROUND(F53*Setup!H35,0)) | J53: =IF(OR($A53="",F53=""),"",ROUND(F53*Setup!I35,0)) | K53: =IF(OR($A53="",F53=""),"",ROUND(F53*Setup!J35,0)) | L53: =IF(OR($A53="",F53=""),"",ROUND(F53*Setup!K35,0)) | M53: =IF(OR($A53="",F53=""),"",ROUND(F53*Setup!L35,0)) | N53: =IF(OR($A53="",F53=""),"",F53*C53) | O53: =IF(OR($A53="",N53=""),"",N53*Setup!$B$6/(1+Setup!$B$6)) | P53: =IF(OR($A53="",N53=""),"",N53-O53) | Q53: =IF($A53="","",Setup!S35) | R53: =IF(OR($A53="",F53="",Q53=""),"",F53*Q53) | S53: =IF(OR($A53="",P53="",R53=""),"",P53-R53)
A54: =IF(Setup!B36="","",Setup!B36) | B54: =IF($A54="","",Setup!C36) | C54: =IF($A54="","",Setup!D36) | D54: =IF($A54="","",Setup!E36) | E54: =IF(OR($A54="",$Q$41=""),"",$Q$41*D54) | F54: =IF(OR($A54="",C54=0,E54=""),"",ROUNDUP(E54/C54,0)) | G54: =IF(OR($A54="",F54=""),"",ROUND(F54*Setup!F36,0)) | H54: =IF(OR($A54="",F54=""),"",ROUND(F54*Setup!G36,0)) | I54: =IF(OR($A54="",F54=""),"",ROUND(F54*Setup!H36,0)) | J54: =IF(OR($A54="",F54=""),"",ROUND(F54*Setup!I36,0)) | K54: =IF(OR($A54="",F54=""),"",ROUND(F54*Setup!J36,0)) | L54: =IF(OR($A54="",F54=""),"",ROUND(F54*Setup!K36,0)) | M54: =IF(OR($A54="",F54=""),"",ROUND(F54*Setup!L36,0)) | N54: =IF(OR($A54="",F54=""),"",F54*C54) | O54: =IF(OR($A54="",N54=""),"",N54*Setup!$B$6/(1+Setup!$B$6)) | P54: =IF(OR($A54="",N54=""),"",N54-O54) | Q54: =IF($A54="","",Setup!S36) | R54: =IF(OR($A54="",F54="",Q54=""),"",F54*Q54) | S54: =IF(OR($A54="",P54="",R54=""),"",P54-R54)
A55: =IF(Setup!B37="","",Setup!B37) | B55: =IF($A55="","",Setup!C37) | C55: =IF($A55="","",Setup!D37) | D55: =IF($A55="","",Setup!E37) | E55: =IF(OR($A55="",$Q$41=""),"",$Q$41*D55) | F55: =IF(OR($A55="",C55=0,E55=""),"",ROUNDUP(E55/C55,0)) | G55: =IF(OR($A55="",F55=""),"",ROUND(F55*Setup!F37,0)) | H55: =IF(OR($A55="",F55=""),"",ROUND(F55*Setup!G37,0)) | I55: =IF(OR($A55="",F55=""),"",ROUND(F55*Setup!H37,0)) | J55: =IF(OR($A55="",F55=""),"",ROUND(F55*Setup!I37,0)) | K55: =IF(OR($A55="",F55=""),"",ROUND(F55*Setup!J37,0)) | L55: =IF(OR($A55="",F55=""),"",ROUND(F55*Setup!K37,0)) | M55: =IF(OR($A55="",F55=""),"",ROUND(F55*Setup!L37,0)) | N55: =IF(OR($A55="",F55=""),"",F55*C55) | O55: =IF(OR($A55="",N55=""),"",N55*Setup!$B$6/(1+Setup!$B$6)) | P55: =IF(OR($A55="",N55=""),"",N55-O55) | Q55: =IF($A55="","",Setup!S37) | R55: =IF(OR($A55="",F55="",Q55=""),"",F55*Q55) | S55: =IF(OR($A55="",P55="",R55=""),"",P55-R55)
... A58: =IF(Setup!B40="","",Setup!B40) | B58: =IF($A58="","",Setup!C40) | C58: =IF($A58="","",Setup!D40) | D58: =IF($A58="","",Setup!E40) | E58: =IF(OR($A58="",$Q$41=""),"",$Q$41*D58) | F58: =IF(OR($A58="",C58=0,E58=""),"",ROUNDUP(E58/C58,0)) | G58: =IF(OR($A58="",F58=""),"",ROUND(F58*Setup!F40,0)) | H58: =IF(OR($A58="",F58=""),"",ROUND(F58*Setup!G40,0)) | I58: =IF(OR($A58="",F58=""),"",ROUND(F58*Setup!H40,0)) | J58: =IF(OR($A58="",F58=""),"",ROUND(F58*Setup!I40,0)) | K58: =IF(OR($A58="",F58=""),"",ROUND(F58*Setup!J40,0)) | L58: =IF(OR($A58="",F58=""),"",ROUND(F58*Setup!K40,0)) | M58: =IF(OR($A58="",F58=""),"",ROUND(F58*Setup!L40,0)) | N58: =IF(OR($A58="",F58=""),"",F58*C58) | O58: =IF(OR($A58="",N58=""),"",N58*Setup!$B$6/(1+Setup!$B$6)) | P58: =IF(OR($A58="",N58=""),"",N58-O58) | Q58: =IF($A58="","",Setup!S40) | R58: =IF(OR($A58="",F58="",Q58=""),"",F58*Q58) | S58: =IF(OR($A58="",P58="",R58=""),"",P58-R58)
A59: TOTAL | E59: =SUM(E44:E58) -> 156000 | F59: =SUM(F44:F58) -> 397 | G59: =SUM(G44:G58) -> 0 | H59: =SUM(H44:H58) -> 35 | I59: =SUM(I44:I58) -> 58 | J59: =SUM(J44:J58) -> 69 | K59: =SUM(K44:K58) -> 40 | L59: =SUM(L44:L58) -> 27 | ... P59: =SUM(P44:P58) -> 136739.13 | R59: =SUM(R44:R58) -> 49167 | S59: =SUM(S44:S58) -> 87572.13
A62: =IF(Setup!C11="","Event 3: Not configured",UPPER(Setup!C11&" - "&Setup!D11&" | "&TEXT(Setup!B11,"DD MMM YYYY"))) -> PRETORIA - SUNBET ARENA TIME SQUARE | 06 JUN 2026 | N62: GROSS TARGET (incl VAT): | Q62: =Setup!I11 -> 380250
A63: Attendance: | B63: =Setup!F11 -> 8450 | D63: Stalls: | E63: =Setup!G11 -> 3 | G63: Spend/Head: | H63: =Setup!H11 -> 45 | J63: VAT Rate: | K63: =Setup!B6 -> 0.15 | M63: Flights: | N63: =Setup!J11 -> 0 | P63: Sales Ops: | Q63: =Setup!L11 -> 75000 | R63: CC Fee: | S63: =Setup!M11 -> 0.032
A64: Product | B64: Category | C64: Price (incl VAT) | D64: % Sales | E64: Target Rev | F64: Total Units | G64: XS | H64: S | I64: M | J64: L | K64: XL | L64: XXL | M64: XXXL | N64: Rev (incl VAT) | O64: VAT | P64: Rev (ex VAT) | Q64: Unit Cost | R64: COGS | S64: Gross Profit
A65: =IF(Setup!B26="","",Setup!B26) -> Sing Song Black tee | B65: =IF($A65="","",Setup!C26) -> Apparel | C65: =IF($A65="","",Setup!D26) -> 550 | D65: =IF($A65="","",Setup!E26) -> 0.3 | E65: =IF(OR($A65="",$Q$62=""),"",$Q$62*D65) -> 114075 | F65: =IF(OR($A65="",C65=0,E65=""),"",ROUNDUP(E65/C65,0)) -> 208 | G65: =IF(OR($A65="",F65=""),"",ROUND(F65*Setup!F26,0)) -> 0 | H65: =IF(OR($A65="",F65=""),"",ROUND(F65*Setup!G26,0)) -> 31 | I65: =IF(OR($A65="",F65=""),"",ROUND(F65*Setup!H26,0)) -> 52 | J65: =IF(OR($A65="",F65=""),"",ROUND(F65*Setup!I26,0)) -> 62 | K65: =IF(OR($A65="",F65=""),"",ROUND(F65*Setup!J26,0)) -> 37 | L65: =IF(OR($A65="",F65=""),"",ROUND(F65*Setup!K26,0)) -> 25 | M65: =IF(OR($A65="",F65=""),"",ROUND(F65*Setup!L26,0)) -> 0 | N65: =IF(OR($A65="",F65=""),"",F65*C65) -> 114400 | O65: =IF(OR($A65="",N65=""),"",N65*Setup!$B$6/(1+Setup!$B$6)) -> 14921.739 | P65: =IF(OR($A65="",N65=""),"",N65-O65) -> 99478.261 | Q65: =IF($A65="","",Setup!S26) -> 169 | R65: =IF(OR($A65="",F65="",Q65=""),"",F65*Q65) -> 35152 | S65: =IF(OR($A65="",P65="",R65=""),"",P65-R65) -> 64326.261
A66: =IF(Setup!B27="","",Setup!B27) -> Kingston Black Tee | B66: =IF($A66="","",Setup!C27) -> Apparel | C66: =IF($A66="","",Setup!D27) -> 550 | D66: =IF($A66="","",Setup!E27) -> 0.2 | E66: =IF(OR($A66="",$Q$62=""),"",$Q$62*D66) -> 76050 | F66: =IF(OR($A66="",C66=0,E66=""),"",ROUNDUP(E66/C66,0)) -> 139 | G66: =IF(OR($A66="",F66=""),"",ROUND(F66*Setup!F27,0)) -> 0 | H66: =IF(OR($A66="",F66=""),"",ROUND(F66*Setup!G27,0)) -> 21 | I66: =IF(OR($A66="",F66=""),"",ROUND(F66*Setup!H27,0)) -> 35 | J66: =IF(OR($A66="",F66=""),"",ROUND(F66*Setup!I27,0)) -> 42 | K66: =IF(OR($A66="",F66=""),"",ROUND(F66*Setup!J27,0)) -> 25 | L66: =IF(OR($A66="",F66=""),"",ROUND(F66*Setup!K27,0)) -> 17 | M66: =IF(OR($A66="",F66=""),"",ROUND(F66*Setup!L27,0)) -> 0 | N66: =IF(OR($A66="",F66=""),"",F66*C66) -> 76450 | O66: =IF(OR($A66="",N66=""),"",N66*Setup!$B$6/(1+Setup!$B$6)) -> 9971.7391 | P66: =IF(OR($A66="",N66=""),"",N66-O66) -> 66478.261 | Q66: =IF($A66="","",Setup!S27) -> 169 | R66: =IF(OR($A66="",F66="",Q66=""),"",F66*Q66) -> 23491 | S66: =IF(OR($A66="",P66="",R66=""),"",P66-R66) -> 42987.261
A67: =IF(Setup!B28="","",Setup!B28) -> Red Red Wine White tee | B67: =IF($A67="","",Setup!C28) -> Apparel | C67: =IF($A67="","",Setup!D28) -> 550 | D67: =IF($A67="","",Setup!E28) -> 0.3 | E67: =IF(OR($A67="",$Q$62=""),"",$Q$62*D67) -> 114075 | F67: =IF(OR($A67="",C67=0,E67=""),"",ROUNDUP(E67/C67,0)) -> 208 | G67: =IF(OR($A67="",F67=""),"",ROUND(F67*Setup!F28,0)) -> 0 | H67: =IF(OR($A67="",F67=""),"",ROUND(F67*Setup!G28,0)) -> 31 | I67: =IF(OR($A67="",F67=""),"",ROUND(F67*Setup!H28,0)) -> 52 | J67: =IF(OR($A67="",F67=""),"",ROUND(F67*Setup!I28,0)) -> 62 | K67: =IF(OR($A67="",F67=""),"",ROUND(F67*Setup!J28,0)) -> 37 | L67: =IF(OR($A67="",F67=""),"",ROUND(F67*Setup!K28,0)) -> 25 | M67: =IF(OR($A67="",F67=""),"",ROUND(F67*Setup!L28,0)) -> 0 | N67: =IF(OR($A67="",F67=""),"",F67*C67) -> 114400 | O67: =IF(OR($A67="",N67=""),"",N67*Setup!$B$6/(1+Setup!$B$6)) -> 14921.739 | P67: =IF(OR($A67="",N67=""),"",N67-O67) -> 99478.261 | Q67: =IF($A67="","",Setup!S28) -> 162 | R67: =IF(OR($A67="",F67="",Q67=""),"",F67*Q67) -> 33696 | S67: =IF(OR($A67="",P67="",R67=""),"",P67-R67) -> 65782.261
A68: =IF(Setup!B29="","",Setup!B29) -> Cap | B68: =IF($A68="","",Setup!C29) -> Accessory | C68: =IF($A68="","",Setup!D29) -> 350 | D68: =IF($A68="","",Setup!E29) -> 0.13 | E68: =IF(OR($A68="",$Q$62=""),"",$Q$62*D68) -> 49432.5 | F68: =IF(OR($A68="",C68=0,E68=""),"",ROUNDUP(E68/C68,0)) -> 142 | G68: =IF(OR($A68="",F68=""),"",ROUND(F68*Setup!F29,0)) -> 0 | H68: =IF(OR($A68="",F68=""),"",ROUND(F68*Setup!G29,0)) -> 0 | I68: =IF(OR($A68="",F68=""),"",ROUND(F68*Setup!H29,0)) -> 0 | J68: =IF(OR($A68="",F68=""),"",ROUND(F68*Setup!I29,0)) -> 0 | K68: =IF(OR($A68="",F68=""),"",ROUND(F68*Setup!J29,0)) -> 0 | L68: =IF(OR($A68="",F68=""),"",ROUND(F68*Setup!K29,0)) -> 0 | M68: =IF(OR($A68="",F68=""),"",ROUND(F68*Setup!L29,0)) -> 0 | N68: =IF(OR($A68="",F68=""),"",F68*C68) -> 49700 | O68: =IF(OR($A68="",N68=""),"",N68*Setup!$B$6/(1+Setup!$B$6)) -> 6482.6087 | P68: =IF(OR($A68="",N68=""),"",N68-O68) -> 43217.391 | Q68: =IF($A68="","",Setup!S29) -> 96 | R68: =IF(OR($A68="",F68="",Q68=""),"",F68*Q68) -> 13632 | S68: =IF(OR($A68="",P68="",R68=""),"",P68-R68) -> 29585.391
A69: =IF(Setup!B30="","",Setup!B30) -> Tote | B69: =IF($A69="","",Setup!C30) -> Accessory | C69: =IF($A69="","",Setup!D30) -> 100 | D69: =IF($A69="","",Setup!E30) -> 0.07 | E69: =IF(OR($A69="",$Q$62=""),"",$Q$62*D69) -> 26617.5 | F69: =IF(OR($A69="",C69=0,E69=""),"",ROUNDUP(E69/C69,0)) -> 267 | G69: =IF(OR($A69="",F69=""),"",ROUND(F69*Setup!F30,0)) -> 0 | H69: =IF(OR($A69="",F69=""),"",ROUND(F69*Setup!G30,0)) -> 0 | I69: =IF(OR($A69="",F69=""),"",ROUND(F69*Setup!H30,0)) -> 0 | J69: =IF(OR($A69="",F69=""),"",ROUND(F69*Setup!I30,0)) -> 0 | K69: =IF(OR($A69="",F69=""),"",ROUND(F69*Setup!J30,0)) -> 0 | L69: =IF(OR($A69="",F69=""),"",ROUND(F69*Setup!K30,0)) -> 0 | M69: =IF(OR($A69="",F69=""),"",ROUND(F69*Setup!L30,0)) -> 0 | N69: =IF(OR($A69="",F69=""),"",F69*C69) -> 26700 | O69: =IF(OR($A69="",N69=""),"",N69*Setup!$B$6/(1+Setup!$B$6)) -> 3482.6087 | P69: =IF(OR($A69="",N69=""),"",N69-O69) -> 23217.391 | Q69: =IF($A69="","",Setup!S30) -> 50 | R69: =IF(OR($A69="",F69="",Q69=""),"",F69*Q69) -> 13350 | S69: =IF(OR($A69="",P69="",R69=""),"",P69-R69) -> 9867.3913
A70: =IF(Setup!B31="","",Setup!B31) | B70: =IF($A70="","",Setup!C31) | C70: =IF($A70="","",Setup!D31) | D70: =IF($A70="","",Setup!E31) | E70: =IF(OR($A70="",$Q$62=""),"",$Q$62*D70) | F70: =IF(OR($A70="",C70=0,E70=""),"",ROUNDUP(E70/C70,0)) | G70: =IF(OR($A70="",F70=""),"",ROUND(F70*Setup!F31,0)) | H70: =IF(OR($A70="",F70=""),"",ROUND(F70*Setup!G31,0)) | I70: =IF(OR($A70="",F70=""),"",ROUND(F70*Setup!H31,0)) | J70: =IF(OR($A70="",F70=""),"",ROUND(F70*Setup!I31,0)) | K70: =IF(OR($A70="",F70=""),"",ROUND(F70*Setup!J31,0)) | L70: =IF(OR($A70="",F70=""),"",ROUND(F70*Setup!K31,0)) | M70: =IF(OR($A70="",F70=""),"",ROUND(F70*Setup!L31,0)) | N70: =IF(OR($A70="",F70=""),"",F70*C70) | O70: =IF(OR($A70="",N70=""),"",N70*Setup!$B$6/(1+Setup!$B$6)) | P70: =IF(OR($A70="",N70=""),"",N70-O70) | Q70: =IF($A70="","",Setup!S31) | R70: =IF(OR($A70="",F70="",Q70=""),"",F70*Q70) | S70: =IF(OR($A70="",P70="",R70=""),"",P70-R70)
A71: =IF(Setup!B32="","",Setup!B32) | B71: =IF($A71="","",Setup!C32) | C71: =IF($A71="","",Setup!D32) | D71: =IF($A71="","",Setup!E32) | E71: =IF(OR($A71="",$Q$62=""),"",$Q$62*D71) | F71: =IF(OR($A71="",C71=0,E71=""),"",ROUNDUP(E71/C71,0)) | G71: =IF(OR($A71="",F71=""),"",ROUND(F71*Setup!F32,0)) | H71: =IF(OR($A71="",F71=""),"",ROUND(F71*Setup!G32,0)) | I71: =IF(OR($A71="",F71=""),"",ROUND(F71*Setup!H32,0)) | J71: =IF(OR($A71="",F71=""),"",ROUND(F71*Setup!I32,0)) | K71: =IF(OR($A71="",F71=""),"",ROUND(F71*Setup!J32,0)) | L71: =IF(OR($A71="",F71=""),"",ROUND(F71*Setup!K32,0)) | M71: =IF(OR($A71="",F71=""),"",ROUND(F71*Setup!L32,0)) | N71: =IF(OR($A71="",F71=""),"",F71*C71) | O71: =IF(OR($A71="",N71=""),"",N71*Setup!$B$6/(1+Setup!$B$6)) | P71: =IF(OR($A71="",N71=""),"",N71-O71) | Q71: =IF($A71="","",Setup!S32) | R71: =IF(OR($A71="",F71="",Q71=""),"",F71*Q71) | S71: =IF(OR($A71="",P71="",R71=""),"",P71-R71)
A72: =IF(Setup!B33="","",Setup!B33) | B72: =IF($A72="","",Setup!C33) | C72: =IF($A72="","",Setup!D33) | D72: =IF($A72="","",Setup!E33) | E72: =IF(OR($A72="",$Q$62=""),"",$Q$62*D72) | F72: =IF(OR($A72="",C72=0,E72=""),"",ROUNDUP(E72/C72,0)) | G72: =IF(OR($A72="",F72=""),"",ROUND(F72*Setup!F33,0)) | H72: =IF(OR($A72="",F72=""),"",ROUND(F72*Setup!G33,0)) | I72: =IF(OR($A72="",F72=""),"",ROUND(F72*Setup!H33,0)) | J72: =IF(OR($A72="",F72=""),"",ROUND(F72*Setup!I33,0)) | K72: =IF(OR($A72="",F72=""),"",ROUND(F72*Setup!J33,0)) | L72: =IF(OR($A72="",F72=""),"",ROUND(F72*Setup!K33,0)) | M72: =IF(OR($A72="",F72=""),"",ROUND(F72*Setup!L33,0)) | N72: =IF(OR($A72="",F72=""),"",F72*C72) | O72: =IF(OR($A72="",N72=""),"",N72*Setup!$B$6/(1+Setup!$B$6)) | P72: =IF(OR($A72="",N72=""),"",N72-O72) | Q72: =IF($A72="","",Setup!S33) | R72: =IF(OR($A72="",F72="",Q72=""),"",F72*Q72) | S72: =IF(OR($A72="",P72="",R72=""),"",P72-R72)
A73: =IF(Setup!B34="","",Setup!B34) | B73: =IF($A73="","",Setup!C34) | C73: =IF($A73="","",Setup!D34) | D73: =IF($A73="","",Setup!E34) | E73: =IF(OR($A73="",$Q$62=""),"",$Q$62*D73) | F73: =IF(OR($A73="",C73=0,E73=""),"",ROUNDUP(E73/C73,0)) | G73: =IF(OR($A73="",F73=""),"",ROUND(F73*Setup!F34,0)) | H73: =IF(OR($A73="",F73=""),"",ROUND(F73*Setup!G34,0)) | I73: =IF(OR($A73="",F73=""),"",ROUND(F73*Setup!H34,0)) | J73: =IF(OR($A73="",F73=""),"",ROUND(F73*Setup!I34,0)) | K73: =IF(OR($A73="",F73=""),"",ROUND(F73*Setup!J34,0)) | L73: =IF(OR($A73="",F73=""),"",ROUND(F73*Setup!K34,0)) | M73: =IF(OR($A73="",F73=""),"",ROUND(F73*Setup!L34,0)) | N73: =IF(OR($A73="",F73=""),"",F73*C73) | O73: =IF(OR($A73="",N73=""),"",N73*Setup!$B$6/(1+Setup!$B$6)) | P73: =IF(OR($A73="",N73=""),"",N73-O73) | Q73: =IF($A73="","",Setup!S34) | R73: =IF(OR($A73="",F73="",Q73=""),"",F73*Q73) | S73: =IF(OR($A73="",P73="",R73=""),"",P73-R73)
A74: =IF(Setup!B35="","",Setup!B35) | B74: =IF($A74="","",Setup!C35) | C74: =IF($A74="","",Setup!D35) | D74: =IF($A74="","",Setup!E35) | E74: =IF(OR($A74="",$Q$62=""),"",$Q$62*D74) | F74: =IF(OR($A74="",C74=0,E74=""),"",ROUNDUP(E74/C74,0)) | G74: =IF(OR($A74="",F74=""),"",ROUND(F74*Setup!F35,0)) | H74: =IF(OR($A74="",F74=""),"",ROUND(F74*Setup!G35,0)) | I74: =IF(OR($A74="",F74=""),"",ROUND(F74*Setup!H35,0)) | J74: =IF(OR($A74="",F74=""),"",ROUND(F74*Setup!I35,0)) | K74: =IF(OR($A74="",F74=""),"",ROUND(F74*Setup!J35,0)) | L74: =IF(OR($A74="",F74=""),"",ROUND(F74*Setup!K35,0)) | M74: =IF(OR($A74="",F74=""),"",ROUND(F74*Setup!L35,0)) | N74: =IF(OR($A74="",F74=""),"",F74*C74) | O74: =IF(OR($A74="",N74=""),"",N74*Setup!$B$6/(1+Setup!$B$6)) | P74: =IF(OR($A74="",N74=""),"",N74-O74) | Q74: =IF($A74="","",Setup!S35) | R74: =IF(OR($A74="",F74="",Q74=""),"",F74*Q74) | S74: =IF(OR($A74="",P74="",R74=""),"",P74-R74)
A75: =IF(Setup!B36="","",Setup!B36) | B75: =IF($A75="","",Setup!C36) | C75: =IF($A75="","",Setup!D36) | D75: =IF($A75="","",Setup!E36) | E75: =IF(OR($A75="",$Q$62=""),"",$Q$62*D75) | F75: =IF(OR($A75="",C75=0,E75=""),"",ROUNDUP(E75/C75,0)) | G75: =IF(OR($A75="",F75=""),"",ROUND(F75*Setup!F36,0)) | H75: =IF(OR($A75="",F75=""),"",ROUND(F75*Setup!G36,0)) | I75: =IF(OR($A75="",F75=""),"",ROUND(F75*Setup!H36,0)) | J75: =IF(OR($A75="",F75=""),"",ROUND(F75*Setup!I36,0)) | K75: =IF(OR($A75="",F75=""),"",ROUND(F75*Setup!J36,0)) | L75: =IF(OR($A75="",F75=""),"",ROUND(F75*Setup!K36,0)) | M75: =IF(OR($A75="",F75=""),"",ROUND(F75*Setup!L36,0)) | N75: =IF(OR($A75="",F75=""),"",F75*C75) | O75: =IF(OR($A75="",N75=""),"",N75*Setup!$B$6/(1+Setup!$B$6)) | P75: =IF(OR($A75="",N75=""),"",N75-O75) | Q75: =IF($A75="","",Setup!S36) | R75: =IF(OR($A75="",F75="",Q75=""),"",F75*Q75) | S75: =IF(OR($A75="",P75="",R75=""),"",P75-R75)
A76: =IF(Setup!B37="","",Setup!B37) | B76: =IF($A76="","",Setup!C37) | C76: =IF($A76="","",Setup!D37) | D76: =IF($A76="","",Setup!E37) | E76: =IF(OR($A76="",$Q$62=""),"",$Q$62*D76) | F76: =IF(OR($A76="",C76=0,E76=""),"",ROUNDUP(E76/C76,0)) | G76: =IF(OR($A76="",F76=""),"",ROUND(F76*Setup!F37,0)) | H76: =IF(OR($A76="",F76=""),"",ROUND(F76*Setup!G37,0)) | I76: =IF(OR($A76="",F76=""),"",ROUND(F76*Setup!H37,0)) | J76: =IF(OR($A76="",F76=""),"",ROUND(F76*Setup!I37,0)) | K76: =IF(OR($A76="",F76=""),"",ROUND(F76*Setup!J37,0)) | L76: =IF(OR($A76="",F76=""),"",ROUND(F76*Setup!K37,0)) | M76: =IF(OR($A76="",F76=""),"",ROUND(F76*Setup!L37,0)) | N76: =IF(OR($A76="",F76=""),"",F76*C76) | O76: =IF(OR($A76="",N76=""),"",N76*Setup!$B$6/(1+Setup!$B$6)) | P76: =IF(OR($A76="",N76=""),"",N76-O76) | Q76: =IF($A76="","",Setup!S37) | R76: =IF(OR($A76="",F76="",Q76=""),"",F76*Q76) | S76: =IF(OR($A76="",P76="",R76=""),"",P76-R76)
... A79: =IF(Setup!B40="","",Setup!B40) | B79: =IF($A79="","",Setup!C40) | C79: =IF($A79="","",Setup!D40) | D79: =IF($A79="","",Setup!E40) | E79: =IF(OR($A79="",$Q$62=""),"",$Q$62*D79) | F79: =IF(OR($A79="",C79=0,E79=""),"",ROUNDUP(E79/C79,0)) | G79: =IF(OR($A79="",F79=""),"",ROUND(F79*Setup!F40,0)) | H79: =IF(OR($A79="",F79=""),"",ROUND(F79*Setup!G40,0)) | I79: =IF(OR($A79="",F79=""),"",ROUND(F79*Setup!H40,0)) | J79: =IF(OR($A79="",F79=""),"",ROUND(F79*Setup!I40,0)) | K79: =IF(OR($A79="",F79=""),"",ROUND(F79*Setup!J40,0)) | L79: =IF(OR($A79="",F79=""),"",ROUND(F79*Setup!K40,0)) | M79: =IF(OR($A79="",F79=""),"",ROUND(F79*Setup!L40,0)) | N79: =IF(OR($A79="",F79=""),"",F79*C79) | O79: =IF(OR($A79="",N79=""),"",N79*Setup!$B$6/(1+Setup!$B$6)) | P79: =IF(OR($A79="",N79=""),"",N79-O79) | Q79: =IF($A79="","",Setup!S40) | R79: =IF(OR($A79="",F79="",Q79=""),"",F79*Q79) | S79: =IF(OR($A79="",P79="",R79=""),"",P79-R79)
A80: TOTAL | E80: =SUM(E65:E79) -> 380250 | F80: =SUM(F65:F79) -> 964 | G80: =SUM(G65:G79) -> 0 | H80: =SUM(H65:H79) -> 83 | I80: =SUM(I65:I79) -> 139 | J80: =SUM(J65:J79) -> 166 | K80: =SUM(K65:K79) -> 99 | L80: =SUM(L65:L79) -> 67 | ... P80: =SUM(P65:P79) -> 331869.57 | R80: =SUM(R65:R79) -> 119321 | S80: =SUM(S65:S79) -> 212548.57
A83: =IF(Setup!C12="","Event 4: Not configured",UPPER(Setup!C12&" - "&Setup!D12&" | "&TEXT(Setup!B12,"DD MMM YYYY"))) -> PRETORIA - SUNBET ARENA TIME SQUARE | 07 JUN 2026 | N83: GROSS TARGET (incl VAT): | Q83: =Setup!I12 -> 192500
A84: Attendance: | B84: =Setup!F12 -> 5500 | D84: Stalls: | E84: =Setup!G12 -> 3 | G84: Spend/Head: | H84: =Setup!H12 -> 35 | J84: VAT Rate: | K84: =Setup!B6 -> 0.15 | M84: Flights: | N84: =Setup!J12 -> 0 | P84: Sales Ops: | Q84: =Setup!L12 -> 60000 | R84: CC Fee: | S84: =Setup!M12 -> 0.032
A85: Product | B85: Category | C85: Price (incl VAT) | D85: % Sales | E85: Target Rev | F85: Total Units | G85: XS | H85: S | I85: M | J85: L | K85: XL | L85: XXL | M85: XXXL | N85: Rev (incl VAT) | O85: VAT | P85: Rev (ex VAT) | Q85: Unit Cost | R85: COGS | S85: Gross Profit
A86: =IF(Setup!B26="","",Setup!B26) -> Sing Song Black tee | B86: =IF($A86="","",Setup!C26) -> Apparel | C86: =IF($A86="","",Setup!D26) -> 550 | D86: =IF($A86="","",Setup!E26) -> 0.3 | E86: =IF(OR($A86="",$Q$83=""),"",$Q$83*D86) -> 57750 | F86: =IF(OR($A86="",C86=0,E86=""),"",ROUNDUP(E86/C86,0)) -> 105 | G86: =IF(OR($A86="",F86=""),"",ROUND(F86*Setup!F26,0)) -> 0 | H86: =IF(OR($A86="",F86=""),"",ROUND(F86*Setup!G26,0)) -> 16 | I86: =IF(OR($A86="",F86=""),"",ROUND(F86*Setup!H26,0)) -> 26 | J86: =IF(OR($A86="",F86=""),"",ROUND(F86*Setup!I26,0)) -> 32 | K86: =IF(OR($A86="",F86=""),"",ROUND(F86*Setup!J26,0)) -> 19 | L86: =IF(OR($A86="",F86=""),"",ROUND(F86*Setup!K26,0)) -> 13 | M86: =IF(OR($A86="",F86=""),"",ROUND(F86*Setup!L26,0)) -> 0 | N86: =IF(OR($A86="",F86=""),"",F86*C86) -> 57750 | O86: =IF(OR($A86="",N86=""),"",N86*Setup!$B$6/(1+Setup!$B$6)) -> 7532.6087 | P86: =IF(OR($A86="",N86=""),"",N86-O86) -> 50217.391 | Q86: =IF($A86="","",Setup!S26) -> 169 | R86: =IF(OR($A86="",F86="",Q86=""),"",F86*Q86) -> 17745 | S86: =IF(OR($A86="",P86="",R86=""),"",P86-R86) -> 32472.391
A87: =IF(Setup!B27="","",Setup!B27) -> Kingston Black Tee | B87: =IF($A87="","",Setup!C27) -> Apparel | C87: =IF($A87="","",Setup!D27) -> 550 | D87: =IF($A87="","",Setup!E27) -> 0.2 | E87: =IF(OR($A87="",$Q$83=""),"",$Q$83*D87) -> 38500 | F87: =IF(OR($A87="",C87=0,E87=""),"",ROUNDUP(E87/C87,0)) -> 70 | G87: =IF(OR($A87="",F87=""),"",ROUND(F87*Setup!F27,0)) -> 0 | H87: =IF(OR($A87="",F87=""),"",ROUND(F87*Setup!G27,0)) -> 11 | I87: =IF(OR($A87="",F87=""),"",ROUND(F87*Setup!H27,0)) -> 18 | J87: =IF(OR($A87="",F87=""),"",ROUND(F87*Setup!I27,0)) -> 21 | K87: =IF(OR($A87="",F87=""),"",ROUND(F87*Setup!J27,0)) -> 13 | L87: =IF(OR($A87="",F87=""),"",ROUND(F87*Setup!K27,0)) -> 8 | M87: =IF(OR($A87="",F87=""),"",ROUND(F87*Setup!L27,0)) -> 0 | N87: =IF(OR($A87="",F87=""),"",F87*C87) -> 38500 | O87: =IF(OR($A87="",N87=""),"",N87*Setup!$B$6/(1+Setup!$B$6)) -> 5021.7391 | P87: =IF(OR($A87="",N87=""),"",N87-O87) -> 33478.261 | Q87: =IF($A87="","",Setup!S27) -> 169 | R87: =IF(OR($A87="",F87="",Q87=""),"",F87*Q87) -> 11830 | S87: =IF(OR($A87="",P87="",R87=""),"",P87-R87) -> 21648.261
A88: =IF(Setup!B28="","",Setup!B28) -> Red Red Wine White tee | B88: =IF($A88="","",Setup!C28) -> Apparel | C88: =IF($A88="","",Setup!D28) -> 550 | D88: =IF($A88="","",Setup!E28) -> 0.3 | E88: =IF(OR($A88="",$Q$83=""),"",$Q$83*D88) -> 57750 | F88: =IF(OR($A88="",C88=0,E88=""),"",ROUNDUP(E88/C88,0)) -> 105 | G88: =IF(OR($A88="",F88=""),"",ROUND(F88*Setup!F28,0)) -> 0 | H88: =IF(OR($A88="",F88=""),"",ROUND(F88*Setup!G28,0)) -> 16 | I88: =IF(OR($A88="",F88=""),"",ROUND(F88*Setup!H28,0)) -> 26 | J88: =IF(OR($A88="",F88=""),"",ROUND(F88*Setup!I28,0)) -> 32 | K88: =IF(OR($A88="",F88=""),"",ROUND(F88*Setup!J28,0)) -> 19 | L88: =IF(OR($A88="",F88=""),"",ROUND(F88*Setup!K28,0)) -> 13 | M88: =IF(OR($A88="",F88=""),"",ROUND(F88*Setup!L28,0)) -> 0 | N88: =IF(OR($A88="",F88=""),"",F88*C88) -> 57750 | O88: =IF(OR($A88="",N88=""),"",N88*Setup!$B$6/(1+Setup!$B$6)) -> 7532.6087 | P88: =IF(OR($A88="",N88=""),"",N88-O88) -> 50217.391 | Q88: =IF($A88="","",Setup!S28) -> 162 | R88: =IF(OR($A88="",F88="",Q88=""),"",F88*Q88) -> 17010 | S88: =IF(OR($A88="",P88="",R88=""),"",P88-R88) -> 33207.391
A89: =IF(Setup!B29="","",Setup!B29) -> Cap | B89: =IF($A89="","",Setup!C29) -> Accessory | C89: =IF($A89="","",Setup!D29) -> 350 | D89: =IF($A89="","",Setup!E29) -> 0.13 | E89: =IF(OR($A89="",$Q$83=""),"",$Q$83*D89) -> 25025 | F89: =IF(OR($A89="",C89=0,E89=""),"",ROUNDUP(E89/C89,0)) -> 72 | G89: =IF(OR($A89="",F89=""),"",ROUND(F89*Setup!F29,0)) -> 0 | H89: =IF(OR($A89="",F89=""),"",ROUND(F89*Setup!G29,0)) -> 0 | I89: =IF(OR($A89="",F89=""),"",ROUND(F89*Setup!H29,0)) -> 0 | J89: =IF(OR($A89="",F89=""),"",ROUND(F89*Setup!I29,0)) -> 0 | K89: =IF(OR($A89="",F89=""),"",ROUND(F89*Setup!J29,0)) -> 0 | L89: =IF(OR($A89="",F89=""),"",ROUND(F89*Setup!K29,0)) -> 0 | M89: =IF(OR($A89="",F89=""),"",ROUND(F89*Setup!L29,0)) -> 0 | N89: =IF(OR($A89="",F89=""),"",F89*C89) -> 25200 | O89: =IF(OR($A89="",N89=""),"",N89*Setup!$B$6/(1+Setup!$B$6)) -> 3286.9565 | P89: =IF(OR($A89="",N89=""),"",N89-O89) -> 21913.043 | Q89: =IF($A89="","",Setup!S29) -> 96 | R89: =IF(OR($A89="",F89="",Q89=""),"",F89*Q89) -> 6912 | S89: =IF(OR($A89="",P89="",R89=""),"",P89-R89) -> 15001.043
A90: =IF(Setup!B30="","",Setup!B30) -> Tote | B90: =IF($A90="","",Setup!C30) -> Accessory | C90: =IF($A90="","",Setup!D30) -> 100 | D90: =IF($A90="","",Setup!E30) -> 0.07 | E90: =IF(OR($A90="",$Q$83=""),"",$Q$83*D90) -> 13475 | F90: =IF(OR($A90="",C90=0,E90=""),"",ROUNDUP(E90/C90,0)) -> 135 | G90: =IF(OR($A90="",F90=""),"",ROUND(F90*Setup!F30,0)) -> 0 | H90: =IF(OR($A90="",F90=""),"",ROUND(F90*Setup!G30,0)) -> 0 | I90: =IF(OR($A90="",F90=""),"",ROUND(F90*Setup!H30,0)) -> 0 | J90: =IF(OR($A90="",F90=""),"",ROUND(F90*Setup!I30,0)) -> 0 | K90: =IF(OR($A90="",F90=""),"",ROUND(F90*Setup!J30,0)) -> 0 | L90: =IF(OR($A90="",F90=""),"",ROUND(F90*Setup!K30,0)) -> 0 | M90: =IF(OR($A90="",F90=""),"",ROUND(F90*Setup!L30,0)) -> 0 | N90: =IF(OR($A90="",F90=""),"",F90*C90) -> 13500 | O90: =IF(OR($A90="",N90=""),"",N90*Setup!$B$6/(1+Setup!$B$6)) -> 1760.8696 | P90: =IF(OR($A90="",N90=""),"",N90-O90) -> 11739.13 | Q90: =IF($A90="","",Setup!S30) -> 50 | R90: =IF(OR($A90="",F90="",Q90=""),"",F90*Q90) -> 6750 | S90: =IF(OR($A90="",P90="",R90=""),"",P90-R90) -> 4989.1304
A91: =IF(Setup!B31="","",Setup!B31) | B91: =IF($A91="","",Setup!C31) | C91: =IF($A91="","",Setup!D31) | D91: =IF($A91="","",Setup!E31) | E91: =IF(OR($A91="",$Q$83=""),"",$Q$83*D91) | F91: =IF(OR($A91="",C91=0,E91=""),"",ROUNDUP(E91/C91,0)) | G91: =IF(OR($A91="",F91=""),"",ROUND(F91*Setup!F31,0)) | H91: =IF(OR($A91="",F91=""),"",ROUND(F91*Setup!G31,0)) | I91: =IF(OR($A91="",F91=""),"",ROUND(F91*Setup!H31,0)) | J91: =IF(OR($A91="",F91=""),"",ROUND(F91*Setup!I31,0)) | K91: =IF(OR($A91="",F91=""),"",ROUND(F91*Setup!J31,0)) | L91: =IF(OR($A91="",F91=""),"",ROUND(F91*Setup!K31,0)) | M91: =IF(OR($A91="",F91=""),"",ROUND(F91*Setup!L31,0)) | N91: =IF(OR($A91="",F91=""),"",F91*C91) | O91: =IF(OR($A91="",N91=""),"",N91*Setup!$B$6/(1+Setup!$B$6)) | P91: =IF(OR($A91="",N91=""),"",N91-O91) | Q91: =IF($A91="","",Setup!S31) | R91: =IF(OR($A91="",F91="",Q91=""),"",F91*Q91) | S91: =IF(OR($A91="",P91="",R91=""),"",P91-R91)
A92: =IF(Setup!B32="","",Setup!B32) | B92: =IF($A92="","",Setup!C32) | C92: =IF($A92="","",Setup!D32) | D92: =IF($A92="","",Setup!E32) | E92: =IF(OR($A92="",$Q$83=""),"",$Q$83*D92) | F92: =IF(OR($A92="",C92=0,E92=""),"",ROUNDUP(E92/C92,0)) | G92: =IF(OR($A92="",F92=""),"",ROUND(F92*Setup!F32,0)) | H92: =IF(OR($A92="",F92=""),"",ROUND(F92*Setup!G32,0)) | I92: =IF(OR($A92="",F92=""),"",ROUND(F92*Setup!H32,0)) | J92: =IF(OR($A92="",F92=""),"",ROUND(F92*Setup!I32,0)) | K92: =IF(OR($A92="",F92=""),"",ROUND(F92*Setup!J32,0)) | L92: =IF(OR($A92="",F92=""),"",ROUND(F92*Setup!K32,0)) | M92: =IF(OR($A92="",F92=""),"",ROUND(F92*Setup!L32,0)) | N92: =IF(OR($A92="",F92=""),"",F92*C92) | O92: =IF(OR($A92="",N92=""),"",N92*Setup!$B$6/(1+Setup!$B$6)) | P92: =IF(OR($A92="",N92=""),"",N92-O92) | Q92: =IF($A92="","",Setup!S32) | R92: =IF(OR($A92="",F92="",Q92=""),"",F92*Q92) | S92: =IF(OR($A92="",P92="",R92=""),"",P92-R92)
A93: =IF(Setup!B33="","",Setup!B33) | B93: =IF($A93="","",Setup!C33) | C93: =IF($A93="","",Setup!D33) | D93: =IF($A93="","",Setup!E33) | E93: =IF(OR($A93="",$Q$83=""),"",$Q$83*D93) | F93: =IF(OR($A93="",C93=0,E93=""),"",ROUNDUP(E93/C93,0)) | G93: =IF(OR($A93="",F93=""),"",ROUND(F93*Setup!F33,0)) | H93: =IF(OR($A93="",F93=""),"",ROUND(F93*Setup!G33,0)) | I93: =IF(OR($A93="",F93=""),"",ROUND(F93*Setup!H33,0)) | J93: =IF(OR($A93="",F93=""),"",ROUND(F93*Setup!I33,0)) | K93: =IF(OR($A93="",F93=""),"",ROUND(F93*Setup!J33,0)) | L93: =IF(OR($A93="",F93=""),"",ROUND(F93*Setup!K33,0)) | M93: =IF(OR($A93="",F93=""),"",ROUND(F93*Setup!L33,0)) | N93: =IF(OR($A93="",F93=""),"",F93*C93) | O93: =IF(OR($A93="",N93=""),"",N93*Setup!$B$6/(1+Setup!$B$6)) | P93: =IF(OR($A93="",N93=""),"",N93-O93) | Q93: =IF($A93="","",Setup!S33) | R93: =IF(OR($A93="",F93="",Q93=""),"",F93*Q93) | S93: =IF(OR($A93="",P93="",R93=""),"",P93-R93)
A94: =IF(Setup!B34="","",Setup!B34) | B94: =IF($A94="","",Setup!C34) | C94: =IF($A94="","",Setup!D34) | D94: =IF($A94="","",Setup!E34) | E94: =IF(OR($A94="",$Q$83=""),"",$Q$83*D94) | F94: =IF(OR($A94="",C94=0,E94=""),"",ROUNDUP(E94/C94,0)) | G94: =IF(OR($A94="",F94=""),"",ROUND(F94*Setup!F34,0)) | H94: =IF(OR($A94="",F94=""),"",ROUND(F94*Setup!G34,0)) | I94: =IF(OR($A94="",F94=""),"",ROUND(F94*Setup!H34,0)) | J94: =IF(OR($A94="",F94=""),"",ROUND(F94*Setup!I34,0)) | K94: =IF(OR($A94="",F94=""),"",ROUND(F94*Setup!J34,0)) | L94: =IF(OR($A94="",F94=""),"",ROUND(F94*Setup!K34,0)) | M94: =IF(OR($A94="",F94=""),"",ROUND(F94*Setup!L34,0)) | N94: =IF(OR($A94="",F94=""),"",F94*C94) | O94: =IF(OR($A94="",N94=""),"",N94*Setup!$B$6/(1+Setup!$B$6)) | P94: =IF(OR($A94="",N94=""),"",N94-O94) | Q94: =IF($A94="","",Setup!S34) | R94: =IF(OR($A94="",F94="",Q94=""),"",F94*Q94) | S94: =IF(OR($A94="",P94="",R94=""),"",P94-R94)
A95: =IF(Setup!B35="","",Setup!B35) | B95: =IF($A95="","",Setup!C35) | C95: =IF($A95="","",Setup!D35) | D95: =IF($A95="","",Setup!E35) | E95: =IF(OR($A95="",$Q$83=""),"",$Q$83*D95) | F95: =IF(OR($A95="",C95=0,E95=""),"",ROUNDUP(E95/C95,0)) | G95: =IF(OR($A95="",F95=""),"",ROUND(F95*Setup!F35,0)) | H95: =IF(OR($A95="",F95=""),"",ROUND(F95*Setup!G35,0)) | I95: =IF(OR($A95="",F95=""),"",ROUND(F95*Setup!H35,0)) | J95: =IF(OR($A95="",F95=""),"",ROUND(F95*Setup!I35,0)) | K95: =IF(OR($A95="",F95=""),"",ROUND(F95*Setup!J35,0)) | L95: =IF(OR($A95="",F95=""),"",ROUND(F95*Setup!K35,0)) | M95: =IF(OR($A95="",F95=""),"",ROUND(F95*Setup!L35,0)) | N95: =IF(OR($A95="",F95=""),"",F95*C95) | O95: =IF(OR($A95="",N95=""),"",N95*Setup!$B$6/(1+Setup!$B$6)) | P95: =IF(OR($A95="",N95=""),"",N95-O95) | Q95: =IF($A95="","",Setup!S35) | R95: =IF(OR($A95="",F95="",Q95=""),"",F95*Q95) | S95: =IF(OR($A95="",P95="",R95=""),"",P95-R95)
A96: =IF(Setup!B36="","",Setup!B36) | B96: =IF($A96="","",Setup!C36) | C96: =IF($A96="","",Setup!D36) | D96: =IF($A96="","",Setup!E36) | E96: =IF(OR($A96="",$Q$83=""),"",$Q$83*D96) | F96: =IF(OR($A96="",C96=0,E96=""),"",ROUNDUP(E96/C96,0)) | G96: =IF(OR($A96="",F96=""),"",ROUND(F96*Setup!F36,0)) | H96: =IF(OR($A96="",F96=""),"",ROUND(F96*Setup!G36,0)) | I96: =IF(OR($A96="",F96=""),"",ROUND(F96*Setup!H36,0)) | J96: =IF(OR($A96="",F96=""),"",ROUND(F96*Setup!I36,0)) | K96: =IF(OR($A96="",F96=""),"",ROUND(F96*Setup!J36,0)) | L96: =IF(OR($A96="",F96=""),"",ROUND(F96*Setup!K36,0)) | M96: =IF(OR($A96="",F96=""),"",ROUND(F96*Setup!L36,0)) | N96: =IF(OR($A96="",F96=""),"",F96*C96) | O96: =IF(OR($A96="",N96=""),"",N96*Setup!$B$6/(1+Setup!$B$6)) | P96: =IF(OR($A96="",N96=""),"",N96-O96) | Q96: =IF($A96="","",Setup!S36) | R96: =IF(OR($A96="",F96="",Q96=""),"",F96*Q96) | S96: =IF(OR($A96="",P96="",R96=""),"",P96-R96)
A97: =IF(Setup!B37="","",Setup!B37) | B97: =IF($A97="","",Setup!C37) | C97: =IF($A97="","",Setup!D37) | D97: =IF($A97="","",Setup!E37) | E97: =IF(OR($A97="",$Q$83=""),"",$Q$83*D97) | F97: =IF(OR($A97="",C97=0,E97=""),"",ROUNDUP(E97/C97,0)) | G97: =IF(OR($A97="",F97=""),"",ROUND(F97*Setup!F37,0)) | H97: =IF(OR($A97="",F97=""),"",ROUND(F97*Setup!G37,0)) | I97: =IF(OR($A97="",F97=""),"",ROUND(F97*Setup!H37,0)) | J97: =IF(OR($A97="",F97=""),"",ROUND(F97*Setup!I37,0)) | K97: =IF(OR($A97="",F97=""),"",ROUND(F97*Setup!J37,0)) | L97: =IF(OR($A97="",F97=""),"",ROUND(F97*Setup!K37,0)) | M97: =IF(OR($A97="",F97=""),"",ROUND(F97*Setup!L37,0)) | N97: =IF(OR($A97="",F97=""),"",F97*C97) | O97: =IF(OR($A97="",N97=""),"",N97*Setup!$B$6/(1+Setup!$B$6)) | P97: =IF(OR($A97="",N97=""),"",N97-O97) | Q97: =IF($A97="","",Setup!S37) | R97: =IF(OR($A97="",F97="",Q97=""),"",F97*Q97) | S97: =IF(OR($A97="",P97="",R97=""),"",P97-R97)
... A100: =IF(Setup!B40="","",Setup!B40) | B100: =IF($A100="","",Setup!C40) | C100: =IF($A100="","",Setup!D40) | D100: =IF($A100="","",Setup!E40) | E100: =IF(OR($A100="",$Q$83=""),"",$Q$83*D100) | F100: =IF(OR($A100="",C100=0,E100=""),"",ROUNDUP(E100/C100,0)) | G100: =IF(OR($A100="",F100=""),"",ROUND(F100*Setup!F40,0)) | H100: =IF(OR($A100="",F100=""),"",ROUND(F100*Setup!G40,0)) | I100: =IF(OR($A100="",F100=""),"",ROUND(F100*Setup!H40,0)) | J100: =IF(OR($A100="",F100=""),"",ROUND(F100*Setup!I40,0)) | K100: =IF(OR($A100="",F100=""),"",ROUND(F100*Setup!J40,0)) | L100: =IF(OR($A100="",F100=""),"",ROUND(F100*Setup!K40,0)) | M100: =IF(OR($A100="",F100=""),"",ROUND(F100*Setup!L40,0)) | N100: =IF(OR($A100="",F100=""),"",F100*C100) | O100: =IF(OR($A100="",N100=""),"",N100*Setup!$B$6/(1+Setup!$B$6)) | P100: =IF(OR($A100="",N100=""),"",N100-O100) | Q100: =IF($A100="","",Setup!S40) | R100: =IF(OR($A100="",F100="",Q100=""),"",F100*Q100) | S100: =IF(OR($A100="",P100="",R100=""),"",P100-R100)
A101: TOTAL | E101: =SUM(E86:E100) -> 192500 | F101: =SUM(F86:F100) -> 487 | G101: =SUM(G86:G100) -> 0 | H101: =SUM(H86:H100) -> 43 | I101: =SUM(I86:I100) -> 70 | J101: =SUM(J86:J100) -> 85 | K101: =SUM(K86:K100) -> 51 | L101: =SUM(L86:L100) -> 34 | ... P101: =SUM(P86:P100) -> 167565.22 | R101: =SUM(R86:R100) -> 60247 | S101: =SUM(S86:S100) -> 107318.22
A104: =IF(Setup!C13="","Event 5: Not configured",UPPER(Setup!C13&" - "&Setup!D13&" | "&TEXT(Setup!B13,"DD MMM YYYY"))) -> Event 5: Not configured | N104: GROSS TARGET (incl VAT): | Q104: =Setup!I13
A105: Attendance: | B105: =Setup!F13 -> 0 | D105: Stalls: | E105: =Setup!G13 -> 0 | G105: Spend/Head: | H105: =Setup!H13 -> 0 | J105: VAT Rate: | K105: =Setup!B6 -> 0.15 | M105: Flights: | N105: =Setup!J13 -> 0 | P105: Sales Ops: | Q105: =Setup!L13 -> 0 | R105: CC Fee: | S105: =Setup!M13 -> 0
A106: Product | B106: Category | C106: Price (incl VAT) | D106: % Sales | E106: Target Rev | F106: Total Units | G106: XS | H106: S | I106: M | J106: L | K106: XL | L106: XXL | M106: XXXL | N106: Rev (incl VAT) | O106: VAT | P106: Rev (ex VAT) | Q106: Unit Cost | R106: COGS | S106: Gross Profit
A107: =IF(Setup!B26="","",Setup!B26) -> Sing Song Black tee | B107: =IF($A107="","",Setup!C26) -> Apparel | C107: =IF($A107="","",Setup!D26) -> 550 | D107: =IF($A107="","",Setup!E26) -> 0.3 | E107: =IF(OR($A107="",$Q$104=""),"",$Q$104*D107) | F107: =IF(OR($A107="",C107=0,E107=""),"",ROUNDUP(E107/C107,0)) | G107: =IF(OR($A107="",F107=""),"",ROUND(F107*Setup!F26,0)) | H107: =IF(OR($A107="",F107=""),"",ROUND(F107*Setup!G26,0)) | I107: =IF(OR($A107="",F107=""),"",ROUND(F107*Setup!H26,0)) | J107: =IF(OR($A107="",F107=""),"",ROUND(F107*Setup!I26,0)) | K107: =IF(OR($A107="",F107=""),"",ROUND(F107*Setup!J26,0)) | L107: =IF(OR($A107="",F107=""),"",ROUND(F107*Setup!K26,0)) | M107: =IF(OR($A107="",F107=""),"",ROUND(F107*Setup!L26,0)) | N107: =IF(OR($A107="",F107=""),"",F107*C107) | O107: =IF(OR($A107="",N107=""),"",N107*Setup!$B$6/(1+Setup!$B$6)) | P107: =IF(OR($A107="",N107=""),"",N107-O107) | Q107: =IF($A107="","",Setup!S26) -> 169 | R107: =IF(OR($A107="",F107="",Q107=""),"",F107*Q107) | S107: =IF(OR($A107="",P107="",R107=""),"",P107-R107)
A108: =IF(Setup!B27="","",Setup!B27) -> Kingston Black Tee | B108: =IF($A108="","",Setup!C27) -> Apparel | C108: =IF($A108="","",Setup!D27) -> 550 | D108: =IF($A108="","",Setup!E27) -> 0.2 | E108: =IF(OR($A108="",$Q$104=""),"",$Q$104*D108) | F108: =IF(OR($A108="",C108=0,E108=""),"",ROUNDUP(E108/C108,0)) | G108: =IF(OR($A108="",F108=""),"",ROUND(F108*Setup!F27,0)) | H108: =IF(OR($A108="",F108=""),"",ROUND(F108*Setup!G27,0)) | I108: =IF(OR($A108="",F108=""),"",ROUND(F108*Setup!H27,0)) | J108: =IF(OR($A108="",F108=""),"",ROUND(F108*Setup!I27,0)) | K108: =IF(OR($A108="",F108=""),"",ROUND(F108*Setup!J27,0)) | L108: =IF(OR($A108="",F108=""),"",ROUND(F108*Setup!K27,0)) | M108: =IF(OR($A108="",F108=""),"",ROUND(F108*Setup!L27,0)) | N108: =IF(OR($A108="",F108=""),"",F108*C108) | O108: =IF(OR($A108="",N108=""),"",N108*Setup!$B$6/(1+Setup!$B$6)) | P108: =IF(OR($A108="",N108=""),"",N108-O108) | Q108: =IF($A108="","",Setup!S27) -> 169 | R108: =IF(OR($A108="",F108="",Q108=""),"",F108*Q108) | S108: =IF(OR($A108="",P108="",R108=""),"",P108-R108)
A109: =IF(Setup!B28="","",Setup!B28) -> Red Red Wine White tee | B109: =IF($A109="","",Setup!C28) -> Apparel | C109: =IF($A109="","",Setup!D28) -> 550 | D109: =IF($A109="","",Setup!E28) -> 0.3 | E109: =IF(OR($A109="",$Q$104=""),"",$Q$104*D109) | F109: =IF(OR($A109="",C109=0,E109=""),"",ROUNDUP(E109/C109,0)) | G109: =IF(OR($A109="",F109=""),"",ROUND(F109*Setup!F28,0)) | H109: =IF(OR($A109="",F109=""),"",ROUND(F109*Setup!G28,0)) | I109: =IF(OR($A109="",F109=""),"",ROUND(F109*Setup!H28,0)) | J109: =IF(OR($A109="",F109=""),"",ROUND(F109*Setup!I28,0)) | K109: =IF(OR($A109="",F109=""),"",ROUND(F109*Setup!J28,0)) | L109: =IF(OR($A109="",F109=""),"",ROUND(F109*Setup!K28,0)) | M109: =IF(OR($A109="",F109=""),"",ROUND(F109*Setup!L28,0)) | N109: =IF(OR($A109="",F109=""),"",F109*C109) | O109: =IF(OR($A109="",N109=""),"",N109*Setup!$B$6/(1+Setup!$B$6)) | P109: =IF(OR($A109="",N109=""),"",N109-O109) | Q109: =IF($A109="","",Setup!S28) -> 162 | R109: =IF(OR($A109="",F109="",Q109=""),"",F109*Q109) | S109: =IF(OR($A109="",P109="",R109=""),"",P109-R109)
A110: =IF(Setup!B29="","",Setup!B29) -> Cap | B110: =IF($A110="","",Setup!C29) -> Accessory | C110: =IF($A110="","",Setup!D29) -> 350 | D110: =IF($A110="","",Setup!E29) -> 0.13 | E110: =IF(OR($A110="",$Q$104=""),"",$Q$104*D110) | F110: =IF(OR($A110="",C110=0,E110=""),"",ROUNDUP(E110/C110,0)) | G110: =IF(OR($A110="",F110=""),"",ROUND(F110*Setup!F29,0)) | H110: =IF(OR($A110="",F110=""),"",ROUND(F110*Setup!G29,0)) | I110: =IF(OR($A110="",F110=""),"",ROUND(F110*Setup!H29,0)) | J110: =IF(OR($A110="",F110=""),"",ROUND(F110*Setup!I29,0)) | K110: =IF(OR($A110="",F110=""),"",ROUND(F110*Setup!J29,0)) | L110: =IF(OR($A110="",F110=""),"",ROUND(F110*Setup!K29,0)) | M110: =IF(OR($A110="",F110=""),"",ROUND(F110*Setup!L29,0)) | N110: =IF(OR($A110="",F110=""),"",F110*C110) | O110: =IF(OR($A110="",N110=""),"",N110*Setup!$B$6/(1+Setup!$B$6)) | P110: =IF(OR($A110="",N110=""),"",N110-O110) | Q110: =IF($A110="","",Setup!S29) -> 96 | R110: =IF(OR($A110="",F110="",Q110=""),"",F110*Q110) | S110: =IF(OR($A110="",P110="",R110=""),"",P110-R110)
A111: =IF(Setup!B30="","",Setup!B30) -> Tote | B111: =IF($A111="","",Setup!C30) -> Accessory | C111: =IF($A111="","",Setup!D30) -> 100 | D111: =IF($A111="","",Setup!E30) -> 0.07 | E111: =IF(OR($A111="",$Q$104=""),"",$Q$104*D111) | F111: =IF(OR($A111="",C111=0,E111=""),"",ROUNDUP(E111/C111,0)) | G111: =IF(OR($A111="",F111=""),"",ROUND(F111*Setup!F30,0)) | H111: =IF(OR($A111="",F111=""),"",ROUND(F111*Setup!G30,0)) | I111: =IF(OR($A111="",F111=""),"",ROUND(F111*Setup!H30,0)) | J111: =IF(OR($A111="",F111=""),"",ROUND(F111*Setup!I30,0)) | K111: =IF(OR($A111="",F111=""),"",ROUND(F111*Setup!J30,0)) | L111: =IF(OR($A111="",F111=""),"",ROUND(F111*Setup!K30,0)) | M111: =IF(OR($A111="",F111=""),"",ROUND(F111*Setup!L30,0)) | N111: =IF(OR($A111="",F111=""),"",F111*C111) | O111: =IF(OR($A111="",N111=""),"",N111*Setup!$B$6/(1+Setup!$B$6)) | P111: =IF(OR($A111="",N111=""),"",N111-O111) | Q111: =IF($A111="","",Setup!S30) -> 50 | R111: =IF(OR($A111="",F111="",Q111=""),"",F111*Q111) | S111: =IF(OR($A111="",P111="",R111=""),"",P111-R111)
A112: =IF(Setup!B31="","",Setup!B31) | B112: =IF($A112="","",Setup!C31) | C112: =IF($A112="","",Setup!D31) | D112: =IF($A112="","",Setup!E31) | E112: =IF(OR($A112="",$Q$104=""),"",$Q$104*D112) | F112: =IF(OR($A112="",C112=0,E112=""),"",ROUNDUP(E112/C112,0)) | G112: =IF(OR($A112="",F112=""),"",ROUND(F112*Setup!F31,0)) | H112: =IF(OR($A112="",F112=""),"",ROUND(F112*Setup!G31,0)) | I112: =IF(OR($A112="",F112=""),"",ROUND(F112*Setup!H31,0)) | J112: =IF(OR($A112="",F112=""),"",ROUND(F112*Setup!I31,0)) | K112: =IF(OR($A112="",F112=""),"",ROUND(F112*Setup!J31,0)) | L112: =IF(OR($A112="",F112=""),"",ROUND(F112*Setup!K31,0)) | M112: =IF(OR($A112="",F112=""),"",ROUND(F112*Setup!L31,0)) | N112: =IF(OR($A112="",F112=""),"",F112*C112) | O112: =IF(OR($A112="",N112=""),"",N112*Setup!$B$6/(1+Setup!$B$6)) | P112: =IF(OR($A112="",N112=""),"",N112-O112) | Q112: =IF($A112="","",Setup!S31) | R112: =IF(OR($A112="",F112="",Q112=""),"",F112*Q112) | S112: =IF(OR($A112="",P112="",R112=""),"",P112-R112)
A113: =IF(Setup!B32="","",Setup!B32) | B113: =IF($A113="","",Setup!C32) | C113: =IF($A113="","",Setup!D32) | D113: =IF($A113="","",Setup!E32) | E113: =IF(OR($A113="",$Q$104=""),"",$Q$104*D113) | F113: =IF(OR($A113="",C113=0,E113=""),"",ROUNDUP(E113/C113,0)) | G113: =IF(OR($A113="",F113=""),"",ROUND(F113*Setup!F32,0)) | H113: =IF(OR($A113="",F113=""),"",ROUND(F113*Setup!G32,0)) | I113: =IF(OR($A113="",F113=""),"",ROUND(F113*Setup!H32,0)) | J113: =IF(OR($A113="",F113=""),"",ROUND(F113*Setup!I32,0)) | K113: =IF(OR($A113="",F113=""),"",ROUND(F113*Setup!J32,0)) | L113: =IF(OR($A113="",F113=""),"",ROUND(F113*Setup!K32,0)) | M113: =IF(OR($A113="",F113=""),"",ROUND(F113*Setup!L32,0)) | N113: =IF(OR($A113="",F113=""),"",F113*C113) | O113: =IF(OR($A113="",N113=""),"",N113*Setup!$B$6/(1+Setup!$B$6)) | P113: =IF(OR($A113="",N113=""),"",N113-O113) | Q113: =IF($A113="","",Setup!S32) | R113: =IF(OR($A113="",F113="",Q113=""),"",F113*Q113) | S113: =IF(OR($A113="",P113="",R113=""),"",P113-R113)
A114: =IF(Setup!B33="","",Setup!B33) | B114: =IF($A114="","",Setup!C33) | C114: =IF($A114="","",Setup!D33) | D114: =IF($A114="","",Setup!E33) | E114: =IF(OR($A114="",$Q$104=""),"",$Q$104*D114) | F114: =IF(OR($A114="",C114=0,E114=""),"",ROUNDUP(E114/C114,0)) | G114: =IF(OR($A114="",F114=""),"",ROUND(F114*Setup!F33,0)) | H114: =IF(OR($A114="",F114=""),"",ROUND(F114*Setup!G33,0)) | I114: =IF(OR($A114="",F114=""),"",ROUND(F114*Setup!H33,0)) | J114: =IF(OR($A114="",F114=""),"",ROUND(F114*Setup!I33,0)) | K114: =IF(OR($A114="",F114=""),"",ROUND(F114*Setup!J33,0)) | L114: =IF(OR($A114="",F114=""),"",ROUND(F114*Setup!K33,0)) | M114: =IF(OR($A114="",F114=""),"",ROUND(F114*Setup!L33,0)) | N114: =IF(OR($A114="",F114=""),"",F114*C114) | O114: =IF(OR($A114="",N114=""),"",N114*Setup!$B$6/(1+Setup!$B$6)) | P114: =IF(OR($A114="",N114=""),"",N114-O114) | Q114: =IF($A114="","",Setup!S33) | R114: =IF(OR($A114="",F114="",Q114=""),"",F114*Q114) | S114: =IF(OR($A114="",P114="",R114=""),"",P114-R114)
A115: =IF(Setup!B34="","",Setup!B34) | B115: =IF($A115="","",Setup!C34) | C115: =IF($A115="","",Setup!D34) | D115: =IF($A115="","",Setup!E34) | E115: =IF(OR($A115="",$Q$104=""),"",$Q$104*D115) | F115: =IF(OR($A115="",C115=0,E115=""),"",ROUNDUP(E115/C115,0)) | G115: =IF(OR($A115="",F115=""),"",ROUND(F115*Setup!F34,0)) | H115: =IF(OR($A115="",F115=""),"",ROUND(F115*Setup!G34,0)) | I115: =IF(OR($A115="",F115=""),"",ROUND(F115*Setup!H34,0)) | J115: =IF(OR($A115="",F115=""),"",ROUND(F115*Setup!I34,0)) | K115: =IF(OR($A115="",F115=""),"",ROUND(F115*Setup!J34,0)) | L115: =IF(OR($A115="",F115=""),"",ROUND(F115*Setup!K34,0)) | M115: =IF(OR($A115="",F115=""),"",ROUND(F115*Setup!L34,0)) | N115: =IF(OR($A115="",F115=""),"",F115*C115) | O115: =IF(OR($A115="",N115=""),"",N115*Setup!$B$6/(1+Setup!$B$6)) | P115: =IF(OR($A115="",N115=""),"",N115-O115) | Q115: =IF($A115="","",Setup!S34) | R115: =IF(OR($A115="",F115="",Q115=""),"",F115*Q115) | S115: =IF(OR($A115="",P115="",R115=""),"",P115-R115)
A116: =IF(Setup!B35="","",Setup!B35) | B116: =IF($A116="","",Setup!C35) | C116: =IF($A116="","",Setup!D35) | D116: =IF($A116="","",Setup!E35) | E116: =IF(OR($A116="",$Q$104=""),"",$Q$104*D116) | F116: =IF(OR($A116="",C116=0,E116=""),"",ROUNDUP(E116/C116,0)) | G116: =IF(OR($A116="",F116=""),"",ROUND(F116*Setup!F35,0)) | H116: =IF(OR($A116="",F116=""),"",ROUND(F116*Setup!G35,0)) | I116: =IF(OR($A116="",F116=""),"",ROUND(F116*Setup!H35,0)) | J116: =IF(OR($A116="",F116=""),"",ROUND(F116*Setup!I35,0)) | K116: =IF(OR($A116="",F116=""),"",ROUND(F116*Setup!J35,0)) | L116: =IF(OR($A116="",F116=""),"",ROUND(F116*Setup!K35,0)) | M116: =IF(OR($A116="",F116=""),"",ROUND(F116*Setup!L35,0)) | N116: =IF(OR($A116="",F116=""),"",F116*C116) | O116: =IF(OR($A116="",N116=""),"",N116*Setup!$B$6/(1+Setup!$B$6)) | P116: =IF(OR($A116="",N116=""),"",N116-O116) | Q116: =IF($A116="","",Setup!S35) | R116: =IF(OR($A116="",F116="",Q116=""),"",F116*Q116) | S116: =IF(OR($A116="",P116="",R116=""),"",P116-R116)
A117: =IF(Setup!B36="","",Setup!B36) | B117: =IF($A117="","",Setup!C36) | C117: =IF($A117="","",Setup!D36) | D117: =IF($A117="","",Setup!E36) | E117: =IF(OR($A117="",$Q$104=""),"",$Q$104*D117) | F117: =IF(OR($A117="",C117=0,E117=""),"",ROUNDUP(E117/C117,0)) | G117: =IF(OR($A117="",F117=""),"",ROUND(F117*Setup!F36,0)) | H117: =IF(OR($A117="",F117=""),"",ROUND(F117*Setup!G36,0)) | I117: =IF(OR($A117="",F117=""),"",ROUND(F117*Setup!H36,0)) | J117: =IF(OR($A117="",F117=""),"",ROUND(F117*Setup!I36,0)) | K117: =IF(OR($A117="",F117=""),"",ROUND(F117*Setup!J36,0)) | L117: =IF(OR($A117="",F117=""),"",ROUND(F117*Setup!K36,0)) | M117: =IF(OR($A117="",F117=""),"",ROUND(F117*Setup!L36,0)) | N117: =IF(OR($A117="",F117=""),"",F117*C117) | O117: =IF(OR($A117="",N117=""),"",N117*Setup!$B$6/(1+Setup!$B$6)) | P117: =IF(OR($A117="",N117=""),"",N117-O117) | Q117: =IF($A117="","",Setup!S36) | R117: =IF(OR($A117="",F117="",Q117=""),"",F117*Q117) | S117: =IF(OR($A117="",P117="",R117=""),"",P117-R117)
A118: =IF(Setup!B37="","",Setup!B37) | B118: =IF($A118="","",Setup!C37) | C118: =IF($A118="","",Setup!D37) | D118: =IF($A118="","",Setup!E37) | E118: =IF(OR($A118="",$Q$104=""),"",$Q$104*D118) | F118: =IF(OR($A118="",C118=0,E118=""),"",ROUNDUP(E118/C118,0)) | G118: =IF(OR($A118="",F118=""),"",ROUND(F118*Setup!F37,0)) | H118: =IF(OR($A118="",F118=""),"",ROUND(F118*Setup!G37,0)) | I118: =IF(OR($A118="",F118=""),"",ROUND(F118*Setup!H37,0)) | J118: =IF(OR($A118="",F118=""),"",ROUND(F118*Setup!I37,0)) | K118: =IF(OR($A118="",F118=""),"",ROUND(F118*Setup!J37,0)) | L118: =IF(OR($A118="",F118=""),"",ROUND(F118*Setup!K37,0)) | M118: =IF(OR($A118="",F118=""),"",ROUND(F118*Setup!L37,0)) | N118: =IF(OR($A118="",F118=""),"",F118*C118) | O118: =IF(OR($A118="",N118=""),"",N118*Setup!$B$6/(1+Setup!$B$6)) | P118: =IF(OR($A118="",N118=""),"",N118-O118) | Q118: =IF($A118="","",Setup!S37) | R118: =IF(OR($A118="",F118="",Q118=""),"",F118*Q118) | S118: =IF(OR($A118="",P118="",R118=""),"",P118-R118)
... A121: =IF(Setup!B40="","",Setup!B40) | B121: =IF($A121="","",Setup!C40) | C121: =IF($A121="","",Setup!D40) | D121: =IF($A121="","",Setup!E40) | E121: =IF(OR($A121="",$Q$104=""),"",$Q$104*D121) | F121: =IF(OR($A121="",C121=0,E121=""),"",ROUNDUP(E121/C121,0)) | G121: =IF(OR($A121="",F121=""),"",ROUND(F121*Setup!F40,0)) | H121: =IF(OR($A121="",F121=""),"",ROUND(F121*Setup!G40,0)) | I121: =IF(OR($A121="",F121=""),"",ROUND(F121*Setup!H40,0)) | J121: =IF(OR($A121="",F121=""),"",ROUND(F121*Setup!I40,0)) | K121: =IF(OR($A121="",F121=""),"",ROUND(F121*Setup!J40,0)) | L121: =IF(OR($A121="",F121=""),"",ROUND(F121*Setup!K40,0)) | M121: =IF(OR($A121="",F121=""),"",ROUND(F121*Setup!L40,0)) | N121: =IF(OR($A121="",F121=""),"",F121*C121) | O121: =IF(OR($A121="",N121=""),"",N121*Setup!$B$6/(1+Setup!$B$6)) | P121: =IF(OR($A121="",N121=""),"",N121-O121) | Q121: =IF($A121="","",Setup!S40) | R121: =IF(OR($A121="",F121="",Q121=""),"",F121*Q121) | S121: =IF(OR($A121="",P121="",R121=""),"",P121-R121)
...

Sheet P&L Summary
A1: =Setup!B3&" - "&Setup!B4&" | P&L SUMMARY" -> UB40 feat. Ali Campbell - UB40 SA Tour 2026 | P&L SUMMARY
A2: ="Exchange Rate: "&TEXT(Setup!H6,"#,##0.00")&" "&Setup!B5&" per 1 "&Setup!H5 -> Exchange Rate: 23,0.00 R per 1 GBP
A3: COST CATEGORY | B3: =IF(Setup!C9="","Event 1",Setup!C9) -> Cape Town | C3: =IF(Setup!C10="","Event 2",Setup!C10) -> Durban | D3: =IF(Setup!C11="","Event 3",Setup!C11) -> Pretoria | E3: =IF(Setup!C12="","Event 4",Setup!C12) -> Pretoria | F3: =IF(Setup!C13="","Event 5",Setup!C13) -> Event 5 | G3: =IF(Setup!C14="","Event 6",Setup!C14) -> Event 6 | H3: =IF(Setup!C15="","Event 7",Setup!C15) -> Event 7 | I3: =IF(Setup!C16="","Event 8",Setup!C16) -> Event 8 | J3: =IF(Setup!C18="","Event 9",Setup!C18) -> Event 9 | K3: =IF(Setup!C19="","Event 10",Setup!C19) -> Event 10 | L3: TOUR TOTAL | M3: =Setup!H5&" TOTAL" -> GBP TOTAL
A4: REVENUE
A5: Gross Revenue (incl VAT) | B5: ='Sales per event'!N38 -> 158250 | C5: ='Sales per event'!N59 -> 157250 | D5: ='Sales per event'!N80 -> 381650 | E5: ='Sales per event'!N101 -> 192700 | F5: ='Sales per event'!N122 -> 0 | G5: ='Sales per event'!N143 -> 0 | H5: ='Sales per event'!N164 -> 0 | I5: ='Sales per event'!N185 -> 0 | J5: ='Sales per event'!N206 -> 0 | K5: ='Sales per event'!N227 -> 0 | L5: =SUM(B5,C5,D5,E5,F5,G5,H5,I5,J5,K5) -> 889850 | M5: =IFERROR(L5/Setup!$H$6,0) -> 38689.13
A6: Less: VAT | B6: ='Sales per event'!O38 -> 20641.304 | C6: ='Sales per event'!O59 -> 20510.87 | D6: ='Sales per event'!O80 -> 49780.435 | E6: ='Sales per event'!O101 -> 25134.783 | F6: ='Sales per event'!O122 -> 0 | G6: ='Sales per event'!O143 -> 0 | H6: ='Sales per event'!O164 -> 0 | I6: ='Sales per event'!O185 -> 0 | J6: ='Sales per event'!O206 -> 0 | K6: ='Sales per event'!O227 -> 0 | L6: =SUM(B6,C6,D6,E6,F6,G6,H6,I6,J6,K6) -> 116067.39 | M6: =IFERROR(L6/Setup!$H$6,0) -> 5046.4083
A7: Net Revenue (ex VAT) | B7: =B5-B6 -> 137608.7 | C7: =C5-C6 -> 136739.13 | D7: =D5-D6 -> 331869.57 | E7: =E5-E6 -> 167565.22 | F7: =F5-F6 -> 0 | G7: =G5-G6 -> 0 | H7: =H5-H6 -> 0 | I7: =I5-I6 -> 0 | ... K7: =K5-K6 -> 0 | L7: =SUM(B7,C7,D7,E7,F7,G7,H7,I7,J7,K7) -> 773782.61 | M7: =IFERROR(L7/Setup!$H$6,0) -> 33642.722
A9: COST OF GOODS SOLD
A10: Manufacturing Cost (COGS) | B10: ='Sales per event'!R38 -> 49482 | C10: ='Sales per event'!R59 -> 49167 | D10: ='Sales per event'!R80 -> 119321 | E10: ='Sales per event'!R101 -> 60247 | F10: ='Sales per event'!R122 -> 0 | G10: ='Sales per event'!R143 -> 0 | H10: ='Sales per event'!R164 -> 0 | I10: ='Sales per event'!R185 -> 0 | J10: ='Sales per event'!R206 -> 0 | K10: ='Sales per event'!R227 -> 0 | L10: =SUM(B10,C10,D10,E10,F10,G10,H10,I10,J10,K10) -> 278217 | M10: =IFERROR(L10/Setup!$H$6,0) -> 12096.391
A11: COGS as % of Net Revenue | B11: =IFERROR(B10/B7,0) -> 0.35958483 | C11: =IFERROR(C10/C7,0) -> 0.35956789 | D11: =IFERROR(D10/D7,0) -> 0.35954186 | E11: =IFERROR(E10/E7,0) -> 0.35954359 | F11: =IFERROR(F10/F7,0) -> 0 | G11: =IFERROR(G10/G7,0) -> 0 | H11: =IFERROR(H10/H7,0) -> 0 | I11: =IFERROR(I10/I7,0) -> 0 | ... L11: =IFERROR(L10/L7,0) -> 0.35955448 | M11: =IFERROR(L10/L7,0) -> 0.35955448
A13: GROSS PROFIT | B13: =B7-B10 -> 88126.696 | C13: =C7-C10 -> 87572.13 | D13: =D7-D10 -> 212548.57 | E13: =E7-E10 -> 107318.22 | F13: =F7-F10 -> 0 | G13: =G7-G10 -> 0 | H13: =H7-H10 -> 0 | I13: =I7-I10 -> 0 | ... K13: =K7-K10 -> 0 | L13: =SUM(B13,C13,D13,E13,F13,G13,H13,I13,J13,K13) -> 495565.61 | M13: =IFERROR(L13/Setup!$H$6,0) -> 21546.331
A14: Gross Margin % | B14: =IFERROR(B13/B7,0) -> 0.64041517 | C14: =IFERROR(C13/C7,0) -> 0.64043211 | D14: =IFERROR(D13/D7,0) -> 0.64045814 | E14: =IFERROR(E13/E7,0) -> 0.64045641 | F14: =IFERROR(F13/F7,0) -> 0 | G14: =IFERROR(G13/G7,0) -> 0 | H14: =IFERROR(H13/H7,0) -> 0 | I14: =IFERROR(I13/I7,0) -> 0 | ... L14: =IFERROR(L13/L7,0) -> 0.64044552 | M14: =IFERROR(L13/L7,0) -> 0.64044552
A16: OPERATING COSTS
A17: Flights & Accommodation | B17: =IF(Setup!J9="",0,Setup!J9) -> 0 | C17: =IF(Setup!J10="",0,Setup!J10) -> 0 | D17: =IF(Setup!J11="",0,Setup!J11) -> 0 | E17: =IF(Setup!J12="",0,Setup!J12) -> 0 | F17: =IF(Setup!J13="",0,Setup!J13) -> 0 | G17: =IF(Setup!J14="",0,Setup!J14) -> 0 | H17: =IF(Setup!J15="",0,Setup!J15) -> 0 | I17: =IF(Setup!J16="",0,Setup!J16) -> 0 | J17: =IF(Setup!J18="",0,Setup!J18) -> 0 | K17: =IF(Setup!J19="",0,Setup!J19) -> 0 | L17: =SUM(B17,C17,D17,E17,F17,G17,H17,I17,J17,K17) -> 0 | M17: =IFERROR(L17/Setup!$H$6,0) -> 0
A18: Other Costs | B18: =IF(Setup!K9="",0,Setup!K9) -> 0 | C18: =IF(Setup!K10="",0,Setup!K10) -> 0 | D18: =IF(Setup!K11="",0,Setup!K11) -> 0 | E18: =IF(Setup!K12="",0,Setup!K12) -> 0 | F18: =IF(Setup!K13="",0,Setup!K13) -> 0 | G18: =IF(Setup!K14="",0,Setup!K14) -> 0 | H18: =IF(Setup!K15="",0,Setup!K15) -> 0 | I18: =IF(Setup!K16="",0,Setup!K16) -> 0 | J18: =IF(Setup!K18="",0,Setup!K18) -> 0 | K18: =IF(Setup!K19="",0,Setup!K19) -> 0 | L18: =SUM(B18,C18,D18,E18,F18,G18,H18,I18,J18,K18) -> 0 | M18: =IFERROR(L18/Setup!$H$6,0) -> 0
A19: Sales Operations | B19: =IF(Setup!L9="",0,Setup!L9) -> 50000 | C19: =IF(Setup!L10="",0,Setup!L10) -> 50000 | D19: =IF(Setup!L11="",0,Setup!L11) -> 75000 | E19: =IF(Setup!L12="",0,Setup!L12) -> 60000 | F19: =IF(Setup!L13="",0,Setup!L13) -> 0 | G19: =IF(Setup!L14="",0,Setup!L14) -> 0 | H19: =IF(Setup!L15="",0,Setup!L15) -> 0 | I19: =IF(Setup!L16="",0,Setup!L16) -> 0 | J19: =IF(Setup!L18="",0,Setup!L18) -> 0 | K19: =IF(Setup!L19="",0,Setup!L19) -> 0 | L19: =SUM(B19,C19,D19,E19,F19,G19,H19,I19,J19,K19) -> 235000 | M19: =IFERROR(L19/Setup!$H$6,0) -> 10217.391
A20: Credit Card Fees (on gross incl VAT) | B20: =IFERROR(B5*Setup!M9,0) -> 5064 | C20: =IFERROR(C5*Setup!M10,0) -> 5032 | D20: =IFERROR(D5*Setup!M11,0) -> 12212.8 | E20: =IFERROR(E5*Setup!M12,0) -> 6166.4 | F20: =IFERROR(F5*Setup!M13,0) -> 0 | G20: =IFERROR(G5*Setup!M14,0) -> 0 | H20: =IFERROR(H5*Setup!M15,0) -> 0 | I20: =IFERROR(I5*Setup!M16,0) -> 0 | J20: =IFERROR(J5*Setup!M18,0) -> 0 | K20: =IFERROR(K5*Setup!M19,0) -> 0 | L20: =SUM(B20,C20,D20,E20,F20,G20,H20,I20,J20,K20) -> 28475.2 | M20: =IFERROR(L20/Setup!$H$6,0) -> 1238.0522
A22: TOTAL OPERATING COSTS | B22: =SUM(B17:B20) -> 55064 | C22: =SUM(C17:C20) -> 55032 | D22: =SUM(D17:D20) -> 87212.8 | E22: =SUM(E17:E20) -> 66166.4 | F22: =SUM(F17:F20) -> 0 | G22: =SUM(G17:G20) -> 0 | H22: =SUM(H17:H20) -> 0 | I22: =SUM(I17:I20) -> 0 | ... K22: =SUM(K17:K20) -> 0 | L22: =SUM(B22,C22,D22,E22,F22,G22,H22,I22,J22,K22) -> 263475.2 | M22: =IFERROR(L22/Setup!$H$6,0) -> 11455.443
A23: Operating Costs as % of Net Revenue | B23: =IFERROR(B22/B7,0) -> 0.40014913 | C23: =IFERROR(C22/C7,0) -> 0.40245978 | D23: =IFERROR(D22/D7,0) -> 0.2627924 | E23: =IFERROR(E22/E7,0) -> 0.39486954 | F23: =IFERROR(F22/F7,0) -> 0 | G23: =IFERROR(G22/G7,0) -> 0 | H23: =IFERROR(H22/H7,0) -> 0 | I23: =IFERROR(I22/I7,0) -> 0 | ... L23: =IFERROR(L22/L7,0) -> 0.34050287 | M23: =IFERROR(L22/L7,0) -> 0.34050287
A25: NET PROFIT | B25: =B13-B22 -> 33062.696 | C25: =C13-C22 -> 32540.13 | D25: =D13-D22 -> 125335.77 | E25: =E13-E22 -> 41151.817 | F25: =F13-F22 -> 0 | G25: =G13-G22 -> 0 | H25: =H13-H22 -> 0 | I25: =I13-I22 -> 0 | ... K25: =K13-K22 -> 0 | L25: =SUM(B25,C25,D25,E25,F25,G25,H25,I25,J25,K25) -> 232090.41 | M25: =IFERROR(L25/Setup!$H$6,0) -> 10090.887
A26: Net Margin % | B26: =IFERROR(B25/B7,0) -> 0.24026603 | C26: =IFERROR(C25/C7,0) -> 0.23797234 | D26: =IFERROR(D25/D7,0) -> 0.37766574 | E26: =IFERROR(E25/E7,0) -> 0.24558687 | F26: =IFERROR(F25/F7,0) -> 0 | G26: =IFERROR(G25/G7,0) -> 0 | H26: =IFERROR(H25/H7,0) -> 0 | I26: =IFERROR(I25/I7,0) -> 0 | ... L26: =IFERROR(L25/L7,0) -> 0.29994265 | M26: =IFERROR(L25/L7,0) -> 0.29994265
A28: PROFIT SHARE
A29: =Setup!L5&" Share ("&TEXT(Setup!N5,"0%")&")" -> Artist Share (70%) | B29: =B25*Setup!$N$5 -> 23143.887 | C29: =C25*Setup!$N$5 -> 22778.091 | D29: =D25*Setup!$N$5 -> 87735.036 | E29: =E25*Setup!$N$5 -> 28806.272 | F29: =F25*Setup!$N$5 -> 0 | G29: =G25*Setup!$N$5 -> 0 | H29: =H25*Setup!$N$5 -> 0 | I29: =I25*Setup!$N$5 -> 0 | ... K29: =K25*Setup!$N$5 -> 0 | L29: =SUM(B29,C29,D29,E29,F29,G29,H29,I29,J29,K29) -> 162463.29 | M29: =IFERROR(L29/Setup!$H$6,0) -> 7063.6211
A30: =Setup!L6&" Share ("&TEXT(Setup!N6,"0%")&")" -> Promoter Share (30%) | B30: =B25*Setup!$N$6 -> 9918.8087 | C30: =C25*Setup!$N$6 -> 9762.0391 | D30: =D25*Setup!$N$6 -> 37600.73 | E30: =E25*Setup!$N$6 -> 12345.545 | F30: =F25*Setup!$N$6 -> 0 | G30: =G25*Setup!$N$6 -> 0 | H30: =H25*Setup!$N$6 -> 0 | I30: =I25*Setup!$N$6 -> 0 | ... K30: =K25*Setup!$N$6 -> 0 | L30: =SUM(B30,C30,D30,E30,F30,G30,H30,I30,J30,K30) -> 69627.123 | M30: =IFERROR(L30/Setup!$H$6,0) -> 3027.2662
A32: TOTAL ALL-IN COSTS | B32: =B10+B22 -> 104546 | C32: =C10+C22 -> 104199 | D32: =D10+D22 -> 206533.8 | E32: =E10+E22 -> 126413.4 | F32: =F10+F22 -> 0 | G32: =G10+G22 -> 0 | H32: =H10+H22 -> 0 | I32: =I10+I22 -> 0 | ... K32: =K10+K22 -> 0 | L32: =SUM(B32,C32,D32,E32,F32,G32,H32,I32,J32,K32) -> 541692.2 | M32: =IFERROR(L32/Setup!$H$6,0) -> 23551.835
A33: All-in Cost as % of Net Revenue | B33: =IFERROR(B32/B7,0) -> 0.75973397 | C33: =IFERROR(C32/C7,0) -> 0.76202766 | D33: =IFERROR(D32/D7,0) -> 0.62233426 | E33: =IFERROR(E32/E7,0) -> 0.75441313 | F33: =IFERROR(F32/F7,0) -> 0 | G33: =IFERROR(G32/G7,0) -> 0 | H33: =IFERROR(H32/H7,0) -> 0 | I33: =IFERROR(I32/I7,0) -> 0 | ... L33: =IFERROR(L32/L7,0) -> 0.70005735 | M33: =IFERROR(L32/L7,0) -> 0.70005735
A36: KEY TOUR METRICS
A37: Total Live Events | B37: =COUNTA(Setup!C9:C16) -> 4
A38: Total Online Events | B38: =COUNTA(Setup!C18:C19) -> 0
A39: Total Est. Attendance | B39: =SUM(Setup!F9:F16)+SUM(Setup!F18:F19) -> 24404
A40: Total Merch Stalls | B40: =SUM(Setup!G9:G16)+SUM(Setup!G18:G19) -> 8
A41: Avg Spend/Head (incl VAT) | B41: =IFERROR(AVERAGEIF(Setup!H9:H16,"<>"),0) -> 35
A42: Total Gross Target (incl VAT) | B42: =SUM(Setup!I9:I16)+SUM(Setup!I18:I19) -> 886370
A43: VAT Rate | B43: =Setup!B6 -> 0.15
A44: Total Products | B44: =COUNTA(Setup!B26:B40) -> 5
